Workbook
Name IQ_CH: 110000
Name IQ_CQ: 5000
Name IQ_CY: 10000
Name IQ_DAILY: 500000
Name IQ_FH: 100000
Name IQ_FQ: 500
Name IQ_FY: 1000
Name IQ_LTM: 2000
Name IQ_MONTH: 15000
Name IQ_NTM: 6000
Name IQ_WEEK: 50000
Name IQ_YTD: 3000

Sheet Input Sheet
B3: Please provide the below inputs
B5: Name of the company | C5: Eicher Motors
B7: WACC Inputs
B8: Country | C8: India
B9: Local Currency 10Y Government Bond Yield | C9: 0.0654
B10: =C8&"'s" &" Moodys Sovereign Rating" -> India's Moodys Sovereign Rating | C10: =VLOOKUP(C8,'Damodaran data'!B3:D160,3,FALSE) -> Baa3
B11: Credit default spread as per Dr Damodaran | C11: =VLOOKUP(C8,'Damodaran data'!B3:E160,4,FALSE) -> 0.021609858
B12: Implied US Equity Risk Premium | C12: 0.0373
B13: Asset Beta | C13: 0.72
B14: Asset Beta Variation (+/-) | C14: 0.05
B15: Debt to Equity | C15: ='Assumptions Working'!J816 -> 0.012512391
B16: Debt to Capital (Gearing) | C16: ='Assumptions Working'!J817 -> 0.012357765
B17: Marginal Tax Rate | C17: 0.2512
B18: Company Credit Rating Available? | C18: Yes
B19: Company is Large Firm or Small Firm? | C19: L | F19: L | G19: Yes
B20: Provide Credit Rating | C20: Aaa/AAA | F20: S | G20: No
B21: Interest Coverage Ratio | C21: ='3StatementModel'!H30/'3StatementModel'!H34 -> 73.292234
B22: ICR Based Corporate Default Spread | C22: =IF(C19="L",VLOOKUP(C21,'Damodaran data'!J6:M21,4,TRUE),VLOOKUP('Input Sheet'!C21,'Damodaran data'!P6:S21,4,TRUE)) -> 0.0045
B23: Small Size Premium | C23: 0
B24: Asset Specific Risk Premium | C24: 0

Sheet WACC
B2: ='Input Sheet'!C5 -> Eicher Motors
B3: Weighted Average Cost of Capital
B5: Particulars | D5: Low | E5: Mid | F5: High | H5: Risk Free Rate
B6: Risk Free Rate | D6: ='Input Sheet'!C9-'Input Sheet'!C11 -> 0.043790142 | E6: =D6 -> 0.043790142 | F6: =E6 -> 0.043790142 | H6: ="We have considered "&TEXT(E6,"0.00%")&" as the risk free rate in estimation of cost of equity of "&TEXT(E11,"0.00%")&". The risk free rate of India is calculated by considering local currency 10 years government bond yield adjusted for default spread of India." -> We have considered 4.38% as the risk free rate in estimation of cost of equity of 8.66%. The risk free rate of India is calculated by considering local currency 10 years government bond yield adjusted for default spread of India.
B7: Equity Risk Premium | D7: ='Input Sheet'!C12+'Input Sheet'!C11 -> 0.058909858 | E7: =D7 -> 0.058909858 | F7: =E7 -> 0.058909858
B8: Asset Beta | D8: =E8-'Input Sheet'!C14 -> 0.67 | E8: ='Input Sheet'!C13 -> 0.72 | F8: =E8+'Input Sheet'!C14 -> 0.77
B9: D/E Ratio | D9: ='Input Sheet'!$C$15 -> 0.012512391 | E9: ='Input Sheet'!$C$15 -> 0.012512391 | F9: ='Input Sheet'!$C$15 -> 0.012512391
B10: Equity Beta | D10: =D8*(1+(D9*(1-'Input Sheet'!$C$17))) -> 0.67627742 | E10: =E8*(1+(E9*(1-'Input Sheet'!$C$17))) -> 0.72674588 | F10: =F8*(1+(F9*(1-'Input Sheet'!$C$17))) -> 0.77721434 | H10: Asset Beta
B11: CAPM Cost of Equity | D11: =D6+D7*D10 -> 0.083629548 | E11: =E6+E7*E10 -> 0.086602639 | F11: =F6+F7*F10 -> 0.089575729 | H11: ="We have estimated an asset beta range of "&TEXT(D8,"0.00")&" to "&TEXT(F8,"0.00")& ", with a mid point of "&TEXT(E8,"0.00")& " based on observed median 5 year monthly asset beta of benchmark listed companies adjusted for blume effect." -> We have estimated an asset beta range of 0.67 to 0.77, with a mid point of 0.72 based on observed median 5 year monthly asset beta of benchmark listed companies adjusted for blume effect.
B13: Small Size Premium | D13: 0.025 | E13: =D13 -> 0.025 | F13: =E13 -> 0.025
B14: Asset Specific Premium | D14: ='Input Sheet'!C24 -> 0 | E14: =D14 -> 0 | F14: =E14 -> 0
B15: Modified Cost of Equity | D15: =D11+D13+D14 -> 0.10862955 | E15: =E11+E13+E14 -> 0.11160264 | F15: =F11+F13+F14 -> 0.11457573 | H15: Equity Risk Premium
H16: ="An ERP of "&TEXT(E7,"0.00%")&" has been adopted based on US implied equity risk premium, relative equity volatility of ICE BoFA Public Sector Issues Emerging Markets Index, S&P Emerging BMI Index and country risk premium of India." -> An ERP of 5.89% has been adopted based on US implied equity risk premium, relative equity volatility of ICE BoFA Public Sector Issues Emerging Markets Index, S&P Emerging BMI Index and country risk premium of India.
B17: Pre Tax Cost of Debt | D17: ='Input Sheet'!C9+(IF('Input Sheet'!C18="No",'Input Sheet'!C22,VLOOKUP('Input Sheet'!C20,'Damodaran data'!L7:M21,2,FALSE))) -> 0.0699 | E17: =D17 -> 0.0699 | F17: =E17 -> 0.0699
B18: Marginal Tax Rate | D18: ='Input Sheet'!C17 -> 0.2512 | E18: =D18 -> 0.2512 | F18: =E18 -> 0.2512
B19: Post Tax Cost of Debt | D19: =D17*(1-D18) -> 0.05234112 | E19: =E17*(1-E18) -> 0.05234112 | F19: =F17*(1-F18) -> 0.05234112
H20: Cost of Debt
B21: Capital Gearing (D/D+E) | D21: ='Input Sheet'!C16 -> 0.012357765 | E21: =D21 -> 0.012357765 | F21: =E21 -> 0.012357765 | H21: For the purpose of assessing the cost of debt, we have used country's risk free rate, country's default spread and corporate default spread based on company's debt rating and interest coverage ratio.
B22: Weighted Average Cost of Capital | D22: =(D19*D21)+(D15*(1-D21)) -> 0.10793395 | E22: =(E19*E21)+(E15*(1-E21)) -> 0.1108703 | F22: =(F19*F21)+(F15*(1-F21)) -> 0.11380665
B23: Weighted Average Cost of Capital (Rounded) | D23: =ROUNDUP(D22,2) -> 0.11 | E23: =ROUNDUP(E22,2) -> 0.12 | F23: =ROUNDUP(F22,2) -> 0.12
H25: Small Size Premium
B26: 1. Tax rate considered as Marginal Tax Rate of India. | H26: Emperically small sized assets have exceeded the returns as compared to large sized assets. We have used the study on size premium conducted by Incwert which is based on difference between actual returns and CAPM expected returns arranged in decile basis market capitalization of Indian Companies.
B27: 2. Asset Beta is considered as median of 5 years beta of comps adjusted for blume effect
B28: 3. Equity Beta = Asset Beta * (1+(1-Tax Rate%)*Debt/Equity)
V30: Note | W30: Realisitic Forecasting | Z30: 0.073 | AA30: 25000
H31: Asset Specific Premium | W31: Actual Forecasting | Z31: 0.11 | AA31: 25000
W32: Asset Specific Premium | Z32: =Z31-Z30 -> 0.037
Q39: Source - Incwert Size Premia Study
B50: =B2 -> Eicher Motors | M50: 0.2512
B51: Beta Analysis - 2 Years Weekly
B53: Company Name | D53: Ticker | E53: No. of Weekly Observations | F53: Market Cap (in Crs.) | G53: Asset Beta | H53: 2 years avg D/E | I53: Equity beta | J53: 2 years avg D/D+E | L53: Considered? | M53: Narrow Set
B54: Bajaj Auto | C54: 252955 | D54: NSE: BAJAJ-AUTO | E54: 104 | F54: 251827 | G54: =I54/(1+(H54*(1-$M$50))) -> 0.95424477 | H54: 0.162 | I54: 1.07 | J54: 0.13 | L54: Y | M54: =IF(L54="Y","TRUE","FALSE") -> TRUE
B55: TVS Motors | C55: 167428 | D55: NSE: TVSMOTOR | E55: 104 | F55: 164107 | G55: =I55/(1+(H55*(1-$M$50))) -> 0.24754 | H55: 3.52 | I55: 0.9 | J55: 0.77 | L55: Y | M55: =IF(L55="Y","TRUE","FALSE") -> TRUE
B56: Hero Motorcorp | C56: 108599 | D56: NSE: HEROMOTOCO | E56: 104 | F56: 120299 | G56: =I56/(1+(H56*(1-$M$50))) -> 1.2808185 | H56: 0.02 | I56: 1.3 | J56: 0.02 | L56: Y | M56: =IF(L56="Y","TRUE","FALSE") -> TRUE
B57: Mahindra & Mahindra Ltd | C57: 445718 | D57: NSE: M&M | E57: 104 | F57: 460522 | G57: =I57/(1+(H57*(1-$M$50))) -> 0.54844345 | H57: 1.27 | I57: 1.07 | J57: 0.55 | L57: Y | M57: =IF(L57="Y","TRUE","FALSE") -> TRUE
B58: Ashok Leyland Ltd | C58: 81882 | D58: NSE: ASHOKLEY | E58: 104 | F58: 85048 | G58: =I58/(1+(H58*(1-$M$50))) -> 0.14929476 | H58: 4.3 | I58: 0.63 | J58: 0.8 | L58: N | M58: =IF(L58="Y","TRUE","FALSE") -> FALSE
B60: Median - Broad Set | G60: =MEDIAN(G54:G58) -> 0.54844345 | H60: =MEDIAN(H54:H58) -> 1.27 | I60: =MEDIAN(I54:I58) -> 1.07 | J60: =MEDIAN(J54:J58) -> 0.55
B61: Average - Broad Set | G61: =AVERAGE(G54:G58) -> 0.63606829 | H61: =AVERAGE(H54:H58) -> 1.8544 | I61: =AVERAGE(I54:I58) -> 0.994 | J61: =AVERAGE(J54:J58) -> 0.454
B63: Median - Considered Set | G63: {=MEDIAN(IF($M$54:$M$58,G54:G58))} -> 0.75134411 | H63: {=MEDIAN(IF($M$54:$M$58,H54:H58))} -> 0.716 | I63: {=MEDIAN(IF($M$54:$M$58,I54:I58))} -> 1.07 | J63: {=MEDIAN(IF($M$54:$M$58,J54:J58))} -> 0.34
B64: Average - Considered Set | G64: {=AVERAGE(IF($M$54:$M$58,G54:G58))} -> 0.75776167 | H64: {=AVERAGE(IF($M$54:$M$58,H54:H58))} -> 1.243 | I64: {=AVERAGE(IF($M$54:$M$58,I54:I58))} -> 1.085 | J64: {=AVERAGE(IF($M$54:$M$58,J54:J58))} -> 0.3675
B71: =B50 -> Eicher Motors | M71: 0.2512
B72: Beta Analysis - 5 Years Monthly
B74: Company Name | D74: Ticker | E74: No. of Monthly Observations | F74: Market Cap (in Crs.) | G74: Asset Beta | H74: 5 years avg D/E | I74: Equity beta | J74: 5 years avg D/D+E | L74: Considered? | M74: Narrow Set
B75: Bajaj Auto | C75: 252955 | D75: NSE: BAJAJ-AUTO | E75: 60 | F75: 251827 | G75: =I75/(1+(H75*(1-$M$50))) -> 1.023994 | H75: 0.06 | I75: 1.07 | J75: 0.05 | L75: Y | M75: =IF(L75="Y","TRUE","FALSE") -> TRUE
B76: TVS Motors | C76: 167428 | D76: NSE: TVSMOTOR | E76: 60 | F76: 164107 | G76: =I76/(1+(H76*(1-$M$50))) -> 0.25817437 | H76: 3.32 | I76: 0.9 | J76: 0.76 | L76: Y | M76: =IF(L76="Y","TRUE","FALSE") -> TRUE
B77: Hero Motorcorp | C77: 108599 | D77: NSE: HEROMOTOCO | E77: 60 | F77: 120299 | G77: =I77/(1+(H77*(1-$M$50))) -> 1.2808185 | H77: 0.02 | I77: 1.3 | J77: 0.02 | L77: Y | M77: =IF(L77="Y","TRUE","FALSE") -> TRUE
B78: Mahindra & Mahindra Ltd | C78: 445718 | D78: NSE: M&M | E78: 60 | F78: 460522 | G78: =I78/(1+(H78*(1-$M$50))) -> 0.49868013 | H78: 1.53 | I78: 1.07 | J78: 0.59 | L78: Y | M78: =IF(L78="Y","TRUE","FALSE") -> TRUE
B79: Ashok Leyland Ltd | C79: 81882 | D79: NSE: ASHOKLEY | E79: 60 | F79: 85048 | G79: =I79/(1+(H79*(1-$M$50))) -> 0.16675278 | H79: 3.71 | I79: 0.63 | J79: 0.78 | L79: N | M79: =IF(L79="Y","TRUE","FALSE") -> FALSE
B81: Median - Broad Set | G81: =MEDIAN(G75:G79) -> 0.49868013 | H81: =MEDIAN(H75:H79) -> 1.53 | I81: =MEDIAN(I75:I79) -> 1.07 | J81: =MEDIAN(J75:J79) -> 0.59
B82: Average - Broad Set | G82: =AVERAGE(G75:G79) -> 0.64568395 | H82: =AVERAGE(H75:H79) -> 1.728 | I82: =AVERAGE(I75:I79) -> 0.994 | J82: =AVERAGE(J75:J79) -> 0.44
B84: Median - Considered Set | G84: {=MEDIAN(IF($M$54:$M$58,G75:G79))} -> 0.76133706 | H84: {=MEDIAN(IF($M$54:$M$58,H75:H79))} -> 0.795 | I84: {=MEDIAN(IF($M$54:$M$58,I75:I79))} -> 1.07 | J84: {=MEDIAN(IF($M$54:$M$58,J75:J79))} -> 0.32
B85: Average - Considered Set | G85: {=AVERAGE(IF($M$54:$M$58,G75:G79))} -> 0.76541674 | H85: {=AVERAGE(IF($M$54:$M$58,H75:H79))} -> 1.2325 | I85: {=AVERAGE(IF($M$54:$M$58,I75:I79))} -> 1.085 | J85: {=AVERAGE(IF($M$54:$M$58,J75:J79))} -> 0.355
B91: 2/3 - Beta + 1/3*Market Beta
B92: Blume Beta Analysis - 5 Years Monthly
B94: Company Name | D94: Ticker | E94: No. of Monthly Observations | F94: Market Cap (in Crs.) | G94: Asset Beta | H94: 5 years avg D/E | I94: Equity beta | J94: 5 years avg D/D+E | L94: Considered? | M94: Narrow Set
B95: Bajaj Auto | C95: 252955 | D95: NSE: BAJAJ-AUTO | E95: 60 | F95: 251827 | G95: =I95/(1+(H95*(1-$M$50))) -> 0.96399943 | H95: 0.06 | I95: =0.33+0.633*I75 -> 1.00731 | J95: 0.05 | L95: Y | M95: =IF(L95="Y","TRUE","FALSE") -> TRUE
B96: TVS Motors | C96: 167428 | D96: NSE: TVSMOTOR | E96: 60 | F96: 164107 | G96: =I96/(1+(H96*(1-$M$50))) -> 0.25808832 | H96: 3.32 | I96: =0.33+0.633*I76 -> 0.8997 | J96: 0.76 | L96: Y | M96: =IF(L96="Y","TRUE","FALSE") -> TRUE
B97: Hero Motorcorp | C97: 108599 | D97: NSE: HEROMOTOCO | E97: 60 | F97: 120299 | G97: =I97/(1+(H97*(1-$M$50))) -> 1.1358889 | H97: 0.02 | I97: =0.33+0.633*I77 -> 1.1529 | J97: 0.02 | L97: Y | M97: =IF(L97="Y","TRUE","FALSE") -> TRUE
B98: Mahindra & Mahindra Ltd | C98: 445718 | D98: NSE: M&M | E98: 60 | F98: 460522 | G98: =I98/(1+(H98*(1-$M$50))) -> 0.46946307 | H98: 1.53 | I98: =0.33+0.633*I78 -> 1.00731 | J98: 0.59 | L98: Y | M98: =IF(L98="Y","TRUE","FALSE") -> TRUE
B99: Ashok Leyland Ltd | C99: 81882 | D99: NSE: ASHOKLEY | E99: 60 | F99: 85048 | G99: =I99/(1+(H99*(1-$M$50))) -> 0.1929012 | H99: 3.71 | I99: =0.33+0.633*I79 -> 0.72879 | J99: 0.78 | L99: N | M99: =IF(L99="Y","TRUE","FALSE") -> FALSE
B101: Median - Broad Set | G101: =MEDIAN(G95:G99) -> 0.46946307 | H101: =MEDIAN(H95:H99) -> 1.53 | I101: =MEDIAN(I95:I99) -> 1.00731 | J101: =MEDIAN(J95:J99) -> 0.59
B102: Average - Broad Set | G102: =AVERAGE(G95:G99) -> 0.60406819 | H102: =AVERAGE(H95:H99) -> 1.728 | I102: =AVERAGE(I95:I99) -> 0.959202 | J102: =AVERAGE(J95:J99) -> 0.44
B104: Median - Considered Set | G104: {=MEDIAN(IF($M$54:$M$58,G95:G99))} -> 0.71673125 | H104: {=MEDIAN(IF($M$54:$M$58,H95:H99))} -> 0.795 | I104: {=MEDIAN(IF($M$54:$M$58,I95:I99))} -> 1.00731 | J104: {=MEDIAN(IF($M$54:$M$58,J95:J99))} -> 0.32
B105: Average - Considered Set | G105: {=AVERAGE(IF($M$54:$M$58,G95:G99))} -> 0.70685994 | H105: {=AVERAGE(IF($M$54:$M$58,H95:H99))} -> 1.2325 | I105: {=AVERAGE(IF($M$54:$M$58,I95:I99))} -> 1.016805 | J105: {=AVERAGE(IF($M$54:$M$58,J95:J99))} -> 0.355
B107: We are taking 0.72 as asset beta of automobile industry (2/3 wheelers)

Sheet Damodaran data
B2: Country Data | J2: Company Data
B3: Country | C3: Africa | D3: Moody's rating | E3: Rating-based Default Spread
B4: India | C4: Asia | D4: Baa3 | E4: 0.021609858 | J4: For large non-financial service firms | P4: For smaller and riskier firms
B5: United Kingdom | C5: Western Europe | D5: Aa3 | E5: 0.0058935977 | J5: If interest coverage ratio is | P5: If interest coverage ratio is
B6: United States | C6: North America | D6: Aa1 | E6: 0.0027 | J6: > | K6: ≤ to | L6: Rating is | M6: Spread is | P6: greater than | Q6: ≤ to | R6: Rating is | S6: Spread is
B7: Abu Dhabi | C7: Middle East | D7: Aa2 | E7: 0.004853551 | J7: -100000 | K7: 0.199999 | L7: D2/D | M7: 0.19 | P7: -100000 | Q7: 0.499999 | R7: D2/D | S7: 0.19
B8: Albania | C8: Eastern Europe & Russia | D8: Ba3 | E8: 0.035361586 | J8: 0.2 | K8: 0.649999 | L8: C2/C | M8: 0.155 | P8: 0.5 | Q8: 0.799999 | R8: C2/C | S8: 0.155
B9: Andorra (Principality of) | C9: Western Europe | D9: Baa1 | E9: 0.015716261 | J9: 0.65 | K9: 0.799999 | L9: Ca2/CC | M9: 0.101 | P9: 0.8 | Q9: 1.249999 | R9: Ca2/CC | S9: 0.101
B10: Angola | C10: Africa | D10: B3 | E10: 0.063905089 | J10: 0.8 | K10: 1.249999 | L10: Caa/CCC | M10: 0.0728 | P10: 1.25 | Q10: 1.499999 | R10: Caa/CCC | S10: 0.0728
B11: Argentina | C11: Central and South America | D11: Caa3 | E11: 0.098342189 | J11: 1.25 | K11: 1.499999 | L11: B3/B- | M11: 0.0442 | P11: 1.5 | Q11: 1.999999 | R11: B3/B- | S11: 0.0442
B12: Armenia | C12: Eastern Europe & Russia | D12: Ba3 | E12: 0.035361586 | J12: 1.5 | K12: 1.749999 | L12: B2/B | M12: 0.03 | P12: 2 | Q12: 2.499999 | R12: B2/B | S12: 0.03
B13: Aruba | C13: Caribbean | D13: Baa3 | E13: 0.021609858 | J13: 1.75 | K13: 1.999999 | L13: B1/B+ | M13: 0.0261 | P13: 2.5 | Q13: 2.999999 | R13: B1/B+ | S13: 0.0261
B14: Australia | C14: Australia & New Zealand | D14: Aaa | E14: 0 | J14: 2 | K14: 2.2499999 | L14: Ba2/BB | M14: 0.0183 | P14: 3 | Q14: 3.499999 | R14: Ba2/BB | S14: 0.0183
B15: Austria | C15: Western Europe | D15: Aa1 | E15: 0.0027 | J15: 2.25 | K15: 2.49999 | L15: Ba1/BB+ | M15: 0.0155 | P15: 3.5 | Q15: 3.9999999 | R15: Ba1/BB+ | S15: 0.0155
B16: Azerbaijan | C16: Eastern Europe & Russia | D16: Baa3 | E16: 0.021609858 | J16: 2.5 | K16: 2.999999 | L16: Baa2/BBB | M16: 0.012 | P16: 4 | Q16: 4.499999 | R16: Baa2/BBB | S16: 0.012
B17: Bahamas | C17: Caribbean | D17: B1 | E17: 0.044259763 | J17: 3 | K17: 4.249999 | L17: A3/A- | M17: 0.0095 | P17: 4.5 | Q17: 5.999999 | R17: A3/A- | S17: 0.0095
B18: Bahrain | C18: Middle East | D18: B2 | E18: 0.054082426 | J18: 4.25 | K18: 5.499999 | L18: A2/A | M18: 0.0085 | P18: 6 | Q18: 7.499999 | R18: A2/A | S18: 0.0085
... B21: Belarus | C21: Eastern Europe & Russia | D21: C | E21: 0.175 | J21: 8.5 | K21: 100000 | L21: Aaa/AAA | M21: 0.0045 | P21: 12.5 | Q21: 100000 | R21: Aaa/AAA | S21: 0.0045
B22: Belgium | C22: Western Europe | D22: Aa3 | E22: 0.0058935977
B23: Belize | C23: Central and South America | D23: Caa1 | E23: 0.073727752
B24: Benin | C24: Africa | D24: B1 | E24: 0.044259763
B25: Bermuda | C25: Caribbean | D25: A2 | E25: 0.0083203732
B26: Bolivia | C26: Central and South America | D26: Ca | E26: 0.11798751
B27: Bosnia and Herzegovina | C27: Eastern Europe & Russia | D27: B3 | E27: 0.063905089
B28: Botswana | C28: Africa | D28: A3 | E28: 0.011787195
B29: Brazil | C29: Central and South America | D29: Ba1 | E29: 0.024614437
B30: Bulgaria | C30: Eastern Europe & Russia | D30: Baa1 | E30: 0.015716261
B31: Burkina Faso | C31: Africa | D31: Caa1 | E31: 0.073727752
B32: Cambodia | C32: Asia | D32: B2 | E32: 0.054082426
B33: Cameroon | C33: Africa | D33: Caa1 | E33: 0.073727752
... B160: Zambia | C160: Africa | D160: Caa2 | E160: 0.088519526

Sheet Controlsheet
B2: ='Input Sheet'!C5 -> Eicher Motors
B3: Control Sheet | Q3: Mangement Case
F4: Current Case: | G4: 2 | Q4: Base Case
Q5: Down Case
H8: Actual | I8: Explicit Forecast Period | N8: Maturity Period
B9: In INR Crores unless stated otherwise | D9: 2021 | E9: =D9+1 -> 2022 | F9: =E9+1 -> 2023 | G9: =F9+1 -> 2024 | H9: =G9+1 -> 2025 | I9: =H9+1 -> 2026 | J9: =I9+1 -> 2027 | K9: =J9+1 -> 2028 | L9: =K9+1 -> 2029 | ... R9: =Q9+1 -> 2035
B11: Assumptions
A13: # | B13: Revenue
B15: Revenue - yoy% growth
B16: Mangement Case | D16: ='ConsolidatedP&L'!E8 -> -0.047329023 | E16: ='ConsolidatedP&L'!F8 -> 0.18089641 | F16: ='ConsolidatedP&L'!G8 -> 0.40244887 | G16: ='ConsolidatedP&L'!H8 -> 0.14496426 | H16: ='ConsolidatedP&L'!I8 -> 0.14118294 | I16: 0.15 | J16: =I16-(($I$16-$M$16)/($M$9-$I$9)) -> 0.1425 | K16: =J16-(($I$16-$M$16)/($M$9-$I$9)) -> 0.135 | L16: =K16-(($I$16-$M$16)/($M$9-$I$9)) -> 0.1275 | M16: 0.12 | N16: 0.12 | O16: 0.12 | P16: 0.12 | Q16: 0.12 | R16: 0.12
B17: Base Case | D17: =D16 -> -0.047329023 | E17: =E16 -> 0.18089641 | F17: =F16 -> 0.40244887 | G17: =G16 -> 0.14496426 | H17: =H16 -> 0.14118294 | I17: 0.15 | J17: =I17-(($I$17-$M$17)/($M$9-$I$9)) -> 0.1425 | K17: =J17-(($I$17-$M$17)/($M$9-$I$9)) -> 0.135 | L17: =K17-(($I$17-$M$17)/($M$9-$I$9)) -> 0.1275 | M17: 0.12 | N17: 0.12 | O17: 0.12 | P17: 0.12 | Q17: 0.12 | R17: 0.12
B18: Down Case | D18: =D17 -> -0.047329023 | E18: =E17 -> 0.18089641 | F18: =F17 -> 0.40244887 | G18: =G17 -> 0.14496426 | H18: =H17 -> 0.14118294 | I18: 0.07 | J18: =I18-(($I$18-$M$18)/($M$9-$I$9)) -> 0.0725 | K18: =J18-(($I$17-$M$17)/($M$9-$I$9)) -> 0.065 | L18: =K18-(($I$17-$M$17)/($M$9-$I$9)) -> 0.0575 | M18: 0.08 | N18: 0.08 | O18: 0.08 | P18: 0.08 | Q18: 0.08 | R18: 0.08
B19: ="Current Case - "&CHOOSE($G$4,B16,B17,B18) -> Current Case - Base Case | I19: =CHOOSE($G$4,I16,I17,I18) -> 0.15 | J19: =CHOOSE($G$4,J16,J17,J18) -> 0.1425 | K19: =CHOOSE($G$4,K16,K17,K18) -> 0.135 | L19: =CHOOSE($G$4,L16,L17,L18) -> 0.1275 | M19: =CHOOSE($G$4,M16,M17,M18) -> 0.12 | N19: =CHOOSE($G$4,N16,N17,N18) -> 0.12 | O19: =CHOOSE($G$4,O16,O17,O18) -> 0.12 | P19: =CHOOSE($G$4,P16,P17,P18) -> 0.12 | ... R19: =CHOOSE($G$4,R16,R17,R18) -> 0.12
A22: # | B22: COGS
B24: Gross Margin%
B25: Mangement Case | D25: ='ConsolidatedP&L'!C19 -> 0.48378595 | E25: ='ConsolidatedP&L'!D19 -> 0.45420917 | F25: ='ConsolidatedP&L'!E19 -> 0.41375404 | G25: ='ConsolidatedP&L'!F19 -> 0.4216568 | H25: ='ConsolidatedP&L'!G19 -> 0.43139471 | I25: 0.45 | J25: 0.45 | K25: 0.45 | L25: 0.45 | M25: 0.454 | N25: 0.454 | O25: 0.454 | P25: 0.454 | Q25: 0.454 | R25: 0.454
B26: Base Case | D26: =D25 -> 0.48378595 | E26: =E25 -> 0.45420917 | F26: =F25 -> 0.41375404 | G26: =G25 -> 0.4216568 | H26: =H25 -> 0.43139471 | I26: 0.45 | J26: =I26-(($I$26-$M$26)/($M$9-$I$9)) -> 0.444 | K26: =J26-(($I$26-$M$26)/($M$9-$I$9)) -> 0.438 | L26: =K26-(($I$26-$M$26)/($M$9-$I$9)) -> 0.432 | M26: 0.426 | N26: 0.426 | O26: 0.426 | P26: 0.426 | Q26: 0.426 | R26: 0.426
B27: Down Case | D27: =D26 -> 0.48378595 | E27: =E26 -> 0.45420917 | F27: =F26 -> 0.41375404 | G27: =G26 -> 0.4216568 | H27: =H26 -> 0.43139471 | I27: 0.42 | J27: =I27-(($I$27-$M$27)/($M$9-$I$9)) -> 0.41275 | K27: =J27-(($I$27-$M$27)/($M$9-$I$9)) -> 0.4055 | L27: =K27-(($I$27-$M$27)/($M$9-$I$9)) -> 0.39825 | M27: 0.391 | N27: 0.391 | O27: 0.391 | P27: 0.391 | Q27: 0.391 | R27: 0.391
B28: ="Current Case - "&CHOOSE($G$4,B25,B26,B27) -> Current Case - Base Case | I28: =CHOOSE($G$4,I25,I26,I27) -> 0.45 | J28: =CHOOSE($G$4,J25,J26,J27) -> 0.444 | K28: =CHOOSE($G$4,K25,K26,K27) -> 0.438 | L28: =CHOOSE($G$4,L25,L26,L27) -> 0.432 | M28: =CHOOSE($G$4,M25,M26,M27) -> 0.426 | N28: =CHOOSE($G$4,N25,N26,N27) -> 0.426 | O28: =CHOOSE($G$4,O25,O26,O27) -> 0.426 | P28: =CHOOSE($G$4,P25,P26,P27) -> 0.426 | ... R28: =CHOOSE($G$4,R25,R26,R27) -> 0.426
B30: Current Case - COGS % Sales | I30: =1-I28 -> 0.55 | J30: =1-J28 -> 0.556 | K30: =1-K28 -> 0.562 | L30: =1-L28 -> 0.568 | M30: =1-M28 -> 0.574 | N30: =1-N28 -> 0.574 | O30: =1-O28 -> 0.574 | P30: =1-P28 -> 0.574 | ... R30: =1-R28 -> 0.574
A33: # | B33: Selling, General and Administration (SG&A)
B35: Selling, General and Administration (SG&A)
B36: Mangement Case | D36: 0.096696807 | E36: 0.096696807 | F36: 0.096696807 | G36: 0.096696807 | H36: 0.096696807 | I36: 0.075 | J36: 0.075 | K36: 0.075 | L36: 0.075 | M36: 0.075 | N36: 0.075 | O36: 0.075 | P36: 0.075 | Q36: 0.075 | R36: 0.075
B37: Base Case | D37: =D36 -> 0.096696807 | E37: =E36 -> 0.096696807 | F37: =F36 -> 0.096696807 | G37: =G36 -> 0.096696807 | H37: =H36 -> 0.096696807 | I37: 0.075 | J37: 0.075 | K37: 0.075 | L37: 0.075 | M37: 0.075 | N37: 0.075 | O37: 0.075 | P37: 0.075 | Q37: 0.075 | R37: 0.075
B38: Down Case | D38: =D37 -> 0.096696807 | E38: =E37 -> 0.096696807 | F38: =F37 -> 0.096696807 | G38: =G37 -> 0.096696807 | H38: =H37 -> 0.096696807 | I38: 0.075 | J38: 0.075 | K38: 0.075 | L38: 0.075 | M38: 0.075 | N38: 0.075 | O38: 0.075 | P38: 0.075 | Q38: 0.075 | R38: 0.075
B39: ="Current Case - "&CHOOSE($G$4,B36,B37,B38) -> Current Case - Base Case | I39: =CHOOSE($G$4,I36,I37,I38) -> 0.075 | J39: =CHOOSE($G$4,J36,J37,J38) -> 0.075 | K39: =CHOOSE($G$4,K36,K37,K38) -> 0.075 | L39: =CHOOSE($G$4,L36,L37,L38) -> 0.075 | M39: =CHOOSE($G$4,M36,M37,M38) -> 0.075 | N39: =CHOOSE($G$4,N36,N37,N38) -> 0.075 | O39: =CHOOSE($G$4,O36,O37,O38) -> 0.075 | P39: =CHOOSE($G$4,P36,P37,P38) -> 0.075 | ... R39: =CHOOSE($G$4,R36,R37,R38) -> 0.075
B41: ='Assumptions Working'!B251 -> Consumption of Stores and machinery spares % Revenue
B42: Mangement Case | D42: 0.015998211 | E42: 0.019281732 | F42: 0.018158616 | G42: 0.014461973 | H42: 0.015185728 | I42: 0.017 | J42: 0.017 | K42: 0.017 | L42: 0.017 | M42: 0.017 | N42: 0.017 | O42: 0.017 | P42: 0.017 | Q42: 0.017 | R42: 0.017
B43: Base Case | D43: =D42 -> 0.015998211 | E43: =E42 -> 0.019281732 | F43: =F42 -> 0.018158616 | G43: =G42 -> 0.014461973 | H43: =H42 -> 0.015185728 | I43: 0.017 | J43: 0.017 | K43: 0.017 | L43: 0.017 | M43: 0.017 | N43: 0.017 | O43: 0.017 | P43: 0.017 | Q43: 0.017 | R43: 0.017
B44: Down Case | D44: =D43 -> 0.015998211 | E44: =E43 -> 0.019281732 | F44: =F43 -> 0.018158616 | G44: =G43 -> 0.014461973 | H44: =H43 -> 0.015185728 | I44: 0.017 | J44: 0.017 | K44: 0.017 | L44: 0.017 | M44: 0.017 | N44: 0.017 | O44: 0.017 | P44: 0.017 | Q44: 0.017 | R44: 0.017
B45: ="Current Case - "&CHOOSE($G$4,B42,B43,B44) -> Current Case - Base Case | I45: =CHOOSE($G$4,I42,I43,I44) -> 0.017 | J45: =CHOOSE($G$4,J42,J43,J44) -> 0.017 | K45: =CHOOSE($G$4,K42,K43,K44) -> 0.017 | L45: =CHOOSE($G$4,L42,L43,L44) -> 0.017 | M45: =CHOOSE($G$4,M42,M43,M44) -> 0.017 | N45: =CHOOSE($G$4,N42,N43,N44) -> 0.017 | O45: =CHOOSE($G$4,O42,O43,O44) -> 0.017 | P45: =CHOOSE($G$4,P42,P43,P44) -> 0.017 | ... R45: =CHOOSE($G$4,R42,R43,R44) -> 0.017
B47: ='Assumptions Working'!B254 -> Freight and handling charges % Revenue
B48: Mangement Case | D48: 0.013887057 | E48: 0.017573605 | F48: 0.018891192 | G48: 0.016060325 | H48: 0.017521668 | I48: 0.016 | J48: 0.016 | K48: 0.016 | L48: 0.016 | M48: 0.016 | N48: 0.016 | O48: 0.016 | P48: 0.016 | Q48: 0.016 | R48: 0.016
B49: Base Case | D49: =D48 -> 0.013887057 | E49: =E48 -> 0.017573605 | F49: =F48 -> 0.018891192 | G49: =G48 -> 0.016060325 | H49: =H48 -> 0.017521668 | I49: 0.016 | J49: 0.016 | K49: 0.016 | L49: 0.016 | M49: 0.016 | N49: 0.016 | O49: 0.016 | P49: 0.016 | Q49: 0.016 | R49: 0.016
B50: Down Case | D50: =D49 -> 0.013887057 | E50: =E49 -> 0.017573605 | F50: =F49 -> 0.018891192 | G50: =G49 -> 0.016060325 | H50: =H49 -> 0.017521668 | I50: 0.016 | J50: 0.016 | K50: 0.016 | L50: 0.016 | M50: 0.016 | N50: 0.016 | O50: 0.016 | P50: 0.016 | Q50: 0.016 | R50: 0.016
B51: ="Current Case - "&CHOOSE($G$4,B48,B49,B50) -> Current Case - Base Case | I51: =CHOOSE($G$4,I48,I49,I50) -> 0.016 | J51: =CHOOSE($G$4,J48,J49,J50) -> 0.016 | K51: =CHOOSE($G$4,K48,K49,K50) -> 0.016 | L51: =CHOOSE($G$4,L48,L49,L50) -> 0.016 | M51: =CHOOSE($G$4,M48,M49,M50) -> 0.016 | N51: =CHOOSE($G$4,N48,N49,N50) -> 0.016 | O51: =CHOOSE($G$4,O48,O49,O50) -> 0.016 | P51: =CHOOSE($G$4,P48,P49,P50) -> 0.016 | ... R51: =CHOOSE($G$4,R48,R49,R50) -> 0.016
B53: ='Assumptions Working'!B257 -> Selling and distribution expenses % Revenue
B54: Mangement Case | D54: 0.02074802 | E54: 0.02764563 | F54: 0.029523936 | G54: 0.033031402 | H54: 0.040321457 | I54: 0.028 | J54: 0.028 | K54: 0.028 | L54: 0.028 | M54: 0.028 | N54: 0.028 | O54: 0.028 | P54: 0.028 | Q54: 0.028 | R54: 0.028
B55: Base Case | D55: =D54 -> 0.02074802 | E55: =E54 -> 0.02764563 | F55: =F54 -> 0.029523936 | G55: =G54 -> 0.033031402 | H55: =H54 -> 0.040321457 | I55: 0.028 | J55: 0.028 | K55: 0.028 | L55: 0.028 | M55: 0.028 | N55: 0.028 | O55: 0.028 | P55: 0.028 | Q55: 0.028 | R55: 0.028
B56: Down Case | D56: =D55 -> 0.02074802 | E56: =E55 -> 0.02764563 | F56: =F55 -> 0.029523936 | G56: =G55 -> 0.033031402 | H56: =H55 -> 0.040321457 | I56: 0.028 | J56: 0.028 | K56: 0.028 | L56: 0.028 | M56: 0.028 | N56: 0.028 | O56: 0.028 | P56: 0.028 | Q56: 0.028 | R56: 0.028
B57: ="Current Case - "&CHOOSE($G$4,B54,B55,B56) -> Current Case - Base Case | I57: =CHOOSE($G$4,I54,I55,I56) -> 0.028 | J57: =CHOOSE($G$4,J54,J55,J56) -> 0.028 | K57: =CHOOSE($G$4,K54,K55,K56) -> 0.028 | L57: =CHOOSE($G$4,L54,L55,L56) -> 0.028 | M57: =CHOOSE($G$4,M54,M55,M56) -> 0.028 | N57: =CHOOSE($G$4,N54,N55,N56) -> 0.028 | O57: =CHOOSE($G$4,O54,O55,O56) -> 0.028 | P57: =CHOOSE($G$4,P54,P55,P56) -> 0.028 | ... R57: =CHOOSE($G$4,R54,R55,R56) -> 0.028
B59: ='Assumptions Working'!B260 -> Other SG&A Expenses % Revenue
B60: Mangement Case | D60: 0.062151175 | E60: 0.066485852 | F60: 0.057006629 | G60: 0.056944396 | H60: 0.057864851 | I60: 0.061 | J60: 0.061 | K60: 0.061 | L60: 0.061 | M60: 0.061 | N60: 0.061 | O60: 0.061 | P60: 0.061 | Q60: 0.061 | R60: 0.061
B61: Base Case | D61: =D60 -> 0.062151175 | E61: =E60 -> 0.066485852 | F61: =F60 -> 0.057006629 | G61: =G60 -> 0.056944396 | H61: =H60 -> 0.057864851 | I61: 0.061 | J61: 0.061 | K61: 0.061 | L61: 0.061 | M61: 0.061 | N61: 0.061 | O61: 0.061 | P61: 0.061 | Q61: 0.061 | R61: 0.061
B62: Down Case | D62: =D61 -> 0.062151175 | E62: =E61 -> 0.066485852 | F62: =F61 -> 0.057006629 | G62: =G61 -> 0.056944396 | H62: =H61 -> 0.057864851 | I62: 0.061 | J62: 0.061 | K62: 0.061 | L62: 0.061 | M62: 0.061 | N62: 0.061 | O62: 0.061 | P62: 0.061 | Q62: 0.061 | R62: 0.061
B63: ="Current Case - "&CHOOSE($G$4,B60,B61,B62) -> Current Case - Base Case | I63: =CHOOSE($G$4,I60,I61,I62) -> 0.061 | J63: =CHOOSE($G$4,J60,J61,J62) -> 0.061 | K63: =CHOOSE($G$4,K60,K61,K62) -> 0.061 | L63: =CHOOSE($G$4,L60,L61,L62) -> 0.061 | M63: =CHOOSE($G$4,M60,M61,M62) -> 0.061 | N63: =CHOOSE($G$4,N60,N61,N62) -> 0.061 | O63: =CHOOSE($G$4,O60,O61,O62) -> 0.061 | P63: =CHOOSE($G$4,P60,P61,P62) -> 0.061 | ... R63: =CHOOSE($G$4,R60,R61,R62) -> 0.061
B65: Total SG&A Expenses % Revenue | D65: =D60+D54+D48+D42+D36 -> 0.20948127 | E65: =E60+E54+E48+E42+E36 -> 0.22768363 | F65: =F60+F54+F48+F42+F36 -> 0.22027718 | G65: =G60+G54+G48+G42+G36 -> 0.2171949 | H65: =H60+H54+H48+H42+H36 -> 0.22759051 | I65: =I60+I54+I48+I42+I36 -> 0.197 | J65: =J60+J54+J48+J42+J36 -> 0.197 | K65: =K60+K54+K48+K42+K36 -> 0.197 | ... R65: =R60+R54+R48+R42+R36 -> 0.197
A67: # | B67: Non-Current Asset
B69: Fixed Assets
B71: Right of Use Asset Growth %
B72: Mangement Case | I72: 0 | J72: 0 | K72: 0 | L72: 0 | M72: 0 | N72: 0 | O72: 0 | P72: 0 | Q72: 0 | R72: 0
B73: Base Case | I73: 0 | J73: 0 | K73: 0 | L73: 0 | M73: 0 | N73: 0 | O73: 0 | P73: 0 | Q73: 0 | R73: 0
B74: Down Case | I74: 0 | J74: 0 | K74: 0 | L74: 0 | M74: 0 | N74: 0 | O74: 0 | P74: 0 | Q74: 0 | R74: 0
B75: ="Current Case - "&CHOOSE($G$4,B72,B73,B74) -> Current Case - Base Case | I75: =CHOOSE($G$4,I72,I73,I74) -> 0 | J75: =CHOOSE($G$4,J72,J73,J74) -> 0 | K75: =CHOOSE($G$4,K72,K73,K74) -> 0 | L75: =CHOOSE($G$4,L72,L73,L74) -> 0 | M75: =CHOOSE($G$4,M72,M73,M74) -> 0 | N75: =CHOOSE($G$4,N72,N73,N74) -> 0 | O75: =CHOOSE($G$4,O72,O73,O74) -> 0 | P75: =CHOOSE($G$4,P72,P73,P74) -> 0 | ... R75: =CHOOSE($G$4,R72,R73,R74) -> 0
B77: Capital Work in Progress % Net Fixed Assets
B78: Mangement Case | I78: 0 | J78: 0 | K78: 0 | L78: 0 | M78: 0 | N78: 0 | O78: 0 | P78: 0 | Q78: 0 | R78: 0
B79: Base Case | I79: 0 | J79: 0 | K79: 0 | L79: 0 | M79: 0 | N79: 0 | O79: 0 | P79: 0 | Q79: 0 | R79: 0
B80: Down Case | I80: 0 | J80: 0 | K80: 0 | L80: 0 | M80: 0 | N80: 0 | O80: 0 | P80: 0 | Q80: 0 | R80: 0
B81: ="Current Case - "&CHOOSE($G$4,B78,B79,B80) -> Current Case - Base Case | I81: =CHOOSE($G$4,I78,I79,I80) -> 0 | J81: =CHOOSE($G$4,J78,J79,J80) -> 0 | K81: =CHOOSE($G$4,K78,K79,K80) -> 0 | L81: =CHOOSE($G$4,L78,L79,L80) -> 0 | M81: =CHOOSE($G$4,M78,M79,M80) -> 0 | N81: =CHOOSE($G$4,N78,N79,N80) -> 0 | O81: =CHOOSE($G$4,O78,O79,O80) -> 0 | P81: =CHOOSE($G$4,P78,P79,P80) -> 0 | ... R81: =CHOOSE($G$4,R78,R79,R80) -> 0
B83: Intangible Non Current Asset
B85: Intangible assets Growth %
B86: Mangement Case | I86: 0 | J86: 0 | K86: 0 | L86: 0 | M86: 0 | N86: 0 | O86: 0 | P86: 0 | Q86: 0 | R86: 0
B87: Base Case | I87: 0 | J87: 0 | K87: 0 | L87: 0 | M87: 0 | N87: 0 | O87: 0 | P87: 0 | Q87: 0 | R87: 0
B88: Down Case | I88: 0 | J88: 0 | K88: 0 | L88: 0 | M88: 0 | N88: 0 | O88: 0 | P88: 0 | Q88: 0 | R88: 0
B89: ="Current Case - "&CHOOSE($G$4,B86,B87,B88) -> Current Case - Base Case | I89: =CHOOSE($G$4,I86,I87,I88) -> 0 | J89: =CHOOSE($G$4,J86,J87,J88) -> 0 | K89: =CHOOSE($G$4,K86,K87,K88) -> 0 | L89: =CHOOSE($G$4,L86,L87,L88) -> 0 | M89: =CHOOSE($G$4,M86,M87,M88) -> 0 | N89: =CHOOSE($G$4,N86,N87,N88) -> 0 | O89: =CHOOSE($G$4,O86,O87,O88) -> 0 | P89: =CHOOSE($G$4,P86,P87,P88) -> 0 | ... R89: =CHOOSE($G$4,R86,R87,R88) -> 0
B91: Intangible assets under development Growth %
B92: Mangement Case | I92: 0 | J92: 0 | K92: 0 | L92: 0 | M92: 0 | N92: 0 | O92: 0 | P92: 0 | Q92: 0 | R92: 0
B93: Base Case | I93: 0 | J93: 0 | K93: 0 | L93: 0 | M93: 0 | N93: 0 | O93: 0 | P93: 0 | Q93: 0 | R93: 0
B94: Down Case | I94: 0 | J94: 0 | K94: 0 | L94: 0 | M94: 0 | N94: 0 | O94: 0 | P94: 0 | Q94: 0 | R94: 0
B95: ="Current Case - "&CHOOSE($G$4,B92,B93,B94) -> Current Case - Base Case | I95: =CHOOSE($G$4,I92,I93,I94) -> 0 | J95: =CHOOSE($G$4,J92,J93,J94) -> 0 | K95: =CHOOSE($G$4,K92,K93,K94) -> 0 | L95: =CHOOSE($G$4,L92,L93,L94) -> 0 | M95: =CHOOSE($G$4,M92,M93,M94) -> 0 | N95: =CHOOSE($G$4,N92,N93,N94) -> 0 | O95: =CHOOSE($G$4,O92,O93,O94) -> 0 | P95: =CHOOSE($G$4,P92,P93,P94) -> 0 | ... R95: =CHOOSE($G$4,R92,R93,R94) -> 0
B97: Non Current Financial Assets
B99: Non Current Financial Assets Growth %
B100: Mangement Case | I100: 0.103 | J100: 0.093 | K100: 0.083 | L100: 0.073 | M100: 0.063 | N100: 0.063 | O100: 0.063 | P100: 0.063 | Q100: 0.063 | R100: 0.063
B101: Base Case | I101: 0.063 | J101: 0.063 | K101: 0.063 | L101: 0.063 | M101: 0.063 | N101: 0.063 | O101: 0.063 | P101: 0.063 | Q101: 0.063 | R101: 0.063
B102: Down Case | I102: 0.063 | J102: 0.063 | K102: 0.063 | L102: 0.063 | M102: 0.063 | N102: 0.063 | O102: 0.063 | P102: 0.063 | Q102: 0.063 | R102: 0.063
B103: ="Current Case - "&CHOOSE($G$4,B100,B101,B102) -> Current Case - Base Case | I103: =CHOOSE($G$4,I100,I101,I102) -> 0.063 | J103: =CHOOSE($G$4,J100,J101,J102) -> 0.063 | K103: =CHOOSE($G$4,K100,K101,K102) -> 0.063 | L103: =CHOOSE($G$4,L100,L101,L102) -> 0.063 | M103: =CHOOSE($G$4,M100,M101,M102) -> 0.063 | N103: =CHOOSE($G$4,N100,N101,N102) -> 0.063 | O103: =CHOOSE($G$4,O100,O101,O102) -> 0.063 | P103: =CHOOSE($G$4,P100,P101,P102) -> 0.063 | ... R103: =CHOOSE($G$4,R100,R101,R102) -> 0.063
B105: Other Non Current Asset % Revenue
B106: Mangement Case | I106: 0 | J106: 0 | K106: 0 | L106: 0 | M106: 0 | N106: 0 | O106: 0 | P106: 0 | Q106: 0 | R106: 0
B107: Base Case | I107: 0 | J107: 0 | K107: 0 | L107: 0 | M107: 0 | N107: 0 | O107: 0 | P107: 0 | Q107: 0 | R107: 0
B108: Down Case | I108: 0 | J108: 0 | K108: 0 | L108: 0 | M108: 0 | N108: 0 | O108: 0 | P108: 0 | Q108: 0 | R108: 0
B109: ="Current Case - "&CHOOSE($G$4,B106,B107,B108) -> Current Case - Base Case | I109: =CHOOSE($G$4,I106,I107,I108) -> 0 | J109: =CHOOSE($G$4,J106,J107,J108) -> 0 | K109: =CHOOSE($G$4,K106,K107,K108) -> 0 | L109: =CHOOSE($G$4,L106,L107,L108) -> 0 | M109: =CHOOSE($G$4,M106,M107,M108) -> 0 | N109: =CHOOSE($G$4,N106,N107,N108) -> 0 | O109: =CHOOSE($G$4,O106,O107,O108) -> 0 | P109: =CHOOSE($G$4,P106,P107,P108) -> 0 | ... R109: =CHOOSE($G$4,R106,R107,R108) -> 0
B111: Deferred Tax Asset Growth %
B112: Mangement Case | I112: 0 | J112: 0 | K112: 0 | L112: 0 | M112: 0 | N112: 0 | O112: 0 | P112: 0 | Q112: 0 | R112: 0
B113: Base Case | I113: 0 | J113: 0 | K113: 0 | L113: 0 | M113: 0 | N113: 0 | O113: 0 | P113: 0 | Q113: 0 | R113: 0
B114: Down Case | I114: 0 | J114: 0 | K114: 0 | L114: 0 | M114: 0 | N114: 0 | O114: 0 | P114: 0 | Q114: 0 | R114: 0
B115: ="Current Case - "&CHOOSE($G$4,B112,B113,B114) -> Current Case - Base Case | I115: =CHOOSE($G$4,I112,I113,I114) -> 0 | J115: =CHOOSE($G$4,J112,J113,J114) -> 0 | K115: =CHOOSE($G$4,K112,K113,K114) -> 0 | L115: =CHOOSE($G$4,L112,L113,L114) -> 0 | M115: =CHOOSE($G$4,M112,M113,M114) -> 0 | N115: =CHOOSE($G$4,N112,N113,N114) -> 0 | O115: =CHOOSE($G$4,O112,O113,O114) -> 0 | P115: =CHOOSE($G$4,P112,P113,P114) -> 0 | ... R115: =CHOOSE($G$4,R112,R113,R114) -> 0
B117: Non-current tax assets Growth %
B118: Mangement Case | I118: 0 | J118: 0 | K118: 0 | L118: 0 | M118: 0 | N118: 0 | O118: 0 | P118: 0 | Q118: 0 | R118: 0
B119: Base Case | I119: 0 | J119: 0 | K119: 0 | L119: 0 | M119: 0 | N119: 0 | O119: 0 | P119: 0 | Q119: 0 | R119: 0
B120: Down Case | I120: 0 | J120: 0 | K120: 0 | L120: 0 | M120: 0 | N120: 0 | O120: 0 | P120: 0 | Q120: 0 | R120: 0
B121: ="Current Case - "&CHOOSE($G$4,B118,B119,B120) -> Current Case - Base Case | I121: =CHOOSE($G$4,I118,I119,I120) -> 0 | J121: =CHOOSE($G$4,J118,J119,J120) -> 0 | K121: =CHOOSE($G$4,K118,K119,K120) -> 0 | L121: =CHOOSE($G$4,L118,L119,L120) -> 0 | M121: =CHOOSE($G$4,M118,M119,M120) -> 0 | N121: =CHOOSE($G$4,N118,N119,N120) -> 0 | O121: =CHOOSE($G$4,O118,O119,O120) -> 0 | P121: =CHOOSE($G$4,P118,P119,P120) -> 0 | ... R121: =CHOOSE($G$4,R118,R119,R120) -> 0
A123: # | B123: Tax Rate
B125: Marginal Tax Rate
B126: Mangement Case | I126: 0.2512 | J126: 0.2512 | K126: 0.2512 | L126: 0.2512 | M126: 0.2512 | N126: 0.2512 | O126: 0.2512 | P126: 0.2512 | Q126: 0.2512 | R126: 0.2512
B127: Best Case | I127: 0.2512 | J127: 0.2512 | K127: 0.2512 | L127: 0.2512 | M127: 0.2512 | N127: 0.2512 | O127: 0.2512 | P127: 0.2512 | Q127: 0.2512 | R127: 0.2512
B128: Down Case | I128: 0.2512 | J128: 0.2512 | K128: 0.2512 | L128: 0.2512 | M128: 0.2512 | N128: 0.2512 | O128: 0.2512 | P128: 0.2512 | Q128: 0.2512 | R128: 0.2512
B129: Current Case - Mangement Case | I129: =CHOOSE($G$4,I126,I127,I128) -> 0.2512 | J129: =CHOOSE($G$4,J126,J127,J128) -> 0.2512 | K129: =CHOOSE($G$4,K126,K127,K128) -> 0.2512 | L129: =CHOOSE($G$4,L126,L127,L128) -> 0.2512 | M129: =CHOOSE($G$4,M126,M127,M128) -> 0.2512 | N129: =CHOOSE($G$4,N126,N127,N128) -> 0.2512 | O129: =CHOOSE($G$4,O126,O127,O128) -> 0.2512 | P129: =CHOOSE($G$4,P126,P127,P128) -> 0.2512 | ... R129: =CHOOSE($G$4,R126,R127,R128) -> 0.2512
A131: # | B131: Long Term Borrowings
B133: % Revenue
B134: Mangement Case | I134: 0.01 | J134: =I134-(($I$134-$M$134)/($M$9-$I$9)) -> 0.00775 | K134: =J134-(($I$134-$M$134)/($M$9-$I$9)) -> 0.0055 | L134: =K134-(($I$134-$M$134)/($M$9-$I$9)) -> 0.00325 | M134: 0.001 | N134: 0.001 | O134: 0.001 | P134: 0.001 | Q134: 0.001 | R134: 0.001
...

Sheet Schedules
B2: ='Input Sheet'!C5 -> Eicher Motors
B3: Schedule Sheet
H4: Current Case: | I4: 0
H8: Actual | I8: Explicit Forecast Period | N8: Maturity Period
B9: In INR Crores unless stated otherwise | D9: =Controlsheet!D9 -> 2021 | E9: =Controlsheet!E9 -> 2022 | F9: =Controlsheet!F9 -> 2023 | G9: =Controlsheet!G9 -> 2024 | H9: =Controlsheet!H9 -> 2025 | I9: =H9+1 -> 2026 | J9: =I9+1 -> 2027 | K9: =J9+1 -> 2028 | L9: =K9+1 -> 2029 | M9: =L9+1 -> 2030 | N9: =M9+1 -> 2031 | O9: =N9+1 -> 2032 | P9: =O9+1 -> 2033 | ... R9: =Q9+1 -> 2035
A11: # | B11: Revenue Schedule
B13: Revenue | D13: ='ConsolidatedP&L'!E6 -> 8720.35 | E13: ='ConsolidatedP&L'!F6 -> 10297.83 | F13: ='ConsolidatedP&L'!G6 -> 14442.18 | G13: ='ConsolidatedP&L'!H6 -> 16535.78 | H13: ='ConsolidatedP&L'!I6 -> 18870.35 | I13: =H13*(1+I15) -> 21700.902 | J13: =I13*(1+J15) -> 24793.281 | K13: =J13*(1+K15) -> 28140.374 | L13: =K13*(1+L15) -> 31728.272 | M13: =L13*(1+M15) -> 35535.664 | N13: =M13*(1+N15) -> 39799.944 | O13: =N13*(1+O15) -> 44575.937 | P13: =O13*(1+P15) -> 49925.05 | ... R13: =Q13*(1+R15) -> 62625.983
B15: Growth YoY% | E15: =E13/D13-1 -> 0.18089641 | F15: =F13/E13-1 -> 0.40244887 | G15: =G13/F13-1 -> 0.14496426 | H15: =H13/G13-1 -> 0.14118294 | I15: =Controlsheet!I19 -> 0.15 | J15: =Controlsheet!J19 -> 0.1425 | K15: =Controlsheet!K19 -> 0.135 | L15: =Controlsheet!L19 -> 0.1275 | M15: =Controlsheet!M19 -> 0.12 | N15: =Controlsheet!N19 -> 0.12 | O15: =Controlsheet!O19 -> 0.12 | P15: =Controlsheet!P19 -> 0.12 | ... R15: =Controlsheet!R19 -> 0.12
A17: # | B17: COGS Schedule
B20: COGS | D20: ='ConsolidatedP&L'!E16*-1 -> 5112.27 | E20: ='ConsolidatedP&L'!F16*-1 -> 5955.68 | F20: ='ConsolidatedP&L'!G16*-1 -> 8211.9 | G20: ='ConsolidatedP&L'!H16*-1 -> 8980.65 | H20: ='ConsolidatedP&L'!I16*-1 -> 10297.08 | I20: =I13*I22 -> 11935.496 | J20: =J13*J22 -> 13785.064 | K20: =K13*K22 -> 15814.89 | L20: =L13*L22 -> 18021.658 | M20: =M13*M22 -> 20397.471 | N20: =N13*N22 -> 22845.168 | O20: =O13*O22 -> 25586.588 | P20: =P13*P22 -> 28656.979 | ... R20: =R13*R22 -> 35947.314
B22: COGS % Sales | D22: =D20/D13 -> 0.58624596 | E22: =E20/E13 -> 0.5783432 | F22: =F20/F13 -> 0.56860529 | G22: =G20/G13 -> 0.54310411 | H22: =H20/H13 -> 0.54567509 | I22: =Controlsheet!I30 -> 0.55 | J22: =Controlsheet!J30 -> 0.556 | K22: =Controlsheet!K30 -> 0.562 | L22: =Controlsheet!L30 -> 0.568 | M22: =Controlsheet!M30 -> 0.574 | N22: =Controlsheet!N30 -> 0.574 | O22: =Controlsheet!O30 -> 0.574 | P22: =Controlsheet!P30 -> 0.574 | ... R22: =Controlsheet!R30 -> 0.574
A24: # | B24: SG&A (Excluding Depreciation & Interest Expenses) Schedule
B26: Employee Benefit Expense
B28: Employee Benefit Expense | D28: ='Assumptions Working'!F247 -> 843.23 | E28: ='Assumptions Working'!G247 -> 821.02 | F28: ='Assumptions Working'!H247 -> 1001.93 | G28: ='Assumptions Working'!I247 -> 1235.69 | H28: ='Assumptions Working'!J247 -> 1391.23 | I28: =I$13*I29 -> 1627.5677 | J28: =J$13*J29 -> 1859.4961 | K28: =K$13*K29 -> 2110.5281 | L28: =L$13*L29 -> 2379.6204 | M28: =M$13*M29 -> 2665.1748 | N28: =N$13*N29 -> 2984.9958 | O28: =O$13*O29 -> 3343.1953 | P28: =P$13*P29 -> 3744.3787 | ... R28: =R$13*R29 -> 4696.9487
B29: Employee Benefit Expense % Revenue | D29: ='Assumptions Working'!F248 -> 0.096696807 | E29: ='Assumptions Working'!G248 -> 0.079727477 | F29: ='Assumptions Working'!H248 -> 0.069375261 | G29: ='Assumptions Working'!I248 -> 0.074728256 | H29: ='Assumptions Working'!J248 -> 0.073725713 | I29: =Controlsheet!I39 -> 0.075 | J29: =Controlsheet!J39 -> 0.075 | K29: =Controlsheet!K39 -> 0.075 | L29: =Controlsheet!L39 -> 0.075 | M29: =Controlsheet!M39 -> 0.075 | N29: =Controlsheet!N39 -> 0.075 | O29: =Controlsheet!O39 -> 0.075 | P29: =Controlsheet!P39 -> 0.075 | ... R29: =Controlsheet!R39 -> 0.075
B31: Consumption of Stores and machinery spares
B33: Consumption of Stores and machinery spares | D33: ='Assumptions Working'!F250 -> 139.51 | E33: ='Assumptions Working'!G250 -> 198.56 | F33: ='Assumptions Working'!H250 -> 262.25 | G33: ='Assumptions Working'!I250 -> 239.14 | H33: ='Assumptions Working'!J250 -> 286.56 | I33: =I$13*I34 -> 368.91534 | J33: =J$13*J34 -> 421.48578 | K33: =K$13*K34 -> 478.38636 | L33: =L$13*L34 -> 539.38062 | M33: =M$13*M34 -> 604.10629 | N33: =N$13*N34 -> 676.59905 | O33: =O$13*O34 -> 757.79094 | P33: =P$13*P34 -> 848.72585 | ... R33: =R$13*R34 -> 1064.6417
B34: Consumption of Stores and machinery spares % Revenue | D34: ='Assumptions Working'!F251 -> 0.015998211 | E34: ='Assumptions Working'!G251 -> 0.019281732 | F34: ='Assumptions Working'!H251 -> 0.018158616 | G34: ='Assumptions Working'!I251 -> 0.014461973 | H34: ='Assumptions Working'!J251 -> 0.015185728 | I34: =Controlsheet!I45 -> 0.017 | J34: =Controlsheet!J45 -> 0.017 | K34: =Controlsheet!K45 -> 0.017 | L34: =Controlsheet!L45 -> 0.017 | M34: =Controlsheet!M45 -> 0.017 | N34: =Controlsheet!N45 -> 0.017 | O34: =Controlsheet!O45 -> 0.017 | P34: =Controlsheet!P45 -> 0.017 | ... R34: =Controlsheet!R45 -> 0.017
B36: Freight and handling charges
B38: Freight and handling charges | D38: ='Assumptions Working'!F253 -> 121.1 | E38: ='Assumptions Working'!G253 -> 180.97 | F38: ='Assumptions Working'!H253 -> 272.83 | G38: ='Assumptions Working'!I253 -> 265.57 | H38: ='Assumptions Working'!J253 -> 330.64 | I38: =I$13*I39 -> 347.21444 | J38: =J$13*J39 -> 396.6925 | K38: =K$13*K39 -> 450.24598 | L38: =L$13*L39 -> 507.65235 | M38: =M$13*M39 -> 568.57063 | N38: =N$13*N39 -> 636.79911 | O38: =O$13*O39 -> 713.215 | P38: =P$13*P39 -> 798.8008 | ... R38: =R$13*R39 -> 1002.0157
B39: Freight and handling charges % Revenue | D39: ='Assumptions Working'!F254 -> 0.013887057 | E39: ='Assumptions Working'!G254 -> 0.017573605 | F39: ='Assumptions Working'!H254 -> 0.018891192 | G39: ='Assumptions Working'!I254 -> 0.016060325 | H39: ='Assumptions Working'!J254 -> 0.017521668 | I39: =Controlsheet!I51 -> 0.016 | J39: =Controlsheet!J51 -> 0.016 | K39: =Controlsheet!K51 -> 0.016 | L39: =Controlsheet!L51 -> 0.016 | M39: =Controlsheet!M51 -> 0.016 | N39: =Controlsheet!N51 -> 0.016 | O39: =Controlsheet!O51 -> 0.016 | P39: =Controlsheet!P51 -> 0.016 | ... R39: =Controlsheet!R51 -> 0.016
B41: Selling and distribution expenses
B43: Selling and distribution expenses | D43: ='Assumptions Working'!F256 -> 180.93 | E43: ='Assumptions Working'!G256 -> 284.69 | F43: ='Assumptions Working'!H256 -> 426.39 | G43: ='Assumptions Working'!I256 -> 546.2 | H43: ='Assumptions Working'!J256 -> 760.88 | I43: =I$13*I44 -> 607.62527 | J43: =J$13*J44 -> 694.21187 | K43: =K$13*K44 -> 787.93047 | L43: =L$13*L44 -> 888.39161 | M43: =M$13*M44 -> 994.9986 | N43: =N$13*N44 -> 1114.3984 | O43: =O$13*O44 -> 1248.1262 | P43: =P$13*P44 -> 1397.9014 | ... R43: =R$13*R44 -> 1753.5275
B44: Selling and distribution expenses % Revenue | D44: ='Assumptions Working'!F257 -> 0.02074802 | E44: ='Assumptions Working'!G257 -> 0.02764563 | F44: ='Assumptions Working'!H257 -> 0.029523936 | G44: ='Assumptions Working'!I257 -> 0.033031402 | H44: ='Assumptions Working'!J257 -> 0.040321457 | I44: =Controlsheet!I57 -> 0.028 | J44: =Controlsheet!J57 -> 0.028 | K44: =Controlsheet!K57 -> 0.028 | L44: =Controlsheet!L57 -> 0.028 | M44: =Controlsheet!M57 -> 0.028 | N44: =Controlsheet!N57 -> 0.028 | O44: =Controlsheet!O57 -> 0.028 | P44: =Controlsheet!P57 -> 0.028 | ... R44: =Controlsheet!R57 -> 0.028
B46: Other SG&A Expenses
B48: Other SG&A Expenses | D48: ='Assumptions Working'!F259 -> 541.98 | E48: ='Assumptions Working'!G259 -> 684.66 | F48: ='Assumptions Working'!H259 -> 823.3 | G48: ='Assumptions Working'!I259 -> 941.62 | H48: ='Assumptions Working'!J259 -> 1091.93 | I48: =I$13*I49 -> 1323.7551 | J48: =J$13*J49 -> 1512.3901 | K48: =K$13*K49 -> 1716.5628 | L48: =L$13*L49 -> 1935.4246 | M48: =M$13*M49 -> 2167.6755 | N48: =N$13*N49 -> 2427.7966 | O48: =O$13*O49 -> 2719.1322 | P48: =P$13*P49 -> 3045.428 | ... R48: =R$13*R49 -> 3820.1849
B49: Other SG&A Expenses % Revenue | D49: ='Assumptions Working'!F260 -> 0.062151175 | E49: ='Assumptions Working'!G260 -> 0.066485852 | F49: ='Assumptions Working'!H260 -> 0.057006629 | G49: ='Assumptions Working'!I260 -> 0.056944396 | H49: ='Assumptions Working'!J260 -> 0.057864851 | I49: =Controlsheet!I63 -> 0.061 | J49: =Controlsheet!J63 -> 0.061 | K49: =Controlsheet!K63 -> 0.061 | L49: =Controlsheet!L63 -> 0.061 | M49: =Controlsheet!M63 -> 0.061 | N49: =Controlsheet!N63 -> 0.061 | O49: =Controlsheet!O63 -> 0.061 | P49: =Controlsheet!P63 -> 0.061 | ... R49: =Controlsheet!R63 -> 0.061
B51: Total SG&A (Excluding Depreciation & Interest Expenses) | D51: =SUM(D28,D33,D38,D43,D48) -> 1826.75 | E51: =SUM(E28,E33,E38,E43,E48) -> 2169.9 | F51: =SUM(F28,F33,F38,F43,F48) -> 2786.7 | G51: =SUM(G28,G33,G38,G43,G48) -> 3228.22 | H51: =SUM(H28,H33,H38,H43,H48) -> 3861.24 | I51: =SUM(I28,I33,I38,I43,I48) -> 4275.0778 | J51: =SUM(J28,J33,J38,J43,J48) -> 4884.2764 | K51: =SUM(K28,K33,K38,K43,K48) -> 5543.6537 | ... R51: =SUM(R28,R33,R38,R43,R48) -> 12337.319
B52: Total SG&A % Sales | D52: =D51/D13 -> 0.20948127 | E52: =E51/E13 -> 0.2107143 | F52: =F51/F13 -> 0.19295563 | G52: =G51/G13 -> 0.19522635 | H52: =H51/H13 -> 0.20461942 | I52: =I51/I13 -> 0.197 | J52: =J51/J13 -> 0.197 | K52: =K51/K13 -> 0.197 | ... R52: =R51/R13 -> 0.197
A54: # | B54: Non Current Asset Schedule
B56: Property Plant & Equipment
B58: Opening PP&E | I58: =ConsolidatedBS!I6 -> 2268.7 | J58: =I61 -> 2919.4431 | K58: =J61 -> 3450.1861 | L58: =K61 -> 3860.9292 | M58: =L61 -> 4151.6722 | N58: =M61 -> 4322.4153 | O58: =N61 -> 4373.1584 | P58: =O61 -> 4303.9014 | Q58: =P61 -> 4114.6445 | R58: =Q61 -> 3805.3875
B59: Add : Capex during the year | I59: 1200 | J59: 1200 | K59: 1200 | L59: 1200 | M59: 1200 | N59: 1200 | O59: 1200 | P59: 1200 | Q59: 1200 | R59: 1200
B60: Less : Depreciation | H60: =('ConsolidatedP&L'!I35*-1)/(SUM(ConsolidatedBS!I6,ConsolidatedBS!I10,ConsolidatedBS!I9,ConsolidatedBS!I11))*ConsolidatedBS!I6 -> 429.25694 | I60: =H60+I59/$C$114 -> 549.25694 | J60: =I60+J59/$C$114 -> 669.25694 | K60: =J60+K59/$C$114 -> 789.25694 | L60: =K60+L59/$C$114 -> 909.25694 | M60: =L60+M59/$C$114 -> 1029.2569 | N60: =M60+N59/$C$114 -> 1149.2569 | O60: =N60+O59/$C$114 -> 1269.2569 | P60: =O60+P59/$C$114 -> 1389.2569 | ... R60: =Q60+R59/$C$114 -> 1629.2569
B61: Closing PP&E | I61: =I58+I59-I60 -> 2919.4431 | J61: =J58+J59-J60 -> 3450.1861 | K61: =K58+K59-K60 -> 3860.9292 | L61: =L58+L59-L60 -> 4151.6722 | M61: =M58+M59-M60 -> 4322.4153 | N61: =N58+N59-N60 -> 4373.1584 | O61: =O58+O59-O60 -> 4303.9014 | P61: =P58+P59-P60 -> 4114.6445 | ... R61: =R58+R59-R60 -> 3376.1306
B62: YoY Growth % | J62: =J61/I61-1 -> 0.181796 | K62: =K61/J61-1 -> 0.11904954 | L62: =L61/K61-1 -> 0.075303909 | M62: =M61/L61-1 -> 0.041126334 | N62: =N61/M61-1 -> 0.011739515 | O62: =O61/N61-1 -> -0.015836824 | P62: =P61/O61-1 -> -0.043973345 | Q62: =Q61/P61-1 -> -0.075160063 | R62: =R61/Q61-1 -> -0.11280242
B64: Right of Use Asset
B65: Right of Use Asset | D65: =ConsolidatedBS!E10 -> 197.62 | E65: =ConsolidatedBS!F10 -> 183.66 | F65: =ConsolidatedBS!G10 -> 226.13 | G65: =ConsolidatedBS!H10 -> 271.99 | H65: =ConsolidatedBS!I10 -> 317.04 | I65: =H65*(1+I71) -> 317.04 | J65: =I68 -> 257.05339 | K65: =J68 -> 197.06678 | L65: =K68 -> 137.08017 | M65: =L68 -> 77.093563 | N65: =M68 -> 17.106954 | O65: =N68 -> -42.879655 | P65: =O68 -> -102.86626 | Q65: =P68 -> -162.85287 | R65: =Q68 -> -222.83948
B66: Addition during the year | I66: =H65*(I71) -> 0 | J66: =I65*(J71) -> 0 | K66: =J65*(K71) -> 0 | L66: =K65*(L71) -> 0 | M66: =L65*(M71) -> 0 | N66: =M65*(N71) -> 0 | O66: =N65*(O71) -> 0 | P66: =O65*(P71) -> 0 | ... R66: =Q65*(R71) -> 0
B67: Less : Depreciation | H67: =('ConsolidatedP&L'!I35*-1)/(SUM(ConsolidatedBS!I6,ConsolidatedBS!I10,ConsolidatedBS!I9,ConsolidatedBS!I11))*ConsolidatedBS!I10 -> 59.986609 | I67: =H67+I66/$C$114 -> 59.986609 | J67: =I67+J66/$C$114 -> 59.986609 | K67: =J67+K66/$C$114 -> 59.986609 | L67: =K67+L66/$C$114 -> 59.986609 | M67: =L67+M66/$C$114 -> 59.986609 | N67: =M67+N66/$C$114 -> 59.986609 | O67: =N67+O66/$C$114 -> 59.986609 | P67: =O67+P66/$C$114 -> 59.986609 | ... R67: =Q67+R66/$C$114 -> 59.986609
B68: Closing Right of Use Asset | I68: =I65+I66-I67 -> 257.05339 | J68: =J65+J66-J67 -> 197.06678 | K68: =K65+K66-K67 -> 137.08017 | L68: =L65+L66-L67 -> 77.093563 | M68: =M65+M66-M67 -> 17.106954 | N68: =N65+N66-N67 -> -42.879655 | O68: =O65+O66-O67 -> -102.86626 | P68: =P65+P66-P67 -> -162.85287 | ... R68: =R65+R66-R67 -> -282.82609
B69: YoY Growth % | J69: =J68/I68-1 -> -0.23336245 | K69: =K68/J68-1 -> -0.30439737 | L69: =L68/K68-1 -> -0.43760238 | M69: =M68/L68-1 -> -0.7781014 | N69: =N68/M68-1 -> -3.5065628 | O69: =O68/N68-1 -> 1.3989527 | P69: =P68/O68-1 -> 0.58315143 | Q69: =Q68/P68-1 -> 0.36834848 | R69: =R68/Q68-1 -> 0.26919201
B71: YoY Growth % | E71: =E65/D65-1 -> -0.070640623 | F71: =F65/E65-1 -> 0.23124251 | G71: =G65/F65-1 -> 0.2028037 | H71: =H65/G65-1 -> 0.16563109 | I71: =Controlsheet!I75 -> 0 | J71: =Controlsheet!J75 -> 0 | K71: =Controlsheet!K75 -> 0 | L71: =Controlsheet!L75 -> 0 | M71: =Controlsheet!M75 -> 0 | N71: =Controlsheet!N75 -> 0 | O71: =Controlsheet!O75 -> 0 | P71: =Controlsheet!P75 -> 0 | ... R71: =Controlsheet!R75 -> 0
B73: Capital Work in Progress
B74: Capital Work in Progress | D74: =ConsolidatedBS!E7 -> 63.91 | E74: =ConsolidatedBS!F7 -> 133.98 | F74: =ConsolidatedBS!G7 -> 77.75 | G74: =ConsolidatedBS!H7 -> 211.65 | H74: =ConsolidatedBS!I7 -> 110.3 | I74: 0 | J74: 0 | K74: 0 | L74: 0 | M74: 0 | N74: 0 | O74: 0 | P74: 0 | Q74: 0 | R74: 0
B75: YoY Growth % | I75: =Controlsheet!I81 -> 0 | J75: =Controlsheet!J81 -> 0 | K75: =Controlsheet!K81 -> 0 | L75: =Controlsheet!L81 -> 0 | M75: =Controlsheet!M81 -> 0 | N75: =Controlsheet!N81 -> 0 | O75: =Controlsheet!O81 -> 0 | P75: =Controlsheet!P81 -> 0 | ... R75: =Controlsheet!R81 -> 0
B77: Intangible assets
B78: Intangible assets | D78: ='Assumptions Working'!F649 -> 341.17 | E78: ='Assumptions Working'!G649 -> 329.84 | F78: ='Assumptions Working'!H649 -> 464.21 | G78: ='Assumptions Working'!I649 -> 692.13 | H78: ='Assumptions Working'!J649 -> 887.73 | I78: =H78*(1+I84) -> 887.73 | J78: =I81 -> 719.76409 | K78: =J81 -> 551.79818 | L78: =K81 -> 383.83227 | M78: =L81 -> 215.86635 | N78: =M81 -> 47.900443 | O78: =N81 -> -120.06547 | P78: =O81 -> -288.03138 | Q78: =P81 -> -455.99729 | R78: =Q81 -> -623.9632
B79: Addition during the year | I79: =H78*(I84) -> 0 | J79: =I78*(J84) -> 0 | K79: =J78*(K84) -> 0 | L79: =K78*(L84) -> 0 | M79: =L78*(M84) -> 0 | N79: =M78*(N84) -> 0 | O79: =N78*(O84) -> 0 | P79: =O78*(P84) -> 0 | ... R79: =Q78*(R84) -> 0
B80: Less : Depreciation | H80: =('ConsolidatedP&L'!I35*-1)/(SUM(ConsolidatedBS!I6,ConsolidatedBS!I10,ConsolidatedBS!I9,ConsolidatedBS!I11))*ConsolidatedBS!I9 -> 167.96591 | I80: =H80+I79/$C$114 -> 167.96591 | J80: =I80+J79/$C$114 -> 167.96591 | K80: =J80+K79/$C$114 -> 167.96591 | L80: =K80+L79/$C$114 -> 167.96591 | M80: =L80+M79/$C$114 -> 167.96591 | N80: =M80+N79/$C$114 -> 167.96591 | O80: =N80+O79/$C$114 -> 167.96591 | P80: =O80+P79/$C$114 -> 167.96591 | ... R80: =Q80+R79/$C$114 -> 167.96591
B81: Closing Intangible Asset | I81: =I78+I79-I80 -> 719.76409 | J81: =J78+J79-J80 -> 551.79818 | K81: =K78+K79-K80 -> 383.83227 | L81: =L78+L79-L80 -> 215.86635 | M81: =M78+M79-M80 -> 47.900443 | N81: =N78+N79-N80 -> -120.06547 | O81: =O78+O79-O80 -> -288.03138 | P81: =P78+P79-P80 -> -455.99729 | ... R81: =R78+R79-R80 -> -791.92911
B82: YoY Growth % | J82: =J81/I81-1 -> -0.23336245 | K82: =K81/J81-1 -> -0.30439737 | L82: =L81/K81-1 -> -0.43760238 | M82: =M81/L81-1 -> -0.7781014 | N82: =N81/M81-1 -> -3.5065628 | O82: =O81/N81-1 -> 1.3989527 | P82: =P81/O81-1 -> 0.58315143 | Q82: =Q81/P81-1 -> 0.36834848 | R82: =R81/Q81-1 -> 0.26919201
B84: YoY Growth % | E84: =E78/D78-1 -> -0.033209251 | F84: =F78/E78-1 -> 0.40737934 | G84: =G78/F78-1 -> 0.49098468 | H84: =H78/G78-1 -> 0.28260587 | I84: =Controlsheet!I89 -> 0 | J84: =Controlsheet!J89 -> 0 | K84: =Controlsheet!K89 -> 0 | L84: =Controlsheet!L89 -> 0 | M84: =Controlsheet!M89 -> 0 | N84: =Controlsheet!N89 -> 0 | O84: =Controlsheet!O89 -> 0 | P84: =Controlsheet!P89 -> 0 | ... R84: =Controlsheet!R89 -> 0
B86: Intangible assets under development
B87: Intangible assets under development | D87: ='Assumptions Working'!F650 -> 250.38 | E87: ='Assumptions Working'!G650 -> 370.8 | F87: ='Assumptions Working'!H650 -> 394.32 | G87: ='Assumptions Working'!I650 -> 343.45 | H87: ='Assumptions Working'!J650 -> 381.17 | I87: =H87*(1+I93) -> 381.17 | J87: =I90 -> 309.04946 | K87: =J90 -> 236.92892 | L87: =K90 -> 164.80838 | M87: =L90 -> 92.687842 | N87: =M90 -> 20.567303 | O87: =N90 -> -51.553237 | P87: =O90 -> -123.67378 | Q87: =P90 -> -195.79432 | R87: =Q90 -> -267.91485
B88: Addition during the year | I88: =H87*(I93) -> 0 | J88: =I87*(J93) -> 0 | K88: =J87*(K93) -> 0 | L88: =K87*(L93) -> 0 | M88: =L87*(M93) -> 0 | N88: =M87*(N93) -> 0 | O88: =N87*(O93) -> 0 | P88: =O87*(P93) -> 0 | ... R88: =Q87*(R93) -> 0
B89: Less : Depreciation | H89: =('ConsolidatedP&L'!I35*-1)/(SUM(ConsolidatedBS!I6,ConsolidatedBS!I10,ConsolidatedBS!I9,ConsolidatedBS!I11))*ConsolidatedBS!I11 -> 72.120539 | I89: =H89+I88/$C$114 -> 72.120539 | J89: =I89+J88/$C$114 -> 72.120539 | K89: =J89+K88/$C$114 -> 72.120539 | L89: =K89+L88/$C$114 -> 72.120539 | M89: =L89+M88/$C$114 -> 72.120539 | N89: =M89+N88/$C$114 -> 72.120539 | O89: =N89+O88/$C$114 -> 72.120539 | P89: =O89+P88/$C$114 -> 72.120539 | ... R89: =Q89+R88/$C$114 -> 72.120539
B90: Closing Intangible asset under development | I90: =I87+I88-I89 -> 309.04946 | J90: =J87+J88-J89 -> 236.92892 | K90: =K87+K88-K89 -> 164.80838 | L90: =L87+L88-L89 -> 92.687842 | M90: =M87+M88-M89 -> 20.567303 | N90: =N87+N88-N89 -> -51.553237 | O90: =O87+O88-O89 -> -123.67378 | P90: =P87+P88-P89 -> -195.79432 | ... R90: =R87+R88-R89 -> -340.03539
B91: YoY Growth % | J91: =J90/I90-1 -> -0.23336245 | K91: =K90/J90-1 -> -0.30439737 | L91: =L90/K90-1 -> -0.43760238 | M91: =M90/L90-1 -> -0.7781014 | N91: =N90/M90-1 -> -3.5065628 | O91: =O90/N90-1 -> 1.3989527 | P91: =P90/O90-1 -> 0.58315143 | Q91: =Q90/P90-1 -> 0.36834848 | R91: =R90/Q90-1 -> 0.26919201
B93: YoY Growth % | E93: =E87/D87-1 -> 0.48094896 | F93: =F87/E87-1 -> 0.063430421 | G93: =G87/F87-1 -> -0.1290069 | H93: =H87/G87-1 -> 0.10982676 | I93: =Controlsheet!I95 -> 0 | J93: =Controlsheet!J95 -> 0 | K93: =Controlsheet!K95 -> 0 | L93: =Controlsheet!L95 -> 0 | M93: =Controlsheet!M95 -> 0 | N93: =Controlsheet!N95 -> 0 | O93: =Controlsheet!O95 -> 0 | P93: =Controlsheet!P95 -> 0 | ... R93: =Controlsheet!R95 -> 0
B95: Non Current Financial Asset
B96: Non Current Financial Asset | D96: =ConsolidatedBS!E14+ConsolidatedBS!E15+ConsolidatedBS!E16 -> 2848.92 | E96: =ConsolidatedBS!F14+ConsolidatedBS!F15+ConsolidatedBS!F16 -> 7368.9 | F96: =ConsolidatedBS!G14+ConsolidatedBS!G15+ConsolidatedBS!G16 -> 12120.05 | G96: =ConsolidatedBS!H14+ConsolidatedBS!H15+ConsolidatedBS!H16 -> 15202.14 | H96: =ConsolidatedBS!I14+ConsolidatedBS!I15+ConsolidatedBS!I16 -> 16013.75 | I96: =H96*(1+I97) -> 17022.616 | J96: =I96*(1+J97) -> 18095.041 | K96: =J96*(1+K97) -> 19235.029 | L96: =K96*(1+L97) -> 20446.835 | M96: =L96*(1+M97) -> 21734.986 | N96: =M96*(1+N97) -> 23104.29 | O96: =N96*(1+O97) -> 24559.861 | P96: =O96*(1+P97) -> 26107.132 | ... R96: =Q96*(1+R97) -> 29500.25
B97: YoY Growth % | E97: =E96/D96-1 -> 1.5865591 | F97: =F96/E96-1 -> 0.64475702 | G97: =G96/F96-1 -> 0.25429681 | H97: =H96/G96-1 -> 0.053387878 | I97: =Controlsheet!I103 -> 0.063 | J97: =Controlsheet!J103 -> 0.063 | K97: =Controlsheet!K103 -> 0.063 | L97: =Controlsheet!L103 -> 0.063 | M97: =Controlsheet!M103 -> 0.063 | N97: =Controlsheet!N103 -> 0.063 | O97: =Controlsheet!O103 -> 0.063 | P97: =Controlsheet!P103 -> 0.063 | ... R97: =Controlsheet!R103 -> 0.063
B99: Other Non Current Asset
B100: Other Non Current Asset | D100: =ConsolidatedBS!E21 -> 102.29 | E100: =ConsolidatedBS!F21 -> 139.41 | F100: =ConsolidatedBS!G21 -> 145.83 | G100: =ConsolidatedBS!H21 -> 188.77 | H100: =ConsolidatedBS!I21 -> 151.85 | I100: =H100*(1+I101) -> 151.85 | J100: =I100*(1+J101) -> 151.85 | K100: =J100*(1+K101) -> 151.85 | L100: =K100*(1+L101) -> 151.85 | M100: =L100*(1+M101) -> 151.85 | N100: =M100*(1+N101) -> 151.85 | O100: =N100*(1+O101) -> 151.85 | P100: =O100*(1+P101) -> 151.85 | ... R100: =Q100*(1+R101) -> 151.85
B101: % of Revenue | E101: =E100/D13 -> 0.015986744 | F101: =F100/E13 -> 0.014161236 | G101: =G100/F13 -> 0.013070741 | H101: =H100/G13 -> 0.0091831169 | I101: =Controlsheet!I109 -> 0 | J101: =Controlsheet!J109 -> 0 | K101: =Controlsheet!K109 -> 0 | L101: =Controlsheet!L109 -> 0 | M101: =Controlsheet!M109 -> 0 | N101: =Controlsheet!N109 -> 0 | O101: =Controlsheet!O109 -> 0 | P101: =Controlsheet!P109 -> 0 | ... R101: =Controlsheet!R109 -> 0
B103: Deferred Tax Asset
B104: Deferred Tax Asset | D104: =ConsolidatedBS!E19 -> 0 | E104: =ConsolidatedBS!F19 -> 0 | F104: =ConsolidatedBS!G19 -> 0 | G104: =ConsolidatedBS!H19 -> 12.8 | H104: =ConsolidatedBS!I19 -> 0 | I104: =H104*(1+I105) -> 0 | J104: =I104*(1+J105) -> 0 | K104: =J104*(1+K105) -> 0 | L104: =K104*(1+L105) -> 0 | M104: =L104*(1+M105) -> 0 | N104: =M104*(1+N105) -> 0 | O104: =N104*(1+O105) -> 0 | P104: =O104*(1+P105) -> 0 | ... R104: =Q104*(1+R105) -> 0
B105: YoY Growth % | E105: =IFERROR(E104/D104-1,0) -> 0 | F105: =IFERROR(F104/E104-1,0) -> 0 | G105: =IFERROR(G104/F104-1,0) -> 0 | H105: =IFERROR(H104/G104-1,0) -> -1 | I105: =Controlsheet!I115 -> 0 | J105: =Controlsheet!J115 -> 0 | K105: =Controlsheet!K115 -> 0 | L105: =Controlsheet!L115 -> 0 | M105: =Controlsheet!M115 -> 0 | N105: =Controlsheet!N115 -> 0 | O105: =Controlsheet!O115 -> 0 | P105: =Controlsheet!P115 -> 0 | ... R105: =Controlsheet!R115 -> 0
B107: Non-current tax assets
B108: Non-current tax assets | D108: =ConsolidatedBS!E20 -> 51.33 | E108: =ConsolidatedBS!F20 -> 83.12 | F108: =ConsolidatedBS!G20 -> 86.47 | G108: =ConsolidatedBS!H20 -> 103.41 | H108: =ConsolidatedBS!I20 -> 89.71 | I108: =H108*(1+I109) -> 89.71 | J108: =I108*(1+J109) -> 89.71 | K108: =J108*(1+K109) -> 89.71 | L108: =K108*(1+L109) -> 89.71 | M108: =L108*(1+M109) -> 89.71 | N108: =M108*(1+N109) -> 89.71 | O108: =N108*(1+O109) -> 89.71 | P108: =O108*(1+P109) -> 89.71 | ... R108: =Q108*(1+R109) -> 89.71
B109: YoY Growth % | E109: =E108/D108-1 -> 0.61932593 | F109: =F108/E108-1 -> 0.040303176 | G109: =G108/F108-1 -> 0.19590609 | H109: =H108/G108-1 -> -0.13248235 | I109: =Controlsheet!I121 -> 0 | J109: =Controlsheet!J121 -> 0 | K109: =Controlsheet!K121 -> 0 | L109: =Controlsheet!L121 -> 0 | M109: =Controlsheet!M121 -> 0 | N109: =Controlsheet!N121 -> 0 | O109: =Controlsheet!O121 -> 0 | P109: =Controlsheet!P121 -> 0 | ... R109: =Controlsheet!R121 -> 0
A111: # | B111: Depreciation Schedule
C114: 10
B116: Total Depreciation | I116: =SUM(I60,I67,I80,I89) -> 849.33 | J116: =SUM(J60,J67,J80,J89) -> 969.33 | K116: =SUM(K60,K67,K80,K89) -> 1089.33 | L116: =SUM(L60,L67,L80,L89) -> 1209.33 | M116: =SUM(M60,M67,M80,M89) -> 1329.33 | N116: =SUM(N60,N67,N80,N89) -> 1449.33 | O116: =SUM(O60,O67,O80,O89) -> 1569.33 | P116: =SUM(P60,P67,P80,P89) -> 1689.33 | ... R116: =SUM(R60,R67,R80,R89) -> 1929.33
B117: Total Net Depreciable Fixed Assets | I117: =SUM(I61,I68,I81,I90) -> 4205.31 | J117: =SUM(J61,J68,J81,J90) -> 4435.98 | K117: =SUM(K61,K68,K81,K90) -> 4546.65 | L117: =SUM(L61,L68,L81,L90) -> 4537.32 | M117: =SUM(M61,M68,M81,M90) -> 4407.99 | N117: =SUM(N61,N68,N81,N90) -> 4158.66 | O117: =SUM(O61,O68,O81,O90) -> 3789.33 | P117: =SUM(P61,P68,P81,P90) -> 3300 | ... R117: =SUM(R61,R68,R81,R90) -> 1961.34
B119: Depreciation % Sales | I119: =I116/I13 -> 0.039138004 | J119: =J116/J13 -> 0.039096479 | K119: =K116/K13 -> 0.038710573 | L119: =L116/L13 -> 0.038115218 | M119: =M116/M13 -> 0.037408334 | N119: =N116/N13 -> 0.036415378 | O119: =O116/O13 -> 0.035205766 | P119: =P116/P13 -> 0.033837322 | ... R119: =R116/R13 -> 0.030807181
B120: Depreciation % Net Fixed Assets | I120: =I116/I117 -> 0.20196609 | J120: =J116/J117 -> 0.21851541 | K120: =K116/K117 -> 0.23958959 | L120: =L116/L117 -> 0.26652958 | M120: =M116/M117 -> 0.30157283 | N120: =N116/N117 -> 0.34850889 | O120: =O116/O117 -> 0.41414445 | P120: =P116/P117 -> 0.51191818 | ... R120: =R116/R117 -> 0.98367953
B122: Depreciation Waterfall Schedule
B124: =H9 -> 2025 | H124: =SUM(H60,H67,H80,H89) -> 729.33 | I124: =H124 -> 729.33 | J124: =I124 -> 729.33 | K124: =J124 -> 729.33 | L124: =K124 -> 729.33 | M124: =L124 -> 729.33 | N124: =M124 -> 729.33 | O124: =N124 -> 729.33 | P124: =O124 -> 729.33 | ... R124: =Q124 -> 729.33
B125: =B124+1 -> 2026 | I125: =I116-I124 -> 120 | J125: =I125 -> 120 | K125: =J125 -> 120 | L125: =K125 -> 120 | M125: =L125 -> 120 | N125: =M125 -> 120 | O125: =N125 -> 120 | P125: =O125 -> 120 | Q125: =P125 -> 120 | R125: =Q125 -> 120
B126: =B125+1 -> 2027 | J126: =J116-I116 -> 120 | K126: =J126 -> 120 | L126: =K126 -> 120 | M126: =L126 -> 120 | N126: =M126 -> 120 | O126: =N126 -> 120 | P126: =O126 -> 120 | Q126: =P126 -> 120 | R126: =Q126 -> 120
B127: =B126+1 -> 2028 | K127: =K116-J116 -> 120 | L127: =K127 -> 120 | M127: =L127 -> 120 | N127: =M127 -> 120 | O127: =N127 -> 120 | P127: =O127 -> 120 | Q127: =P127 -> 120 | R127: =Q127 -> 120
B128: =B127+1 -> 2029 | L128: =L116-K116 -> 120 | M128: =L128 -> 120 | N128: =M128 -> 120 | O128: =N128 -> 120 | P128: =O128 -> 120 | Q128: =P128 -> 120 | R128: =Q128 -> 120
B129: =B128+1 -> 2030 | M129: =M116-L116 -> 120 | N129: =N116-M116 -> 120 | O129: =O116-N116 -> 120 | P129: =P116-O116 -> 120 | Q129: =Q116-P116 -> 120 | R129: =R116-Q116 -> 120
B130: Total Depreciation | H130: =SUM(H124:H129) -> 729.33 | I130: =SUM(I124:I129) -> 849.33 | J130: =SUM(J124:J129) -> 969.33 | K130: =SUM(K124:K129) -> 1089.33 | L130: =SUM(L124:L129) -> 1209.33 | M130: =SUM(M124:M129) -> 1329.33 | N130: =SUM(N124:N129) -> 1329.33 | O130: =SUM(O124:O129) -> 1329.33 | ... R130: =SUM(R124:R129) -> 1329.33
A132: # | B132: Tax Expense Schedule
B134: Revenue | H134: ='3StatementModel'!H13 -> 18870.35 | I134: ='3StatementModel'!I13 -> 21700.902 | J134: ='3StatementModel'!J13 -> 24793.281 | K134: ='3StatementModel'!K13 -> 28140.374 | L134: ='3StatementModel'!L13 -> 31728.272 | M134: ='3StatementModel'!M13 -> 35535.664 | N134: ='3StatementModel'!N13 -> 39799.944 | O134: ='3StatementModel'!O13 -> 44575.937 | ... R134: ='3StatementModel'!R13 -> 62625.983
B135: Less : Cost of Goods Sold | H135: ='3StatementModel'!H14*-1 -> -10297.08 | I135: ='3StatementModel'!I14*-1 -> -11935.496 | J135: ='3StatementModel'!J14*-1 -> -13785.064 | K135: ='3StatementModel'!K14*-1 -> -15814.89 | L135: ='3StatementModel'!L14*-1 -> -18021.658 | M135: ='3StatementModel'!M14*-1 -> -20397.471 | N135: ='3StatementModel'!N14*-1 -> -22845.168 | O135: ='3StatementModel'!O14*-1 -> -25586.588 | ... R135: ='3StatementModel'!R14*-1 -> -35947.314
B136: Less : SG&A Expense | H136: =SUM('3StatementModel'!H20:H24)*-1 -> -3861.24 | I136: =SUM('3StatementModel'!I20:I24)*-1 -> -4275.0778 | J136: =SUM('3StatementModel'!J20:J24)*-1 -> -4884.2764 | K136: =SUM('3StatementModel'!K20:K24)*-1 -> -5543.6537 | L136: =SUM('3StatementModel'!L20:L24)*-1 -> -6250.4695 | M136: =SUM('3StatementModel'!M20:M24)*-1 -> -7000.5259 | N136: =SUM('3StatementModel'!N20:N24)*-1 -> -7840.589 | O136: =SUM('3StatementModel'!O20:O24)*-1 -> -8781.4597 | ... R136: =SUM('3StatementModel'!R20:R24)*-1 -> -12337.319
B137: Less : Depreciation & Amortization | H137: ='3StatementModel'!H29*-1 -> -729.33 | I137: ='3StatementModel'!I29*-1 -> -849.33 | J137: ='3StatementModel'!J29*-1 -> -969.33 | K137: ='3StatementModel'!K29*-1 -> -1089.33 | L137: ='3StatementModel'!L29*-1 -> -1209.33 | M137: ='3StatementModel'!M29*-1 -> -1329.33 | N137: ='3StatementModel'!N29*-1 -> -1449.33 | O137: ='3StatementModel'!O29*-1 -> -1569.33 | ... R137: ='3StatementModel'!R29*-1 -> -1929.33
B138: Less : Interest Expense | H138: ='3StatementModel'!H34*-1 -> -54.34 | I138: ='3StatementModel'!I34*-1 -> -22.238487 | J138: ='3StatementModel'!J34*-1 -> -25.711568 | K138: ='3StatementModel'!K34*-1 -> -25.110945 | L138: ='3StatementModel'!L34*-1 -> -23.693931 | M138: ='3StatementModel'!M34*-1 -> -21.332504 | N138: ='3StatementModel'!N34*-1 -> -21.09397 | O138: ='3StatementModel'!O34*-1 -> -23.625247 | ... R138: ='3StatementModel'!R34*-1 -> -33.191771
B139: Earnings Before Tax | H139: =SUM(H134:H138) -> 3928.36 | I139: =SUM(I134:I138) -> 4618.7598 | J139: =SUM(J134:J138) -> 5128.8989 | K139: =SUM(K134:K138) -> 5667.3892 | L139: =SUM(L134:L138) -> 6223.1199 | M139: =SUM(M134:M138) -> 6787.0046 | N139: =SUM(N134:N138) -> 7643.7632 | O139: =SUM(O134:O138) -> 8614.9344 | ... R139: =SUM(R134:R138) -> 12378.828
B140: Less : Tax Expenses | H140: ='3StatementModel'!H39*-1 -> -1198.63 | I140: =I139*-I143 -> -1160.2325 | J140: =J139*-J143 -> -1288.3794 | K140: =K139*-K143 -> -1423.6482 | L140: =L139*-L143 -> -1563.2477 | M140: =M139*-M143 -> -1704.8956 | N140: =N139*-N143 -> -1920.1133 | O140: =O139*-O143 -> -2164.0715 | P140: =P139*-P143 -> -2440.922 | ... R140: =R139*-R143 -> -3109.5617
B141: Net Income | H141: =H139+H140 -> 2729.73 | I141: =I139+I140 -> 3458.5274 | J141: =J139+J140 -> 3840.5195 | K141: =K139+K140 -> 4243.741 | L141: =L139+L140 -> 4659.8722 | M141: =M139+M140 -> 5082.1091 | N141: =N139+N140 -> 5723.6499 | O141: =O139+O140 -> 6450.8629 | ... R141: =R139+R140 -> 9269.2666
B143: Marginal Tax Rate | I143: =Controlsheet!I129 -> 0.2512 | J143: =Controlsheet!J129 -> 0.2512 | K143: =Controlsheet!K129 -> 0.2512 | L143: =Controlsheet!L129 -> 0.2512 | M143: =Controlsheet!M129 -> 0.2512 | N143: =Controlsheet!N129 -> 0.2512 | O143: =Controlsheet!O129 -> 0.2512 | P143: =Controlsheet!P129 -> 0.2512 | ... R143: =Controlsheet!R129 -> 0.2512
A145: # | B145: Other Equity Schedule
B147: Other Equity - Beginning of the Year | I147: ='3StatementModel'!H82 -> 21269.07 | J147: =I150 -> 23648.123 | K147: =J150 -> 25979.955 | L147: =K150 -> 28222.353 | M147: =L150 -> 29974.741 | N147: =M150 -> 31500.695 | O147: =N150 -> 33199.307 | P147: =O150 -> 35093.031 | Q147: =P150 -> 37207.439 | R147: =Q150 -> 39571.167
B148: Add : Net Income | I148: ='3StatementModel'!I40 -> 5286.7843 | J148: ='3StatementModel'!J40 -> 5829.5801 | K148: ='3StatementModel'!K40 -> 6406.8505 | L148: ='3StatementModel'!L40 -> 7009.5523 | M148: ='3StatementModel'!M40 -> 7629.7736 | N148: ='3StatementModel'!N40 -> 8493.057 | O148: ='3StatementModel'!O40 -> 9468.6216 | P148: ='3StatementModel'!P40 -> 10572.037 | ... R148: ='3StatementModel'!R40 -> 13225.628
B149: Add : Dividend Paid | I149: =I148*-I152 -> -2907.7314 | J149: =J148*-J152 -> -3497.7481 | K149: =K148*-K152 -> -4164.4528 | L149: =L148*-L152 -> -5257.1643 | M149: =M148*-M152 -> -6103.8189 | N149: =N148*-N152 -> -6794.4456 | O149: =O148*-O152 -> -7574.8973 | P149: =P148*-P152 -> -8457.6294 | ... R149: =R148*-R152 -> -10580.502
...

Sheet 3StatementModel
B2: ='Input Sheet'!C5 -> Eicher Motors
B3: 3 Statement Model
H4: Current Case: | I4: 0
T7: CAGR
F8: Actual | I8: Explicit Forecast Period | T8: 5 Years | U8: 3 Years
B9: In INR Crores unless stated otherwise | D9: =Controlsheet!D9 -> 2021 | E9: =Controlsheet!E9 -> 2022 | F9: =Controlsheet!F9 -> 2023 | G9: =Controlsheet!G9 -> 2024 | H9: =Controlsheet!H9 -> 2025 | I9: =H9+1 -> 2026 | J9: =I9+1 -> 2027 | K9: =J9+1 -> 2028 | L9: =K9+1 -> 2029 | M9: =L9+1 -> 2030 | N9: =M9+1 -> 2031 | O9: =N9+1 -> 2032 | P9: =O9+1 -> 2033 | ... R9: =Q9+1 -> 2035
A11: # | B11: Income Statement
B13: Revenue | D13: =Schedules!D13 -> 8720.35 | E13: =Schedules!E13 -> 10297.83 | F13: =Schedules!F13 -> 14442.18 | G13: =Schedules!G13 -> 16535.78 | H13: =Schedules!H13 -> 18870.35 | I13: =Schedules!I13 -> 21700.902 | J13: =Schedules!J13 -> 24793.281 | K13: =Schedules!K13 -> 28140.374 | ... R13: =Schedules!R13 -> 62625.983 | T13: =_xlfn.RRI($M$9-$H$9,H13,M13) -> 0.13495044 | U13: =_xlfn.RRI($M$9-$J$9,J13,M13) -> 0.12748337
B14: Less: Cost of Goods Sold | D14: =Schedules!D20 -> 5112.27 | E14: =Schedules!E20 -> 5955.68 | F14: =Schedules!F20 -> 8211.9 | G14: =Schedules!G20 -> 8980.65 | H14: =Schedules!H20 -> 10297.08 | I14: =Schedules!I20 -> 11935.496 | J14: =Schedules!J20 -> 13785.064 | K14: =Schedules!K20 -> 15814.89 | ... R14: =Schedules!R20 -> 35947.314 | T14: =_xlfn.RRI($M$9-$H$9,H14,M14) -> 0.14649575 | U14: =_xlfn.RRI($M$9-$J$9,J14,M14) -> 0.13952147
B15: Gross Profit | D15: =D13-D14 -> 3608.08 | E15: =E13-E14 -> 4342.15 | F15: =F13-F14 -> 6230.28 | G15: =G13-G14 -> 7555.13 | H15: =H13-H14 -> 8573.27 | I15: =I13-I14 -> 9765.4061 | J15: =J13-J14 -> 11008.217 | K15: =K13-K14 -> 12325.484 | ... S15: =S13-S14 -> 0 | T15: =_xlfn.RRI($M$9-$H$9,H15,M15) -> 0.12043201 | U15: =_xlfn.RRI($M$9-$J$9,J15,M15) -> 0.11203645
B17: Gross Margins | D17: =D15/D13 -> 0.41375404 | E17: =E15/E13 -> 0.4216568 | F17: =F15/F13 -> 0.43139471 | G17: =G15/G13 -> 0.45689589 | H17: =H15/H13 -> 0.45432491 | I17: =I15/I13 -> 0.45 | J17: =J15/J13 -> 0.444 | K17: =K15/K13 -> 0.438 | ... R17: =R15/R13 -> 0.426
B19: Less: SG&A Expenses (Excluding Depreciation & Interest)
B20: Employee Benefit Expense | D20: =Schedules!D28 -> 843.23 | E20: =Schedules!E28 -> 821.02 | F20: =Schedules!F28 -> 1001.93 | G20: =Schedules!G28 -> 1235.69 | H20: =Schedules!H28 -> 1391.23 | I20: =Schedules!I28 -> 1627.5677 | J20: =Schedules!J28 -> 1859.4961 | K20: =Schedules!K28 -> 2110.5281 | ... R20: =Schedules!R28 -> 4696.9487 | T20: =_xlfn.RRI($M$9-$H$9,H20,M20) -> 0.13884693 | U20: =_xlfn.RRI($M$9-$J$9,J20,M20) -> 0.12748337
B21: Consumption of Stores and machinery spares | D21: =Schedules!D33 -> 139.51 | E21: =Schedules!E33 -> 198.56 | F21: =Schedules!F33 -> 262.25 | G21: =Schedules!G33 -> 239.14 | H21: =Schedules!H33 -> 286.56 | I21: =Schedules!I33 -> 368.91534 | J21: =Schedules!J33 -> 421.48578 | K21: =Schedules!K33 -> 478.38636 | ... R21: =Schedules!R33 -> 1064.6417 | T21: =_xlfn.RRI($M$9-$H$9,H21,M21) -> 0.16085923 | U21: =_xlfn.RRI($M$9-$J$9,J21,M21) -> 0.12748337
B22: Freight and handling charges | D22: =Schedules!D38 -> 121.1 | E22: =Schedules!E38 -> 180.97 | F22: =Schedules!F38 -> 272.83 | G22: =Schedules!G38 -> 265.57 | H22: =Schedules!H38 -> 330.64 | I22: =Schedules!I38 -> 347.21444 | J22: =Schedules!J38 -> 396.6925 | K22: =Schedules!K38 -> 450.24598 | ... R22: =Schedules!R38 -> 1002.0157 | T22: =_xlfn.RRI($M$9-$H$9,H22,M22) -> 0.11451471 | U22: =_xlfn.RRI($M$9-$J$9,J22,M22) -> 0.12748337
B23: Selling and distribution expenses | D23: =Schedules!D43 -> 180.93 | E23: =Schedules!E43 -> 284.69 | F23: =Schedules!F43 -> 426.39 | G23: =Schedules!G43 -> 546.2 | H23: =Schedules!H43 -> 760.88 | I23: =Schedules!I43 -> 607.62527 | J23: =Schedules!J43 -> 694.21187 | K23: =Schedules!K43 -> 787.93047 | ... R23: =Schedules!R43 -> 1753.5275 | T23: =_xlfn.RRI($M$9-$H$9,H23,M23) -> 0.055118555 | U23: =_xlfn.RRI($M$9-$J$9,J23,M23) -> 0.12748337
B24: Other SG&A Expenses | D24: =Schedules!D48 -> 541.98 | E24: =Schedules!E48 -> 684.66 | F24: =Schedules!F48 -> 823.3 | G24: =Schedules!G48 -> 941.62 | H24: =Schedules!H48 -> 1091.93 | I24: =Schedules!I48 -> 1323.7551 | J24: =Schedules!J48 -> 1512.3901 | K24: =Schedules!K48 -> 1716.5628 | ... R24: =Schedules!R48 -> 3820.1849 | T24: =_xlfn.RRI($M$9-$H$9,H24,M24) -> 0.1469907 | U24: =_xlfn.RRI($M$9-$J$9,J24,M24) -> 0.12748337
B25: Earnings Before Interest,Taxes,Depreciation & Amortization | D25: =D15-SUM(D20:D24) -> 1781.33 | E25: =E15-SUM(E20:E24) -> 2172.25 | F25: =F15-SUM(F20:F24) -> 3443.58 | G25: =G15-SUM(G20:G24) -> 4326.91 | H25: =H15-SUM(H20:H24) -> 4712.03 | I25: =I15-SUM(I20:I24) -> 5490.3283 | J25: =J15-SUM(J20:J24) -> 6123.9404 | K25: =K15-SUM(K20:K24) -> 6781.8301 | ... R25: =R15-SUM(R20:R24) -> 14341.35 | T25: =_xlfn.RRI($M$9-$H$9,H25,M25) -> 0.11547123 | U25: =_xlfn.RRI($M$9-$J$9,J25,M25) -> 0.09940149
B27: EBITDA Margins | D27: =D25/D13 -> 0.20427276 | E27: =E25/E13 -> 0.2109425 | F27: =F25/F13 -> 0.23843907 | G27: =G25/G13 -> 0.26166954 | H27: =H25/H13 -> 0.24970549 | I27: =I25/I13 -> 0.253 | J27: =J25/J13 -> 0.247 | K27: =K25/K13 -> 0.241 | ... R27: =R25/R13 -> 0.229
B29: Less : Depreciation & Amortization | D29: ='ConsolidatedP&L'!E35*-1 -> 450.73 | E29: ='ConsolidatedP&L'!F35*-1 -> 451.93 | F29: ='ConsolidatedP&L'!G35*-1 -> 526.21 | G29: ='ConsolidatedP&L'!H35*-1 -> 597.6 | H29: ='ConsolidatedP&L'!I35*-1 -> 729.33 | I29: =Schedules!I116 -> 849.33 | J29: =Schedules!J116 -> 969.33 | K29: =Schedules!K116 -> 1089.33 | L29: =Schedules!L116 -> 1209.33 | M29: =Schedules!M116 -> 1329.33 | N29: =Schedules!N116 -> 1449.33 | O29: =Schedules!O116 -> 1569.33 | P29: =Schedules!P116 -> 1689.33 | ... R29: =Schedules!R116 -> 1929.33 | T29: =_xlfn.RRI($M$9-$H$9,H29,M29) -> 0.12756541 | U29: =_xlfn.RRI($M$9-$J$9,J29,M29) -> 0.11101618
B30: Earnings Before Interest & Taxes | D30: =D25-D29 -> 1330.6 | E30: =E25-E29 -> 1720.32 | F30: =F25-F29 -> 2917.37 | G30: =G25-G29 -> 3729.31 | H30: =H25-H29 -> 3982.7 | I30: =I25-I29 -> 4640.9983 | J30: =J25-J29 -> 5154.6104 | K30: =K25-K29 -> 5692.5001 | ... R30: =R25-R29 -> 12412.02 | T30: =_xlfn.RRI($M$9-$H$9,H30,M30) -> 0.1131987 | U30: =_xlfn.RRI($M$9-$J$9,J30,M30) -> 0.097189733
B32: EBIT Margins | D32: =D30/D13 -> 0.15258562 | E32: =E30/E13 -> 0.16705655 | F32: =F30/F13 -> 0.20200344 | G32: =G30/G13 -> 0.22552973 | H32: =H30/H13 -> 0.21105597 | I32: =I30/I13 -> 0.213862 | J32: =J30/J13 -> 0.20790352 | K32: =K30/K13 -> 0.20228943 | ... R32: =R30/R13 -> 0.19819282
B34: Less : Interest | D34: ='ConsolidatedP&L'!E38*-1 -> 16.45 | E34: ='ConsolidatedP&L'!F38*-1 -> 18.78 | F34: ='ConsolidatedP&L'!G38*-1 -> 28.02 | G34: ='ConsolidatedP&L'!H38*-1 -> 50.88 | H34: ='ConsolidatedP&L'!I38*-1 -> 54.34 | I34: =Schedules!I247 -> 22.238487 | J34: =Schedules!J247 -> 25.711568 | K34: =Schedules!K247 -> 25.110945 | L34: =Schedules!L247 -> 23.693931 | M34: =Schedules!M247 -> 21.332504 | N34: =Schedules!N247 -> 21.09397 | O34: =Schedules!O247 -> 23.625247 | P34: =Schedules!P247 -> 26.460276 | ... R34: =Schedules!R247 -> 33.191771
B35: Add : Other Income | D35: ='ConsolidatedP&L'!E39 -> 453.19 | E35: ='ConsolidatedP&L'!F39 -> 440.82 | F35: ='ConsolidatedP&L'!G39 -> 595.11 | G35: ='ConsolidatedP&L'!H39 -> 1075.87 | H35: ='ConsolidatedP&L'!I39 -> 1304.9 | I35: =Schedules!I254 -> 1128.4469 | J35: =Schedules!J254 -> 1289.2506 | K35: =Schedules!K254 -> 1463.2995 | L35: =Schedules!L254 -> 1649.8701 | M35: =Schedules!M254 -> 1847.8545 | N35: =Schedules!N254 -> 2069.5971 | O35: =Schedules!O254 -> 2317.9487 | P35: =Schedules!P254 -> 2596.1026 | ... R35: =Schedules!R254 -> 3256.5511
B36: Share of profit of joint venture (VE Commercial Vehicles Limited) | D36: ='ConsolidatedP&L'!E42 -> 31.13 | E36: ='ConsolidatedP&L'!F42 -> 60.15 | F36: ='ConsolidatedP&L'!G42 -> 315.17 | G36: ='ConsolidatedP&L'!H42 -> 447.72 | H36: ='ConsolidatedP&L'!I42 -> 699.81 | I36: =H36 -> 699.81 | J36: =I36 -> 699.81 | K36: =J36 -> 699.81 | L36: =K36 -> 699.81 | M36: =L36 -> 699.81 | N36: =M36 -> 699.81 | O36: =N36 -> 699.81 | P36: =O36 -> 699.81 | ... R36: =Q36 -> 699.81
B37: Profit Before Tax | D37: =D30-D34+SUM(D35:D36) -> 1798.47 | E37: =E30-E34+SUM(E35:E36) -> 2202.51 | F37: =F30-F34+SUM(F35:F36) -> 3799.63 | G37: =G30-G34+SUM(G35:G36) -> 5202.02 | H37: =H30-H34+SUM(H35:H36) -> 5933.07 | I37: =I30-I34+SUM(I35:I36) -> 6447.0168 | J37: =J30-J34+SUM(J35:J36) -> 7117.9595 | K37: =K30-K34+SUM(K35:K36) -> 7830.4987 | ... R37: =R30-R34+SUM(R35:R36) -> 16335.189
B39: Less: Taxes | D39: ='ConsolidatedP&L'!E45*-1 -> 451.5 | E39: ='ConsolidatedP&L'!F45*-1 -> 525.91 | F39: ='ConsolidatedP&L'!G45*-1 -> 885.69 | G39: ='ConsolidatedP&L'!H45*-1 -> 1201.01 | H39: ='ConsolidatedP&L'!I45*-1 -> 1198.63 | I39: =Schedules!I140*-1 -> 1160.2325 | J39: =Schedules!J140*-1 -> 1288.3794 | K39: =Schedules!K140*-1 -> 1423.6482 | L39: =Schedules!L140*-1 -> 1563.2477 | M39: =Schedules!M140*-1 -> 1704.8956 | N39: =Schedules!N140*-1 -> 1920.1133 | O39: =Schedules!O140*-1 -> 2164.0715 | P39: =Schedules!P140*-1 -> 2440.922 | ... R39: =Schedules!R140*-1 -> 3109.5617 | T39: =_xlfn.RRI($M$9-$H$9,H39,M39) -> 0.073006932 | U39: =_xlfn.RRI($M$9-$J$9,J39,M39) -> 0.097871059
B40: Net Income | D40: =D37-D39 -> 1346.97 | E40: =E37-E39 -> 1676.6 | F40: =F37-F39 -> 2913.94 | G40: =G37-G39 -> 4001.01 | H40: =H37-H39 -> 4734.44 | I40: =I37-I39 -> 5286.7843 | J40: =J37-J39 -> 5829.5801 | K40: =K37-K39 -> 6406.8505 | ... R40: =R37-R39 -> 13225.628 | T40: =_xlfn.RRI($M$9-$H$9,H40,M40) -> 0.10014165 | U40: =_xlfn.RRI($M$9-$J$9,J40,M40) -> 0.093850895
B42: Sales Growth % | E42: =IFERROR(E13/D13-1,"NM") -> 0.18089641 | F42: =IFERROR(F13/E13-1,"NM") -> 0.40244887 | G42: =IFERROR(G13/F13-1,"NM") -> 0.14496426 | H42: =IFERROR(H13/G13-1,"NM") -> 0.14118294 | I42: =IFERROR(I13/H13-1,"NM") -> 0.15 | J42: =IFERROR(J13/I13-1,"NM") -> 0.1425 | K42: =IFERROR(K13/J13-1,"NM") -> 0.135 | L42: =IFERROR(L13/K13-1,"NM") -> 0.1275 | ... R42: =IFERROR(R13/Q13-1,"NM") -> 0.12
B43: Gross Profit Margins % | D43: =IFERROR(D15/D13,"NM") -> 0.41375404 | E43: =IFERROR(E15/E13,"NM") -> 0.4216568 | F43: =IFERROR(F15/F13,"NM") -> 0.43139471 | G43: =IFERROR(G15/G13,"NM") -> 0.45689589 | H43: =IFERROR(H15/H13,"NM") -> 0.45432491 | I43: =IFERROR(I15/I13,"NM") -> 0.45 | J43: =IFERROR(J15/J13,"NM") -> 0.444 | K43: =IFERROR(K15/K13,"NM") -> 0.438 | ... R43: =IFERROR(R15/R13,"NM") -> 0.426
B44: EBITDA Margins % | D44: =IFERROR(D25/D13,"NM") -> 0.20427276 | E44: =IFERROR(E25/E13,"NM") -> 0.2109425 | F44: =IFERROR(F25/F13,"NM") -> 0.23843907 | G44: =IFERROR(G25/G13,"NM") -> 0.26166954 | H44: =IFERROR(H25/H13,"NM") -> 0.24970549 | I44: =IFERROR(I25/I13,"NM") -> 0.253 | J44: =IFERROR(J25/J13,"NM") -> 0.247 | K44: =IFERROR(K25/K13,"NM") -> 0.241 | ... R44: =IFERROR(R25/R13,"NM") -> 0.229
B45: EBIT Margins % | D45: =IFERROR(D30/D13,"NM") -> 0.15258562 | E45: =IFERROR(E30/E13,"NM") -> 0.16705655 | F45: =IFERROR(F30/F13,"NM") -> 0.20200344 | G45: =IFERROR(G30/G13,"NM") -> 0.22552973 | H45: =IFERROR(H30/H13,"NM") -> 0.21105597 | I45: =IFERROR(I30/I13,"NM") -> 0.213862 | J45: =IFERROR(J30/J13,"NM") -> 0.20790352 | K45: =IFERROR(K30/K13,"NM") -> 0.20228943 | ... R45: =IFERROR(R30/R13,"NM") -> 0.19819282
B46: Actual Tax Rate % | D46: =IFERROR(D39/D37,"NM") -> 0.25104672 | E46: =IFERROR(E39/E37,"NM") -> 0.23877758 | F46: =IFERROR(F39/F37,"NM") -> 0.23309901 | G46: =IFERROR(G39/G37,"NM") -> 0.23087378 | H46: =IFERROR(H39/H37,"NM") -> 0.20202526 | I46: =IFERROR(I39/I37,"NM") -> 0.17996424 | J46: =IFERROR(J39/J37,"NM") -> 0.18100404 | K46: =IFERROR(K39/K37,"NM") -> 0.18180811 | ... R46: =IFERROR(R39/R37,"NM") -> 0.19035969
B47: Net Income Margin % | D47: =IFERROR(D40/D13,"NM") -> 0.15446284 | E47: =IFERROR(E40/E13,"NM") -> 0.162811 | F47: =IFERROR(F40/F13,"NM") -> 0.20176594 | G47: =IFERROR(G40/G13,"NM") -> 0.24196077 | H47: =IFERROR(H40/H13,"NM") -> 0.25089307 | I47: =IFERROR(I40/I13,"NM") -> 0.24362048 | J47: =IFERROR(J40/J13,"NM") -> 0.23512741 | K47: =IFERROR(K40/K13,"NM") -> 0.22767467 | ... R47: =IFERROR(R40/R13,"NM") -> 0.21118435
A49: # | B49: Balance Sheet
B51: Assets
B52: Non Current Assets
B53: Property Plant & Equipment | D53: =ConsolidatedBS!E6 -> 1894.51 | E53: =ConsolidatedBS!F6 -> 1910.78 | F53: =ConsolidatedBS!G6 -> 1999.65 | G53: =ConsolidatedBS!H6 -> 1950.26 | H53: =ConsolidatedBS!I6 -> 2268.7 | I53: =Schedules!I61 -> 2919.4431 | J53: =Schedules!J61 -> 3450.1861 | K53: =Schedules!K61 -> 3860.9292 | L53: =Schedules!L61 -> 4151.6722 | M53: =Schedules!M61 -> 4322.4153 | N53: =Schedules!N61 -> 4373.1584 | O53: =Schedules!O61 -> 4303.9014 | P53: =Schedules!P61 -> 4114.6445 | ... R53: =Schedules!R61 -> 3376.1306
B54: Right of Use Asset | D54: =ConsolidatedBS!E10 -> 197.62 | E54: =ConsolidatedBS!F10 -> 183.66 | F54: =ConsolidatedBS!G10 -> 226.13 | G54: =ConsolidatedBS!H10 -> 271.99 | H54: =ConsolidatedBS!I10 -> 317.04 | I54: =Schedules!I68 -> 257.05339 | J54: =Schedules!J68 -> 197.06678 | K54: =Schedules!K68 -> 137.08017 | L54: =Schedules!L68 -> 77.093563 | M54: =Schedules!M68 -> 17.106954 | N54: =Schedules!N68 -> -42.879655 | O54: =Schedules!O68 -> -102.86626 | P54: =Schedules!P68 -> -162.85287 | ... R54: =Schedules!R68 -> -282.82609
B55: Capital Work in Progress | D55: =ConsolidatedBS!E7 -> 63.91 | E55: =ConsolidatedBS!F7 -> 133.98 | F55: =ConsolidatedBS!G7 -> 77.75 | G55: =ConsolidatedBS!H7 -> 211.65 | H55: =ConsolidatedBS!I7 -> 110.3 | I55: =Schedules!I74 -> 0 | J55: =Schedules!J74 -> 0 | K55: =Schedules!K74 -> 0 | L55: =Schedules!L74 -> 0 | M55: =Schedules!M74 -> 0 | N55: =Schedules!N74 -> 0 | O55: =Schedules!O74 -> 0 | P55: =Schedules!P74 -> 0 | ... R55: =Schedules!R74 -> 0
B56: Intangible assets | D56: =ConsolidatedBS!E9 -> 341.17 | E56: =ConsolidatedBS!F9 -> 329.84 | F56: =ConsolidatedBS!G9 -> 464.21 | G56: =ConsolidatedBS!H9 -> 692.13 | H56: =ConsolidatedBS!I9 -> 887.73 | I56: =Schedules!I81 -> 719.76409 | J56: =Schedules!J81 -> 551.79818 | K56: =Schedules!K81 -> 383.83227 | L56: =Schedules!L81 -> 215.86635 | M56: =Schedules!M81 -> 47.900443 | N56: =Schedules!N81 -> -120.06547 | O56: =Schedules!O81 -> -288.03138 | P56: =Schedules!P81 -> -455.99729 | ... R56: =Schedules!R81 -> -791.92911 | S56: =Schedules!N81 -> -120.06547
B57: Intangible assets under development | D57: =ConsolidatedBS!E11 -> 250.38 | E57: =ConsolidatedBS!F11 -> 370.8 | F57: =ConsolidatedBS!G11 -> 394.32 | G57: =ConsolidatedBS!H11 -> 343.45 | H57: =ConsolidatedBS!I11 -> 381.17 | I57: =Schedules!I90 -> 309.04946 | J57: =Schedules!J90 -> 236.92892 | K57: =Schedules!K90 -> 164.80838 | L57: =Schedules!L90 -> 92.687842 | M57: =Schedules!M90 -> 20.567303 | N57: =Schedules!N90 -> -51.553237 | O57: =Schedules!O90 -> -123.67378 | P57: =Schedules!P90 -> -195.79432 | ... R57: =Schedules!R90 -> -340.03539
B58: Non Current Financial Asset | D58: =ConsolidatedBS!E13 -> 2848.92 | E58: =ConsolidatedBS!F13 -> 7368.9 | F58: =ConsolidatedBS!G13 -> 12120.05 | G58: =ConsolidatedBS!H13 -> 15202.14 | H58: =ConsolidatedBS!I13 -> 16013.75 | I58: =Schedules!I96 -> 17022.616 | J58: =Schedules!J96 -> 18095.041 | K58: =Schedules!K96 -> 19235.029 | L58: =Schedules!L96 -> 20446.835 | M58: =Schedules!M96 -> 21734.986 | N58: =Schedules!N96 -> 23104.29 | O58: =Schedules!O96 -> 24559.861 | P58: =Schedules!P96 -> 26107.132 | ... R58: =Schedules!R96 -> 29500.25
B59: Other Non Current Asset | D59: =ConsolidatedBS!E21 -> 102.29 | E59: =ConsolidatedBS!F21 -> 139.41 | F59: =ConsolidatedBS!G21 -> 145.83 | G59: =ConsolidatedBS!H21 -> 188.77 | H59: =ConsolidatedBS!I21 -> 151.85 | I59: =Schedules!I100 -> 151.85 | J59: =Schedules!J100 -> 151.85 | K59: =Schedules!K100 -> 151.85 | L59: =Schedules!L100 -> 151.85 | M59: =Schedules!M100 -> 151.85 | N59: =Schedules!N100 -> 151.85 | O59: =Schedules!O100 -> 151.85 | P59: =Schedules!P100 -> 151.85 | ... R59: =Schedules!R100 -> 151.85
B60: Deferred Tax Asset | D60: =ConsolidatedBS!E19 -> 0 | E60: =ConsolidatedBS!F19 -> 0 | F60: =ConsolidatedBS!G19 -> 0 | G60: =ConsolidatedBS!H19 -> 12.8 | H60: =ConsolidatedBS!I19 -> 0 | I60: =Schedules!I104 -> 0 | J60: =Schedules!J104 -> 0 | K60: =Schedules!K104 -> 0 | L60: =Schedules!L104 -> 0 | M60: =Schedules!M104 -> 0 | N60: =Schedules!N104 -> 0 | O60: =Schedules!O104 -> 0 | P60: =Schedules!P104 -> 0 | ... R60: =Schedules!R104 -> 0
B61: Non-current tax assets | D61: =ConsolidatedBS!E20 -> 51.33 | E61: =ConsolidatedBS!F20 -> 83.12 | F61: =ConsolidatedBS!G20 -> 86.47 | G61: =ConsolidatedBS!H20 -> 103.41 | H61: =ConsolidatedBS!I20 -> 89.71 | I61: =Schedules!I108 -> 89.71 | J61: =Schedules!J108 -> 89.71 | K61: =Schedules!K108 -> 89.71 | L61: =Schedules!L108 -> 89.71 | M61: =Schedules!M108 -> 89.71 | N61: =Schedules!N108 -> 89.71 | O61: =Schedules!O108 -> 89.71 | P61: =Schedules!P108 -> 89.71 | ... R61: =Schedules!R108 -> 89.71
B62: Total Non Current Assets | D62: =SUM(D53:D61) -> 5750.13 | E62: =SUM(E53:E61) -> 10520.49 | F62: =SUM(F53:F61) -> 15514.41 | G62: =SUM(G53:G61) -> 18976.6 | H62: =SUM(H53:H61) -> 20220.25 | I62: =SUM(I53:I61) -> 21469.486 | J62: =SUM(J53:J61) -> 22772.581 | K62: =SUM(K53:K61) -> 24023.239 | ... R62: =SUM(R53:R61) -> 31703.15 | S62: =SUM(S52:S56) -> -120.06547
B64: =ConsolidatedBS!B24 -> Current assets :
B65: =ConsolidatedBS!B25 -> Inventories | D65: =ConsolidatedBS!E25 -> 874.6 | E65: =ConsolidatedBS!F25 -> 1132.4 | F65: =ConsolidatedBS!G25 -> 1278.44 | G65: =ConsolidatedBS!H25 -> 1409.64 | H65: =ConsolidatedBS!I25 -> 1563.75 | I65: =Schedules!I164 -> 1783.6358 | J65: =Schedules!J164 -> 2037.8039 | K65: =Schedules!K164 -> 2312.9075 | L65: =Schedules!L164 -> 2607.8032 | M65: =Schedules!M164 -> 2920.7395 | N65: =Schedules!N164 -> 3271.2283 | O65: =Schedules!O164 -> 3663.7757 | P65: =Schedules!P164 -> 4103.4288 | ... R65: =Schedules!R164 -> 5147.341
B66: =ConsolidatedBS!B26 -> Trade receivables | D66: =ConsolidatedBS!E26 -> 158.16 | E66: =ConsolidatedBS!F26 -> 302.04 | F66: =ConsolidatedBS!G26 -> 368.92 | G66: =ConsolidatedBS!H26 -> 373.78 | H66: =ConsolidatedBS!I26 -> 549.64 | I66: =Schedules!I158 -> 713.45433 | J66: =Schedules!J158 -> 815.12157 | K66: =Schedules!K158 -> 770.96915 | L66: =Schedules!L158 -> 869.26772 | M66: =Schedules!M158 -> 973.57985 | N66: =Schedules!N158 -> 1090.4094 | O66: =Schedules!O158 -> 1221.2586 | P66: =Schedules!P158 -> 1367.8096 | ... R66: =Schedules!R158 -> 1715.7803
B67: =ConsolidatedBS!B27 -> Financial Assets
B68: =ConsolidatedBS!B28 -> Investments (Current) | D68: =ConsolidatedBS!E28 -> 1076.08 | E68: =ConsolidatedBS!F28 -> 424.69 | F68: =ConsolidatedBS!G28 -> 219.89 | G68: =ConsolidatedBS!H28 -> 180.92 | H68: =ConsolidatedBS!I28 -> 847.55 | I68: =H68 -> 847.55 | J68: =I68 -> 847.55 | K68: =J68 -> 847.55 | L68: =K68 -> 847.55 | M68: =L68 -> 847.55 | N68: =M68 -> 847.55 | O68: =N68 -> 847.55 | P68: =O68 -> 847.55 | ... R68: =Q68 -> 847.55
B69: =ConsolidatedBS!B29 -> Loans / Bill discounting | D69: =ConsolidatedBS!E29 -> 459.16 | E69: =ConsolidatedBS!F29 -> 676.79 | F69: =ConsolidatedBS!G29 -> 588.94 | G69: =ConsolidatedBS!H29 -> 476.88 | H69: =ConsolidatedBS!I29 -> 445.96 | I69: =H69 -> 445.96 | J69: =I69 -> 445.96 | K69: =J69 -> 445.96 | L69: =K69 -> 445.96 | M69: =L69 -> 445.96 | N69: =M69 -> 445.96 | O69: =N69 -> 445.96 | P69: =O69 -> 445.96 | ... R69: =Q69 -> 445.96
B70: =ConsolidatedBS!B30 -> Other financial assets (Current) | D70: =ConsolidatedBS!E30 -> 214.93 | E70: =ConsolidatedBS!F30 -> 65.75 | F70: =ConsolidatedBS!G30 -> 125.96 | G70: =ConsolidatedBS!H30 -> 1253.32 | H70: =ConsolidatedBS!I30 -> 2868.12 | I70: =H70 -> 2868.12 | J70: =I70 -> 2868.12 | K70: =J70 -> 2868.12 | L70: =K70 -> 2868.12 | M70: =L70 -> 2868.12 | N70: =M70 -> 2868.12 | O70: =N70 -> 2868.12 | P70: =O70 -> 2868.12 | ... R70: =Q70 -> 2868.12
B71: =ConsolidatedBS!B31 -> Other current assets | D71: =ConsolidatedBS!E31 -> 195.19 | E71: =ConsolidatedBS!F31 -> 295.2 | F71: =ConsolidatedBS!G31 -> 335.5 | G71: =ConsolidatedBS!H31 -> 310.48 | H71: =ConsolidatedBS!I31 -> 416.13 | I71: =Schedules!I170 -> 477.41985 | J71: =Schedules!J170 -> 545.45218 | K71: =Schedules!K170 -> 619.08823 | L71: =Schedules!L170 -> 698.02198 | M71: =Schedules!M170 -> 781.78462 | N71: =Schedules!N170 -> 875.59877 | O71: =Schedules!O170 -> 980.67062 | P71: =Schedules!P170 -> 1098.3511 | ... R71: =Schedules!R170 -> 1377.7716
B72: =ConsolidatedBS!B32 -> Cash and cash equivalents | D72: =D148 -> 93 | E72: =E148 -> 44.6 | F72: =F148 -> 55.4 | G72: =G148 -> 102 | H72: =H148 -> 223 | I72: =I148 -> 1423.5211 | J72: =J148 -> 2481.2341 | K72: =K148 -> 3654.9458 | ... R72: =R148 -> 10544.46
B73: =ConsolidatedBS!B33 -> Bank balances other than C&CE | D73: =ConsolidatedBS!E33 -> 5736.24 | E73: =ConsolidatedBS!F33 -> 2671.94 | F73: =ConsolidatedBS!G33 -> 676.77 | G73: =ConsolidatedBS!H33 -> 39.1 | H73: =ConsolidatedBS!I33 -> 44.05 | I73: =H73 -> 44.05 | J73: =I73 -> 44.05 | K73: =J73 -> 44.05 | L73: =K73 -> 44.05 | M73: =L73 -> 44.05 | N73: =M73 -> 44.05 | O73: =N73 -> 44.05 | P73: =O73 -> 44.05 | ... R73: =Q73 -> 44.05
B74: Total Current Assets | D74: =SUM(D65:D66,D68:D73) -> 8807.36 | E74: =SUM(E65:E66,E68:E73) -> 5613.41 | F74: =SUM(F65:F66,F68:F73) -> 3649.82 | G74: =SUM(G65:G66,G68:G73) -> 4146.12 | H74: =SUM(H65:H66,H68:H73) -> 6958.2 | I74: =SUM(I65:I66,I68:I73) -> 8603.7111 | J74: =SUM(J65:J66,J68:J73) -> 10085.292 | K74: =SUM(K65:K66,K68:K73) -> 11563.591 | ... R74: =SUM(R65:R66,R68:R73) -> 22991.033
B76: Total Assets | D76: =D62+D74 -> 14557.49 | E76: =E62+E74 -> 16133.9 | F76: =F62+F74 -> 19164.23 | G76: =G62+G74 -> 23122.72 | H76: =H62+H74 -> 27178.45 | I76: =I62+I74 -> 30073.197 | J76: =J62+J74 -> 32857.873 | K76: =K62+K74 -> 35586.829 | ... R76: =R62+R74 -> 54694.182
B78: Equity & Liabilities
B80: Equity
B81: =ConsolidatedBS!B40 -> Equity share capital | D81: =ConsolidatedBS!E40 -> 27.33 | E81: =ConsolidatedBS!F40 -> 27.34 | F81: =ConsolidatedBS!G40 -> 27.35 | G81: =ConsolidatedBS!H40 -> 27.38 | H81: =ConsolidatedBS!I40 -> 27.42 | I81: =H81 -> 27.42 | J81: =I81 -> 27.42 | K81: =J81 -> 27.42 | L81: =K81 -> 27.42 | M81: =L81 -> 27.42 | N81: =M81 -> 27.42 | O81: =N81 -> 27.42 | P81: =O81 -> 27.42 | ... R81: =Q81 -> 27.42
B82: =ConsolidatedBS!B41 -> Other equity | D82: =ConsolidatedBS!E41 -> 11410.75 | E82: =ConsolidatedBS!F41 -> 12580.66 | F82: =ConsolidatedBS!G41 -> 14962.93 | G82: =ConsolidatedBS!H41 -> 18018.15 | H82: =ConsolidatedBS!I41 -> 21269.07 | I82: =Schedules!I150 -> 23648.123 | J82: =Schedules!J150 -> 25979.955 | K82: =Schedules!K150 -> 28222.353 | L82: =Schedules!L150 -> 29974.741 | M82: =Schedules!M150 -> 31500.695 | N82: =Schedules!N150 -> 33199.307 | O82: =Schedules!O150 -> 35093.031 | P82: =Schedules!P150 -> 37207.439 | ... R82: =Schedules!R150 -> 42216.293 | T82: =_xlfn.RRI($M$9-$H$9,H82,M82) -> 0.081718677 | U82: =_xlfn.RRI($M$9-$J$9,J82,M82) -> 0.066335618
B83: =ConsolidatedBS!B42 -> Total equity | D83: =D81+D82 -> 11438.08 | E83: =E81+E82 -> 12608 | F83: =F81+F82 -> 14990.28 | G83: =G81+G82 -> 18045.53 | H83: =H81+H82 -> 21296.49 | I83: =I81+I82 -> 23675.543 | J83: =J81+J82 -> 26007.375 | K83: =K81+K82 -> 28249.773 | ... R83: =R81+R82 -> 42243.713
B85: =ConsolidatedBS!B44 -> Non-current liabilities:
B86: =ConsolidatedBS!B46 -> Borrowings | D86: =ConsolidatedBS!E46 -> 0 | E86: =ConsolidatedBS!F46 -> 0 | F86: =ConsolidatedBS!G46 -> 62.96 | G86: =ConsolidatedBS!H46 -> 163.46 | H86: =ConsolidatedBS!I46 -> 184.36 | I86: =Schedules!I234 -> 217.00902 | J86: =Schedules!J234 -> 192.14793 | K86: =Schedules!K234 -> 154.77206 | L86: =Schedules!L234 -> 103.11688 | M86: =Schedules!M234 -> 35.535664 | N86: =Schedules!N234 -> 39.799944 | O86: =Schedules!O234 -> 44.575937 | P86: =Schedules!P234 -> 49.92505 | ... R86: =Schedules!R234 -> 62.625983
B87: =ConsolidatedBS!B47 -> Lease liability | D87: =ConsolidatedBS!E47 -> 46.12 | E87: =ConsolidatedBS!F47 -> 35.32 | F87: =ConsolidatedBS!G47 -> 67.79 | G87: =ConsolidatedBS!H47 -> 107.98 | H87: =ConsolidatedBS!I47 -> 123.81 | I87: =H87 -> 123.81 | J87: =I87 -> 123.81 | K87: =J87 -> 123.81 | L87: =K87 -> 123.81 | M87: =L87 -> 123.81 | N87: =M87 -> 123.81 | O87: =N87 -> 123.81 | P87: =O87 -> 123.81 | ... R87: =Q87 -> 123.81
B88: =ConsolidatedBS!B48 -> Other financial liabilities | D88: =ConsolidatedBS!E48 -> 14.62 | E88: =ConsolidatedBS!F48 -> 14.82 | F88: =ConsolidatedBS!G48 -> 15.51 | G88: =ConsolidatedBS!H48 -> 15.07 | H88: =ConsolidatedBS!I48 -> 29.24 | I88: =H88 -> 29.24 | J88: =I88 -> 29.24 | K88: =J88 -> 29.24 | L88: =K88 -> 29.24 | M88: =L88 -> 29.24 | N88: =M88 -> 29.24 | O88: =N88 -> 29.24 | P88: =O88 -> 29.24 | ... R88: =Q88 -> 29.24
B89: =ConsolidatedBS!B49 -> Provisions | D89: =ConsolidatedBS!E49 -> 22.56 | E89: =ConsolidatedBS!F49 -> 67.96 | F89: =ConsolidatedBS!G49 -> 102.46 | G89: =ConsolidatedBS!H49 -> 175.02 | H89: =ConsolidatedBS!I49 -> 194.91 | I89: =H89 -> 194.91 | J89: =I89 -> 194.91 | K89: =J89 -> 194.91 | L89: =K89 -> 194.91 | M89: =L89 -> 194.91 | N89: =M89 -> 194.91 | O89: =N89 -> 194.91 | P89: =O89 -> 194.91 | ... R89: =Q89 -> 194.91
B90: =ConsolidatedBS!B50 -> Deferred tax liabilities (net) | D90: =ConsolidatedBS!E50 -> 221.5 | E90: =ConsolidatedBS!F50 -> 220.06 | F90: =ConsolidatedBS!G50 -> 291.31 | G90: =ConsolidatedBS!H50 -> 461.08 | H90: =ConsolidatedBS!I50 -> 492.95 | I90: =H90 -> 492.95 | J90: =I90 -> 492.95 | K90: =J90 -> 492.95 | L90: =K90 -> 492.95 | M90: =L90 -> 492.95 | N90: =M90 -> 492.95 | O90: =N90 -> 492.95 | P90: =O90 -> 492.95 | ... R90: =Q90 -> 492.95
B91: =ConsolidatedBS!B51 -> Government grant | D91: =ConsolidatedBS!E51 -> 63.42 | E91: =ConsolidatedBS!F51 -> 63.76 | F91: =ConsolidatedBS!G51 -> 96.37 | G91: =ConsolidatedBS!H51 -> 133.28 | H91: =ConsolidatedBS!I51 -> 123.2 | I91: =H91 -> 123.2 | J91: =I91 -> 123.2 | K91: =J91 -> 123.2 | L91: =K91 -> 123.2 | M91: =L91 -> 123.2 | N91: =M91 -> 123.2 | O91: =N91 -> 123.2 | P91: =O91 -> 123.2 | ... R91: =Q91 -> 123.2
B92: =ConsolidatedBS!B52 -> Other non-current liabilities | D92: =ConsolidatedBS!E52 -> 123.5 | E92: =ConsolidatedBS!F52 -> 236.54 | F92: =ConsolidatedBS!G52 -> 336.38 | G92: =ConsolidatedBS!H52 -> 428.1 | H92: =ConsolidatedBS!I52 -> 463.67 | I92: =H92 -> 463.67 | J92: =I92 -> 463.67 | K92: =J92 -> 463.67 | L92: =K92 -> 463.67 | M92: =L92 -> 463.67 | N92: =M92 -> 463.67 | O92: =N92 -> 463.67 | P92: =O92 -> 463.67 | ... R92: =Q92 -> 463.67
B93: =ConsolidatedBS!B53 -> Total non-current liabilities | D93: =SUM(D86:D92) -> 491.72 | E93: =SUM(E86:E92) -> 638.46 | F93: =SUM(F86:F92) -> 972.78 | G93: =SUM(G86:G92) -> 1483.99 | H93: =SUM(H86:H92) -> 1612.14 | I93: =SUM(I86:I92) -> 1644.789 | J93: =SUM(J86:J92) -> 1619.9279 | K93: =SUM(K86:K92) -> 1582.5521 | ... R93: =SUM(R86:R92) -> 1490.406
B95: =ConsolidatedBS!B55 -> Current liabilities :
B96: =ConsolidatedBS!B56 -> Trade payables | D96: =ConsolidatedBS!E56 -> 1513.23 | E96: =ConsolidatedBS!F56 -> 1788.09 | F96: =ConsolidatedBS!G56 -> 1810.44 | G96: =ConsolidatedBS!H56 -> 2090.13 | H96: =ConsolidatedBS!I56 -> 2529.75 | I96: =Schedules!I175 -> 2942.9991 | J96: =Schedules!J175 -> 3399.0569 | K96: =Schedules!K175 -> 3899.562 | L96: =Schedules!L175 -> 4443.6966 | M96: =Schedules!M175 -> 5029.5135 | N96: =Schedules!N175 -> 5633.0551 | O96: =Schedules!O175 -> 6309.0217 | P96: =Schedules!P175 -> 7066.1043 | ... R96: =Schedules!R175 -> 8863.7213
B97: =ConsolidatedBS!B57 -> Othe Current Liabilites / Financial Liabilities
B98: =ConsolidatedBS!B58 -> Borrowings | D98: =ConsolidatedBS!E58 -> 157.41 | E98: =ConsolidatedBS!F58 -> 58.84 | F98: =ConsolidatedBS!G58 -> 132.74 | G98: =ConsolidatedBS!H58 -> 112.12 | H98: =ConsolidatedBS!I58 -> 82.11 | I98: =Schedules!I179 -> 151.90632 | J98: =Schedules!J179 -> 173.55297 | K98: =Schedules!K179 -> 196.98262 | L98: =Schedules!L179 -> 222.0979 | M98: =Schedules!M179 -> 248.74965 | N98: =Schedules!N179 -> 278.59961 | O98: =Schedules!O179 -> 312.03156 | P98: =Schedules!P179 -> 349.47535 | ... R98: =Schedules!R179 -> 438.38188
B99: =ConsolidatedBS!B59 -> Lease liability | D99: =ConsolidatedBS!E59 -> 15.72 | E99: =ConsolidatedBS!F59 -> 13.55 | F99: =ConsolidatedBS!G59 -> 24.92 | G99: =ConsolidatedBS!H59 -> 35.88 | H99: =ConsolidatedBS!I59 -> 67.85 | I99: =Schedules!I184 -> 67.85 | J99: =Schedules!J184 -> 67.85 | K99: =Schedules!K184 -> 67.85 | L99: =Schedules!L184 -> 67.85 | M99: =Schedules!M184 -> 67.85 | N99: =Schedules!N184 -> 67.85 | O99: =Schedules!O184 -> 67.85 | P99: =Schedules!P184 -> 67.85 | ... R99: =Schedules!R184 -> 67.85
B100: =ConsolidatedBS!B60 -> Other financial liabilities | D100: =ConsolidatedBS!E60 -> 204.9 | E100: =ConsolidatedBS!F60 -> 250 | F100: =ConsolidatedBS!G60 -> 221.98 | G100: =ConsolidatedBS!H60 -> 306.1 | H100: =ConsolidatedBS!I60 -> 354.85 | I100: =Schedules!I188 -> 354.85 | J100: =Schedules!J188 -> 354.85 | K100: =Schedules!K188 -> 354.85 | L100: =Schedules!L188 -> 354.85 | M100: =Schedules!M188 -> 354.85 | N100: =Schedules!N188 -> 354.85 | O100: =Schedules!O188 -> 354.85 | P100: =Schedules!P188 -> 354.85 | ... R100: =Schedules!R188 -> 354.85
B101: =ConsolidatedBS!B61 -> Provisions | D101: =ConsolidatedBS!E61 -> 90.19 | E101: =ConsolidatedBS!F61 -> 121.82 | F101: =ConsolidatedBS!G61 -> 155.48 | G101: =ConsolidatedBS!H61 -> 99.55 | H101: =ConsolidatedBS!I61 -> 122.8 | I101: =Schedules!I192 -> 122.8 | J101: =Schedules!J192 -> 122.8 | K101: =Schedules!K192 -> 122.8 | L101: =Schedules!L192 -> 122.8 | M101: =Schedules!M192 -> 122.8 | N101: =Schedules!N192 -> 122.8 | O101: =Schedules!O192 -> 122.8 | P101: =Schedules!P192 -> 122.8 | ... R101: =Schedules!R192 -> 122.8
B102: =ConsolidatedBS!B62 -> Government grant | D102: =ConsolidatedBS!E62 -> 15.61 | E102: =ConsolidatedBS!F62 -> 19.38 | F102: =ConsolidatedBS!G62 -> 32.45 | G102: =ConsolidatedBS!H62 -> 25.69 | H102: =ConsolidatedBS!I62 -> 40.48 | I102: =Schedules!I200 -> 40.48 | J102: =Schedules!J200 -> 40.48 | K102: =Schedules!K200 -> 40.48 | L102: =Schedules!L200 -> 40.48 | M102: =Schedules!M200 -> 40.48 | N102: =Schedules!N200 -> 40.48 | O102: =Schedules!O200 -> 40.48 | P102: =Schedules!P200 -> 40.48 | ... R102: =Schedules!R200 -> 40.48
B103: =ConsolidatedBS!B63 -> Contract liability | D103: =ConsolidatedBS!E63 -> 227.67 | E103: =ConsolidatedBS!F63 -> 170.14 | F103: =ConsolidatedBS!G63 -> 180.1 | G103: =ConsolidatedBS!H63 -> 262.58 | H103: =ConsolidatedBS!I63 -> 270.68 | I103: =Schedules!I196 -> 270.68 | J103: =Schedules!J196 -> 270.68 | K103: =Schedules!K196 -> 270.68 | L103: =Schedules!L196 -> 270.68 | M103: =Schedules!M196 -> 270.68 | N103: =Schedules!N196 -> 270.68 | O103: =Schedules!O196 -> 270.68 | P103: =Schedules!P196 -> 270.68 | ... R103: =Schedules!R196 -> 270.68
B104: =ConsolidatedBS!B64 -> Other current liabilities | D104: =ConsolidatedBS!E64 -> 273.05 | E104: =ConsolidatedBS!F64 -> 300.93 | F104: =ConsolidatedBS!G64 -> 453.64 | G104: =ConsolidatedBS!H64 -> 454.34 | H104: =ConsolidatedBS!I64 -> 558.58 | I104: =Schedules!I204 -> 558.58 | J104: =Schedules!J204 -> 558.58 | K104: =Schedules!K204 -> 558.58 | L104: =Schedules!L204 -> 558.58 | M104: =Schedules!M204 -> 558.58 | N104: =Schedules!N204 -> 558.58 | O104: =Schedules!O204 -> 558.58 | P104: =Schedules!P204 -> 558.58 | ... R104: =Schedules!R204 -> 558.58
B105: =ConsolidatedBS!B65 -> Current tax liabilities (net) | D105: =ConsolidatedBS!E65 -> 131.03 | E105: =ConsolidatedBS!F65 -> 170.62 | F105: =ConsolidatedBS!G65 -> 222.83 | G105: =ConsolidatedBS!H65 -> 212.02 | H105: =ConsolidatedBS!I65 -> 238.68 | I105: =Schedules!I208 -> 238.68 | J105: =Schedules!J208 -> 238.68 | K105: =Schedules!K208 -> 238.68 | L105: =Schedules!L208 -> 238.68 | M105: =Schedules!M208 -> 238.68 | N105: =Schedules!N208 -> 238.68 | O105: =Schedules!O208 -> 238.68 | P105: =Schedules!P208 -> 238.68 | ... R105: =Schedules!R208 -> 238.68
B106: =ConsolidatedBS!B66 -> Total current liabilities | D106: =SUM(D96,D98:D105) -> 2628.81 | E106: =SUM(E96,E98:E105) -> 2893.37 | F106: =SUM(F96,F98:F105) -> 3234.58 | G106: =SUM(G96,G98:G105) -> 3598.41 | H106: =SUM(H96,H98:H105) -> 4265.78 | I106: =SUM(I96,I98:I105) -> 4748.8254 | J106: =SUM(J96,J98:J105) -> 5226.5299 | K106: =SUM(K96,K98:K105) -> 5750.4646 | ... R106: =SUM(R96,R98:R105) -> 10956.023
B108: Total Liabilities | D108: =D93+D106 -> 3120.53 | E108: =E93+E106 -> 3531.83 | F108: =F93+F106 -> 4207.36 | G108: =G93+G106 -> 5082.4 | H108: =H93+H106 -> 5877.92 | I108: =I93+I106 -> 6393.6144 | J108: =J93+J106 -> 6846.4578 | K108: =K93+K106 -> 7333.0166 | ... R108: =R93+R106 -> 12446.429
B110: Total equity and liabilities | D110: =D83+D108 -> 14558.61 | E110: =E83+E108 -> 16139.83 | F110: =F83+F108 -> 19197.64 | G110: =G83+G108 -> 23127.93 | H110: =H83+H108 -> 27174.41 | I110: =I83+I108 -> 30069.157 | J110: =J83+J108 -> 32853.833 | K110: =K83+K108 -> 35582.789 | ... R110: =R83+R108 -> 54690.142
B112: Check | D112: =D76-D110 -> -1.12 | E112: =E76-E110 -> -5.93 | F112: =F76-F110 -> -33.41 | G112: =G76-G110 -> -5.21 | H112: =H76-H110 -> 4.04 | I112: =I76-I110 -> 4.04 | J112: =J76-J110 -> 4.04 | K112: =K76-K110 -> 4.04 | ... R112: =R76-R110 -> 4.04
B114: Net Working Capital | D114: =D74-D106 -> 6178.55 | E114: =E74-E106 -> 2720.04 | F114: =F74-F106 -> 415.24 | G114: =G74-G106 -> 547.71 | H114: =H74-H106 -> 2692.42 | I114: =I74-I106 -> 3854.8857 | J114: =J74-J106 -> 4858.7618 | K114: =K74-K106 -> 5813.126 | ... R114: =R74-R106 -> 12035.009
B115: Trade Receivable Days | D115: =Schedules!D159 -> 6.6199636 | E115: =Schedules!E159 -> 10.705615 | F115: =Schedules!F159 -> 9.3237863 | G115: =Schedules!G159 -> 8.2505754 | H115: =Schedules!H159 -> 10.631419 | I115: =Schedules!I159 -> 12 | J115: =Schedules!J159 -> 12 | K115: =Schedules!K159 -> 10 | ... R115: =Schedules!R159 -> 10
B116: Inventory Days | D116: =Schedules!D165 -> 36.607361 | E116: =Schedules!E165 -> 35.568416 | F116: =Schedules!F165 -> 30.464812 | G116: =Schedules!G165 -> 29.667461 | H116: =Schedules!H165 -> 28.756418 | I116: =Schedules!I165 -> 30 | J116: =Schedules!J165 -> 30 | K116: =Schedules!K165 -> 30 | ... R116: =Schedules!R165 -> 30
B117: Trade Payable Days | D117: =Schedules!D176 -> 108.03986 | E117: =Schedules!E176 -> 109.58494 | F117: =Schedules!F176 -> 80.469879 | G117: =Schedules!G176 -> 84.949024 | H117: =Schedules!H176 -> 89.671902 | I117: =Schedules!I176 -> 90 | J117: =Schedules!J176 -> 90 | K117: =Schedules!K176 -> 90 | ... R117: =Schedules!R176 -> 90
A119: # | B119: Cash Flow Statement
B121: Profit Before Tax | D121: =ConsolidatedCashFlow!E6 -> 1798 | E121: =ConsolidatedCashFlow!F6 -> 2203 | F121: =ConsolidatedCashFlow!G6 -> 3800 | G121: =ConsolidatedCashFlow!H6 -> 5202 | H121: =ConsolidatedCashFlow!I6 -> 5933 | I121: =I37 -> 6447.0168 | J121: =J37 -> 7117.9595 | K121: =K37 -> 7830.4987 | L121: =L37 -> 8572.8001 | M121: =M37 -> 9334.6692 | N121: =N37 -> 10413.17 | O121: =O37 -> 11632.693 | P121: =P37 -> 13012.959 | ... R121: =R37 -> 16335.189
B122: Add : Depreciation | D122: =D29 -> 450.73 | E122: =E29 -> 451.93 | F122: =F29 -> 526.21 | G122: =G29 -> 597.6 | H122: =H29 -> 729.33 | I122: =I29 -> 849.33 | J122: =J29 -> 969.33 | K122: =K29 -> 1089.33 | ... R122: =R29 -> 1929.33
B123: Add : Interest Expenses | D123: =D34 -> 16.45 | E123: =E34 -> 18.78 | F123: =F34 -> 28.02 | G123: =G34 -> 50.88 | H123: =H34 -> 54.34 | I123: =I34 -> 22.238487 | J123: =J34 -> 25.711568 | K123: =K34 -> 25.110945 | ... S123: =S34 -> 0
B124: Add : Other Items | D124: =ConsolidatedCashFlow!E7-SUM(D122:D123) -> -353.18 | E124: =ConsolidatedCashFlow!F7-SUM(E122:E123) -> -501.71 | F124: =ConsolidatedCashFlow!G7-SUM(F122:F123) -> -826.23 | G124: =ConsolidatedCashFlow!H7-SUM(G122:G123) -> -1446.48 | H124: =ConsolidatedCashFlow!I7-SUM(H122:H123) -> -1867.67 | I124: 0 | J124: 0 | K124: 0 | L124: 0 | M124: 0 | N124: 0 | O124: 0 | P124: 0 | Q124: 0 | R124: 0
B125: Less : Changes in Working Capital | D125: =ConsolidatedCashFlow!E17 -> 235 | E125: =ConsolidatedCashFlow!F17 -> -131 | F125: =ConsolidatedCashFlow!G17 -> 66 | G125: =ConsolidatedCashFlow!H17 -> 388 | H125: =ConsolidatedCashFlow!I17 -> 211 | I125: =Schedules!I229*-1 -> -31.7409 | J125: =Schedules!J229*-1 -> 32.190167 | K125: =Schedules!K229*-1 -> 195.91787 | L125: =Schedules!L229*-1 -> 72.006591 | M125: =Schedules!M229*-1 -> 84.805759 | N125: =Schedules!N229*-1 -> 42.409138 | O125: =Schedules!O229*-1 -> 47.498235 | P125: =Schedules!P229*-1 -> 53.198023 | ... R125: =Schedules!R229*-1 -> 66.7316
B126: Less: Taxes Paid | D126: =ConsolidatedCashFlow!E19 -> -457 | E126: =ConsolidatedCashFlow!F19 -> -514 | F126: =ConsolidatedCashFlow!G19 -> -770 | G126: =ConsolidatedCashFlow!H19 -> -1068 | H126: =ConsolidatedCashFlow!I19 -> -1080 | I126: =I39*-1 -> -1160.2325 | J126: =J39*-1 -> -1288.3794 | K126: =K39*-1 -> -1423.6482 | L126: =L39*-1 -> -1563.2477 | M126: =M39*-1 -> -1704.8956 | N126: =N39*-1 -> -1920.1133 | O126: =O39*-1 -> -2164.0715 | P126: =P39*-1 -> -2440.922 | ... R126: =R39*-1 -> -3109.5617
B127: Cash Flow from Operations | D127: =SUM(D121:D126) -> 1690 | E127: =SUM(E121:E126) -> 1527 | F127: =SUM(F121:F126) -> 2824 | G127: =SUM(G121:G126) -> 3724 | H127: =SUM(H121:H126) -> 3980 | I127: =SUM(I121:I126) -> 6126.6119 | J127: =SUM(J121:J126) -> 6856.8118 | K127: =SUM(K121:K126) -> 7717.2093 | ... R127: =SUM(R121:R126) -> 15254.881
...

Sheet CommonSizeStatement
B2: ='Input Sheet'!C5 -> Eicher Motors
B3: Common Size Statement Model
H4: Current Case: | I4: 0
F8: Actual | I8: Explicit Forecast Period
B9: In INR Crores unless stated otherwise | D9: =Controlsheet!D9 -> 2021 | E9: =Controlsheet!E9 -> 2022 | F9: =Controlsheet!F9 -> 2023 | G9: =Controlsheet!G9 -> 2024 | H9: =Controlsheet!H9 -> 2025 | I9: =H9+1 -> 2026 | J9: =I9+1 -> 2027 | K9: =J9+1 -> 2028 | L9: =K9+1 -> 2029 | M9: =L9+1 -> 2030
A11: # | B11: Income Statement
B13: Revenue | D13: ='3StatementModel'!D13/'3StatementModel'!D$13 -> 1 | E13: ='3StatementModel'!E13/'3StatementModel'!E$13 -> 1 | F13: ='3StatementModel'!F13/'3StatementModel'!F$13 -> 1 | G13: ='3StatementModel'!G13/'3StatementModel'!G$13 -> 1 | H13: ='3StatementModel'!H13/'3StatementModel'!H$13 -> 1 | I13: ='3StatementModel'!I13/'3StatementModel'!I$13 -> 1 | J13: ='3StatementModel'!J13/'3StatementModel'!J$13 -> 1 | K13: ='3StatementModel'!K13/'3StatementModel'!K$13 -> 1 | ... M13: ='3StatementModel'!M13/'3StatementModel'!M$13 -> 1
B14: Less: Cost of Goods Sold | D14: ='3StatementModel'!D14/'3StatementModel'!D$13 -> 0.58624596 | E14: ='3StatementModel'!E14/'3StatementModel'!E$13 -> 0.5783432 | F14: ='3StatementModel'!F14/'3StatementModel'!F$13 -> 0.56860529 | G14: ='3StatementModel'!G14/'3StatementModel'!G$13 -> 0.54310411 | H14: ='3StatementModel'!H14/'3StatementModel'!H$13 -> 0.54567509 | I14: ='3StatementModel'!I14/'3StatementModel'!I$13 -> 0.55 | J14: ='3StatementModel'!J14/'3StatementModel'!J$13 -> 0.556 | K14: ='3StatementModel'!K14/'3StatementModel'!K$13 -> 0.562 | ... M14: ='3StatementModel'!M14/'3StatementModel'!M$13 -> 0.574
B15: Gross Profit | D15: ='3StatementModel'!D15/'3StatementModel'!D$13 -> 0.41375404 | E15: ='3StatementModel'!E15/'3StatementModel'!E$13 -> 0.4216568 | F15: ='3StatementModel'!F15/'3StatementModel'!F$13 -> 0.43139471 | G15: ='3StatementModel'!G15/'3StatementModel'!G$13 -> 0.45689589 | H15: ='3StatementModel'!H15/'3StatementModel'!H$13 -> 0.45432491 | I15: ='3StatementModel'!I15/'3StatementModel'!I$13 -> 0.45 | J15: ='3StatementModel'!J15/'3StatementModel'!J$13 -> 0.444 | K15: ='3StatementModel'!K15/'3StatementModel'!K$13 -> 0.438 | ... M15: ='3StatementModel'!M15/'3StatementModel'!M$13 -> 0.426
B17: Less: SG&A Expenses (Excluding Depreciation & Interest)
B18: Employee Benefit Expense | D18: ='3StatementModel'!D20/'3StatementModel'!D$13 -> 0.096696807 | E18: ='3StatementModel'!E20/'3StatementModel'!E$13 -> 0.079727477 | F18: ='3StatementModel'!F20/'3StatementModel'!F$13 -> 0.069375261 | G18: ='3StatementModel'!G20/'3StatementModel'!G$13 -> 0.074728256 | H18: ='3StatementModel'!H20/'3StatementModel'!H$13 -> 0.073725713 | I18: ='3StatementModel'!I20/'3StatementModel'!I$13 -> 0.075 | J18: ='3StatementModel'!J20/'3StatementModel'!J$13 -> 0.075 | K18: ='3StatementModel'!K20/'3StatementModel'!K$13 -> 0.075 | ... M18: ='3StatementModel'!M20/'3StatementModel'!M$13 -> 0.075
B19: Consumption of Stores and machinery spares | D19: ='3StatementModel'!D21/'3StatementModel'!D$13 -> 0.015998211 | E19: ='3StatementModel'!E21/'3StatementModel'!E$13 -> 0.019281732 | F19: ='3StatementModel'!F21/'3StatementModel'!F$13 -> 0.018158616 | G19: ='3StatementModel'!G21/'3StatementModel'!G$13 -> 0.014461973 | H19: ='3StatementModel'!H21/'3StatementModel'!H$13 -> 0.015185728 | I19: ='3StatementModel'!I21/'3StatementModel'!I$13 -> 0.017 | J19: ='3StatementModel'!J21/'3StatementModel'!J$13 -> 0.017 | K19: ='3StatementModel'!K21/'3StatementModel'!K$13 -> 0.017 | ... M19: ='3StatementModel'!M21/'3StatementModel'!M$13 -> 0.017
B20: Freight and handling charges | D20: ='3StatementModel'!D22/'3StatementModel'!D$13 -> 0.013887057 | E20: ='3StatementModel'!E22/'3StatementModel'!E$13 -> 0.017573605 | F20: ='3StatementModel'!F22/'3StatementModel'!F$13 -> 0.018891192 | G20: ='3StatementModel'!G22/'3StatementModel'!G$13 -> 0.016060325 | H20: ='3StatementModel'!H22/'3StatementModel'!H$13 -> 0.017521668 | I20: ='3StatementModel'!I22/'3StatementModel'!I$13 -> 0.016 | J20: ='3StatementModel'!J22/'3StatementModel'!J$13 -> 0.016 | K20: ='3StatementModel'!K22/'3StatementModel'!K$13 -> 0.016 | ... M20: ='3StatementModel'!M22/'3StatementModel'!M$13 -> 0.016
B21: Selling and distribution expenses | D21: ='3StatementModel'!D23/'3StatementModel'!D$13 -> 0.02074802 | E21: ='3StatementModel'!E23/'3StatementModel'!E$13 -> 0.02764563 | F21: ='3StatementModel'!F23/'3StatementModel'!F$13 -> 0.029523936 | G21: ='3StatementModel'!G23/'3StatementModel'!G$13 -> 0.033031402 | H21: ='3StatementModel'!H23/'3StatementModel'!H$13 -> 0.040321457 | I21: ='3StatementModel'!I23/'3StatementModel'!I$13 -> 0.028 | J21: ='3StatementModel'!J23/'3StatementModel'!J$13 -> 0.028 | K21: ='3StatementModel'!K23/'3StatementModel'!K$13 -> 0.028 | ... M21: ='3StatementModel'!M23/'3StatementModel'!M$13 -> 0.028
B22: Other SG&A Expenses | D22: ='3StatementModel'!D24/'3StatementModel'!D$13 -> 0.062151175 | E22: ='3StatementModel'!E24/'3StatementModel'!E$13 -> 0.066485852 | F22: ='3StatementModel'!F24/'3StatementModel'!F$13 -> 0.057006629 | G22: ='3StatementModel'!G24/'3StatementModel'!G$13 -> 0.056944396 | H22: ='3StatementModel'!H24/'3StatementModel'!H$13 -> 0.057864851 | I22: ='3StatementModel'!I24/'3StatementModel'!I$13 -> 0.061 | J22: ='3StatementModel'!J24/'3StatementModel'!J$13 -> 0.061 | K22: ='3StatementModel'!K24/'3StatementModel'!K$13 -> 0.061 | ... M22: ='3StatementModel'!M24/'3StatementModel'!M$13 -> 0.061
B23: Earnings Before Interest,Taxes,Depreciation & Amortization | D23: ='3StatementModel'!D25/'3StatementModel'!D$13 -> 0.20427276 | E23: ='3StatementModel'!E25/'3StatementModel'!E$13 -> 0.2109425 | F23: ='3StatementModel'!F25/'3StatementModel'!F$13 -> 0.23843907 | G23: ='3StatementModel'!G25/'3StatementModel'!G$13 -> 0.26166954 | H23: ='3StatementModel'!H25/'3StatementModel'!H$13 -> 0.24970549 | I23: ='3StatementModel'!I25/'3StatementModel'!I$13 -> 0.253 | J23: ='3StatementModel'!J25/'3StatementModel'!J$13 -> 0.247 | K23: ='3StatementModel'!K25/'3StatementModel'!K$13 -> 0.241 | ... M23: ='3StatementModel'!M25/'3StatementModel'!M$13 -> 0.229
B25: Less : Depreciation & Amortization | D25: ='3StatementModel'!D29/'3StatementModel'!D$13 -> 0.051687146 | E25: ='3StatementModel'!E29/'3StatementModel'!E$13 -> 0.043885945 | F25: ='3StatementModel'!F29/'3StatementModel'!F$13 -> 0.036435635 | G25: ='3StatementModel'!G29/'3StatementModel'!G$13 -> 0.036139813 | H25: ='3StatementModel'!H29/'3StatementModel'!H$13 -> 0.038649522 | I25: ='3StatementModel'!I29/'3StatementModel'!I$13 -> 0.039138004 | J25: ='3StatementModel'!J29/'3StatementModel'!J$13 -> 0.039096479 | K25: ='3StatementModel'!K29/'3StatementModel'!K$13 -> 0.038710573 | ... M25: ='3StatementModel'!M29/'3StatementModel'!M$13 -> 0.037408334
B26: Earnings Before Interest & Taxes | D26: ='3StatementModel'!D30/'3StatementModel'!D$15 -> 0.3687834 | E26: ='3StatementModel'!E30/'3StatementModel'!E$15 -> 0.39619083 | F26: ='3StatementModel'!F30/'3StatementModel'!F$15 -> 0.46825664 | G26: ='3StatementModel'!G30/'3StatementModel'!G$15 -> 0.49361295 | H26: ='3StatementModel'!H30/'3StatementModel'!H$15 -> 0.46454853 | I26: ='3StatementModel'!I30/'3StatementModel'!I$15 -> 0.47524888 | J26: ='3StatementModel'!J30/'3StatementModel'!J$15 -> 0.46825117 | K26: ='3StatementModel'!K30/'3StatementModel'!K$15 -> 0.46184801 | ... M26: ='3StatementModel'!M30/'3StatementModel'!M$15 -> 0.44974569
B28: Less : Interest | D28: ='3StatementModel'!D34/'3StatementModel'!D$13 -> 0.0018863922 | E28: ='3StatementModel'!E34/'3StatementModel'!E$13 -> 0.0018236852 | F28: ='3StatementModel'!F34/'3StatementModel'!F$13 -> 0.0019401503 | G28: ='3StatementModel'!G34/'3StatementModel'!G$13 -> 0.003076964 | H28: ='3StatementModel'!H34/'3StatementModel'!H$13 -> 0.0028796498 | I28: ='3StatementModel'!I34/'3StatementModel'!I$13 -> 0.0010247724 | J28: ='3StatementModel'!J34/'3StatementModel'!J$13 -> 0.0010370377 | K28: ='3StatementModel'!K34/'3StatementModel'!K$13 -> 0.00089234581 | ... M28: ='3StatementModel'!M34/'3StatementModel'!M$13 -> 0.0006003125
B29: Add : Other Income | D29: ='3StatementModel'!D35/'3StatementModel'!D$13 -> 0.051969244 | E29: ='3StatementModel'!E35/'3StatementModel'!E$13 -> 0.042807077 | F29: ='3StatementModel'!F35/'3StatementModel'!F$13 -> 0.041206383 | G29: ='3StatementModel'!G35/'3StatementModel'!G$13 -> 0.065063154 | H29: ='3StatementModel'!H35/'3StatementModel'!H$13 -> 0.069150811 | I29: ='3StatementModel'!I35/'3StatementModel'!I$13 -> 0.052 | J29: ='3StatementModel'!J35/'3StatementModel'!J$13 -> 0.052 | K29: ='3StatementModel'!K35/'3StatementModel'!K$13 -> 0.052 | ... M29: ='3StatementModel'!M35/'3StatementModel'!M$13 -> 0.052
B30: Share of profit of joint venture (VE Commercial Vehicles Limited) | D30: ='3StatementModel'!D36/'3StatementModel'!D$13 -> 0.0035698108 | E30: ='3StatementModel'!E36/'3StatementModel'!E$13 -> 0.0058410364 | F30: ='3StatementModel'!F36/'3StatementModel'!F$13 -> 0.021822883 | G30: ='3StatementModel'!G36/'3StatementModel'!G$13 -> 0.027075832 | H30: ='3StatementModel'!H36/'3StatementModel'!H$13 -> 0.037085163 | I30: ='3StatementModel'!I36/'3StatementModel'!I$13 -> 0.032247968 | J30: ='3StatementModel'!J36/'3StatementModel'!J$13 -> 0.028225792 | K30: ='3StatementModel'!K36/'3StatementModel'!K$13 -> 0.024868539 | ... M30: ='3StatementModel'!M36/'3StatementModel'!M$13 -> 0.019693173
B31: Profit Before Tax | D31: ='3StatementModel'!D37/'3StatementModel'!D$13 -> 0.20623828 | E31: ='3StatementModel'!E37/'3StatementModel'!E$13 -> 0.21388098 | F31: ='3StatementModel'!F37/'3StatementModel'!F$13 -> 0.26309255 | G31: ='3StatementModel'!G37/'3StatementModel'!G$13 -> 0.31459175 | H31: ='3StatementModel'!H37/'3StatementModel'!H$13 -> 0.31441229 | I31: ='3StatementModel'!I37/'3StatementModel'!I$13 -> 0.29708519 | J31: ='3StatementModel'!J37/'3StatementModel'!J$13 -> 0.28709228 | K31: ='3StatementModel'!K37/'3StatementModel'!K$13 -> 0.27826562 | ... M31: ='3StatementModel'!M37/'3StatementModel'!M$13 -> 0.26268453
B33: Less: Taxes | D33: ='3StatementModel'!D39/'3StatementModel'!D$13 -> 0.051775445 | E33: ='3StatementModel'!E39/'3StatementModel'!E$13 -> 0.051069983 | F33: ='3StatementModel'!F39/'3StatementModel'!F$13 -> 0.061326614 | G33: ='3StatementModel'!G39/'3StatementModel'!G$13 -> 0.072630986 | H33: ='3StatementModel'!H39/'3StatementModel'!H$13 -> 0.063519225 | I33: ='3StatementModel'!I39/'3StatementModel'!I$13 -> 0.053464711 | J33: ='3StatementModel'!J39/'3StatementModel'!J$13 -> 0.051964861 | K33: ='3StatementModel'!K39/'3StatementModel'!K$13 -> 0.050590947 | ... M33: ='3StatementModel'!M39/'3StatementModel'!M$13 -> 0.047977028
B34: Net Income | D34: ='3StatementModel'!D40/'3StatementModel'!D$13 -> 0.15446284 | E34: ='3StatementModel'!E40/'3StatementModel'!E$13 -> 0.162811 | F34: ='3StatementModel'!F40/'3StatementModel'!F$13 -> 0.20176594 | G34: ='3StatementModel'!G40/'3StatementModel'!G$13 -> 0.24196077 | H34: ='3StatementModel'!H40/'3StatementModel'!H$13 -> 0.25089307 | I34: ='3StatementModel'!I40/'3StatementModel'!I$13 -> 0.24362048 | J34: ='3StatementModel'!J40/'3StatementModel'!J$13 -> 0.23512741 | K34: ='3StatementModel'!K40/'3StatementModel'!K$13 -> 0.22767467 | ... M34: ='3StatementModel'!M40/'3StatementModel'!M$13 -> 0.2147075
A36: # | B36: Balance Sheet
B38: Assets
B39: Non Current Assets
B40: Property Plant & Equipment | D40: ='3StatementModel'!D53/'3StatementModel'!D$76 -> 0.13013988 | E40: ='3StatementModel'!E53/'3StatementModel'!E$76 -> 0.11843262 | F40: ='3StatementModel'!F53/'3StatementModel'!F$76 -> 0.10434283 | G40: ='3StatementModel'!G53/'3StatementModel'!G$76 -> 0.084343883 | H40: ='3StatementModel'!H53/'3StatementModel'!H$76 -> 0.083474223 | I40: ='3StatementModel'!I53/'3StatementModel'!I$76 -> 0.097077907 | J40: ='3StatementModel'!J53/'3StatementModel'!J$76 -> 0.10500333 | K40: ='3StatementModel'!K53/'3StatementModel'!K$76 -> 0.10849321 | ... M40: ='3StatementModel'!M53/'3StatementModel'!M$76 -> 0.10825618
B41: Right of Use Asset | D41: ='3StatementModel'!D54/'3StatementModel'!D$76 -> 0.013575142 | E41: ='3StatementModel'!E54/'3StatementModel'!E$76 -> 0.011383484 | F41: ='3StatementModel'!F54/'3StatementModel'!F$76 -> 0.011799587 | G41: ='3StatementModel'!G54/'3StatementModel'!G$76 -> 0.011762889 | H41: ='3StatementModel'!H54/'3StatementModel'!H$76 -> 0.011665124 | I41: ='3StatementModel'!I54/'3StatementModel'!I$76 -> 0.008547591 | J41: ='3StatementModel'!J54/'3StatementModel'!J$76 -> 0.0059975514 | K41: ='3StatementModel'!K54/'3StatementModel'!K$76 -> 0.0038519917 | ... M41: ='3StatementModel'!M54/'3StatementModel'!M$76 -> 0.00042844876
B42: Capital Work in Progress | D42: ='3StatementModel'!D55/'3StatementModel'!D$76 -> 0.0043901799 | E42: ='3StatementModel'!E55/'3StatementModel'!E$76 -> 0.0083042538 | F42: ='3StatementModel'!F55/'3StatementModel'!F$76 -> 0.0040570375 | G42: ='3StatementModel'!G55/'3StatementModel'!G$76 -> 0.0091533349 | H42: ='3StatementModel'!H55/'3StatementModel'!H$76 -> 0.0040583624 | I42: ='3StatementModel'!I55/'3StatementModel'!I$76 -> 0 | J42: ='3StatementModel'!J55/'3StatementModel'!J$76 -> 0 | K42: ='3StatementModel'!K55/'3StatementModel'!K$76 -> 0 | ... M42: ='3StatementModel'!M55/'3StatementModel'!M$76 -> 0
B43: Intangible assets | D43: ='3StatementModel'!D56/'3StatementModel'!D$76 -> 0.023436046 | E43: ='3StatementModel'!E56/'3StatementModel'!E$76 -> 0.02044391 | F43: ='3StatementModel'!F56/'3StatementModel'!F$76 -> 0.024222732 | G43: ='3StatementModel'!G56/'3StatementModel'!G$76 -> 0.029932897 | H43: ='3StatementModel'!H56/'3StatementModel'!H$76 -> 0.032663011 | I43: ='3StatementModel'!I56/'3StatementModel'!I$76 -> 0.02393374 | J43: ='3StatementModel'!J56/'3StatementModel'!J$76 -> 0.016793484 | K43: ='3StatementModel'!K56/'3StatementModel'!K$76 -> 0.010785796 | ... M43: ='3StatementModel'!M56/'3StatementModel'!M$76 -> 0.0011996809
B44: Intangible assets under development | D44: ='3StatementModel'!D57/'3StatementModel'!D$76 -> 0.017199394 | E44: ='3StatementModel'!E57/'3StatementModel'!E$76 -> 0.022982664 | F44: ='3StatementModel'!F57/'3StatementModel'!F$76 -> 0.020575833 | G44: ='3StatementModel'!G57/'3StatementModel'!G$76 -> 0.014853356 | H44: ='3StatementModel'!H57/'3StatementModel'!H$76 -> 0.014024714 | I44: ='3StatementModel'!I57/'3StatementModel'!I$76 -> 0.010276575 | J44: ='3StatementModel'!J57/'3StatementModel'!J$76 -> 0.00721072 | K44: ='3StatementModel'!K57/'3StatementModel'!K$76 -> 0.0046311623 | ... M44: ='3StatementModel'!M57/'3StatementModel'!M$76 -> 0.00051511423
B45: Non Current Financial Asset | D45: ='3StatementModel'!D58/'3StatementModel'!D$76 -> 0.19570132 | E45: ='3StatementModel'!E58/'3StatementModel'!E$76 -> 0.45673396 | F45: ='3StatementModel'!F58/'3StatementModel'!F$76 -> 0.63243084 | G45: ='3StatementModel'!G58/'3StatementModel'!G$76 -> 0.65745466 | H45: ='3StatementModel'!H58/'3StatementModel'!H$76 -> 0.58920763 | I45: ='3StatementModel'!I58/'3StatementModel'!I$76 -> 0.56603945 | J45: ='3StatementModel'!J58/'3StatementModel'!J$76 -> 0.55070641 | K45: ='3StatementModel'!K58/'3StatementModel'!K$76 -> 0.54050976 | ... M45: ='3StatementModel'!M58/'3StatementModel'!M$76 -> 0.5443592
B46: Other Non Current Asset | D46: ='3StatementModel'!D59/'3StatementModel'!D$76 -> 0.0070266234 | E46: ='3StatementModel'!E59/'3StatementModel'!E$76 -> 0.0086408122 | F46: ='3StatementModel'!F59/'3StatementModel'!F$76 -> 0.0076094891 | G46: ='3StatementModel'!G59/'3StatementModel'!G$76 -> 0.0081638319 | H46: ='3StatementModel'!H59/'3StatementModel'!H$76 -> 0.0055871472 | I46: ='3StatementModel'!I59/'3StatementModel'!I$76 -> 0.0050493467 | J46: ='3StatementModel'!J59/'3StatementModel'!J$76 -> 0.0046214191 | K46: ='3StatementModel'!K59/'3StatementModel'!K$76 -> 0.0042670281 | ... M46: ='3StatementModel'!M59/'3StatementModel'!M$76 -> 0.0038031285
B47: Deferred Tax Asset | D47: ='3StatementModel'!D60/'3StatementModel'!D$76 -> 0 | E47: ='3StatementModel'!E60/'3StatementModel'!E$76 -> 0 | F47: ='3StatementModel'!F60/'3StatementModel'!F$76 -> 0 | G47: ='3StatementModel'!G60/'3StatementModel'!G$76 -> 0.00055356809 | H47: ='3StatementModel'!H60/'3StatementModel'!H$76 -> 0 | I47: ='3StatementModel'!I60/'3StatementModel'!I$76 -> 0 | J47: ='3StatementModel'!J60/'3StatementModel'!J$76 -> 0 | K47: ='3StatementModel'!K60/'3StatementModel'!K$76 -> 0 | ... M47: ='3StatementModel'!M60/'3StatementModel'!M$76 -> 0
B48: Non-current tax assets | D48: ='3StatementModel'!D61/'3StatementModel'!D$76 -> 0.0035260199 | E48: ='3StatementModel'!E61/'3StatementModel'!E$76 -> 0.0051518852 | F48: ='3StatementModel'!F61/'3StatementModel'!F$76 -> 0.0045120519 | G48: ='3StatementModel'!G61/'3StatementModel'!G$76 -> 0.0044722247 | H48: ='3StatementModel'!H61/'3StatementModel'!H$76 -> 0.0033007769 | I48: ='3StatementModel'!I61/'3StatementModel'!I$76 -> 0.0029830549 | J48: ='3StatementModel'!J61/'3StatementModel'!J$76 -> 0.0027302437 | K48: ='3StatementModel'!K61/'3StatementModel'!K$76 -> 0.0025208765 | ... M48: ='3StatementModel'!M61/'3StatementModel'!M$76 -> 0.0022468137
B49: Total Non Current Assets | D49: ='3StatementModel'!D62/'3StatementModel'!D$76 -> 0.3949946 | E49: ='3StatementModel'!E62/'3StatementModel'!E$76 -> 0.65207358 | F49: ='3StatementModel'!F62/'3StatementModel'!F$76 -> 0.8095504 | G49: ='3StatementModel'!G62/'3StatementModel'!G$76 -> 0.82069065 | H49: ='3StatementModel'!H62/'3StatementModel'!H$76 -> 0.74398098 | I49: ='3StatementModel'!I62/'3StatementModel'!I$76 -> 0.71390767 | J49: ='3StatementModel'!J62/'3StatementModel'!J$76 -> 0.69306316 | K49: ='3StatementModel'!K62/'3StatementModel'!K$76 -> 0.67505982 | ... M49: ='3StatementModel'!M62/'3StatementModel'!M$76 -> 0.66080857
B51: =ConsolidatedBS!B24 -> Current assets :
B52: =ConsolidatedBS!B25 -> Inventories | D52: ='3StatementModel'!D65/'3StatementModel'!D$76 -> 0.060079038 | E52: ='3StatementModel'!E65/'3StatementModel'!E$76 -> 0.070187617 | F52: ='3StatementModel'!F65/'3StatementModel'!F$76 -> 0.066709698 | G52: ='3StatementModel'!G65/'3StatementModel'!G$76 -> 0.060963416 | H52: ='3StatementModel'!H65/'3StatementModel'!H$76 -> 0.057536394 | I52: ='3StatementModel'!I65/'3StatementModel'!I$76 -> 0.059309817 | J52: ='3StatementModel'!J65/'3StatementModel'!J$76 -> 0.062018742 | K52: ='3StatementModel'!K65/'3StatementModel'!K$76 -> 0.064993356 | ... M52: ='3StatementModel'!M65/'3StatementModel'!M$76 -> 0.073150792
B53: =ConsolidatedBS!B26 -> Trade receivables | D53: ='3StatementModel'!D66/'3StatementModel'!D$76 -> 0.01086451 | E53: ='3StatementModel'!E66/'3StatementModel'!E$76 -> 0.01872083 | F53: ='3StatementModel'!F66/'3StatementModel'!F$76 -> 0.019250447 | G53: ='3StatementModel'!G66/'3StatementModel'!G$76 -> 0.016165053 | H53: ='3StatementModel'!H66/'3StatementModel'!H$76 -> 0.020223376 | I53: ='3StatementModel'!I66/'3StatementModel'!I$76 -> 0.023723927 | J53: ='3StatementModel'!J66/'3StatementModel'!J$76 -> 0.024807497 | K53: ='3StatementModel'!K66/'3StatementModel'!K$76 -> 0.021664452 | ... M53: ='3StatementModel'!M66/'3StatementModel'!M$76 -> 0.024383597
B54: =ConsolidatedBS!B27 -> Financial Assets | D54: ='3StatementModel'!D67/'3StatementModel'!D$76 -> 0 | E54: ='3StatementModel'!E67/'3StatementModel'!E$76 -> 0 | F54: ='3StatementModel'!F67/'3StatementModel'!F$76 -> 0 | G54: ='3StatementModel'!G67/'3StatementModel'!G$76 -> 0 | H54: ='3StatementModel'!H67/'3StatementModel'!H$76 -> 0 | I54: ='3StatementModel'!I67/'3StatementModel'!I$76 -> 0 | J54: ='3StatementModel'!J67/'3StatementModel'!J$76 -> 0 | K54: ='3StatementModel'!K67/'3StatementModel'!K$76 -> 0 | ... M54: ='3StatementModel'!M67/'3StatementModel'!M$76 -> 0
B55: =ConsolidatedBS!B28 -> Investments (Current) | D55: ='3StatementModel'!D68/'3StatementModel'!D$76 -> 0.073919336 | E55: ='3StatementModel'!E68/'3StatementModel'!E$76 -> 0.026322836 | F55: ='3StatementModel'!F68/'3StatementModel'!F$76 -> 0.01147398 | G55: ='3StatementModel'!G68/'3StatementModel'!G$76 -> 0.007824339 | H55: ='3StatementModel'!H68/'3StatementModel'!H$76 -> 0.031184633 | I55: ='3StatementModel'!I68/'3StatementModel'!I$76 -> 0.028182903 | J55: ='3StatementModel'!J68/'3StatementModel'!J$76 -> 0.025794427 | K55: ='3StatementModel'!K68/'3StatementModel'!K$76 -> 0.023816395 | ... M55: ='3StatementModel'!M68/'3StatementModel'!M$76 -> 0.021227142
B56: =ConsolidatedBS!B29 -> Loans / Bill discounting | D56: ='3StatementModel'!D69/'3StatementModel'!D$76 -> 0.031541152 | E56: ='3StatementModel'!E69/'3StatementModel'!E$76 -> 0.04194832 | F56: ='3StatementModel'!F69/'3StatementModel'!F$76 -> 0.030731211 | G56: ='3StatementModel'!G69/'3StatementModel'!G$76 -> 0.020623871 | H56: ='3StatementModel'!H69/'3StatementModel'!H$76 -> 0.016408588 | I56: ='3StatementModel'!I69/'3StatementModel'!I$76 -> 0.014829151 | J56: ='3StatementModel'!J69/'3StatementModel'!J$76 -> 0.013572394 | K56: ='3StatementModel'!K69/'3StatementModel'!K$76 -> 0.012531603 | ... M56: ='3StatementModel'!M69/'3StatementModel'!M$76 -> 0.011169201
B57: =ConsolidatedBS!B30 -> Other financial assets (Current) | D57: ='3StatementModel'!D70/'3StatementModel'!D$76 -> 0.014764221 | E57: ='3StatementModel'!E70/'3StatementModel'!E$76 -> 0.0040752701 | F57: ='3StatementModel'!F70/'3StatementModel'!F$76 -> 0.0065726617 | G57: ='3StatementModel'!G70/'3StatementModel'!G$76 -> 0.054202966 | H57: ='3StatementModel'!H70/'3StatementModel'!H$76 -> 0.1055292 | I57: ='3StatementModel'!I70/'3StatementModel'!I$76 -> 0.095371302 | J57: ='3StatementModel'!J70/'3StatementModel'!J$76 -> 0.087288669 | K57: ='3StatementModel'!K70/'3StatementModel'!K$76 -> 0.080594986 | ... M57: ='3StatementModel'!M70/'3StatementModel'!M$76 -> 0.07183292
B58: =ConsolidatedBS!B31 -> Other current assets | D58: ='3StatementModel'!D71/'3StatementModel'!D$76 -> 0.013408218 | E58: ='3StatementModel'!E71/'3StatementModel'!E$76 -> 0.018296878 | F58: ='3StatementModel'!F71/'3StatementModel'!F$76 -> 0.017506573 | G58: ='3StatementModel'!G71/'3StatementModel'!G$76 -> 0.013427486 | H58: ='3StatementModel'!H71/'3StatementModel'!H$76 -> 0.015311028 | I58: ='3StatementModel'!I71/'3StatementModel'!I$76 -> 0.015875261 | J58: ='3StatementModel'!J71/'3StatementModel'!J$76 -> 0.01660035 | K58: ='3StatementModel'!K71/'3StatementModel'!K$76 -> 0.017396555 | ... M58: ='3StatementModel'!M71/'3StatementModel'!M$76 -> 0.019580029
B59: =ConsolidatedBS!B32 -> Cash and cash equivalents | D59: ='3StatementModel'!D72/'3StatementModel'!D$76 -> 0.0063884639 | E59: ='3StatementModel'!E72/'3StatementModel'!E$76 -> 0.0027643657 | F59: ='3StatementModel'!F72/'3StatementModel'!F$76 -> 0.0028908023 | G59: ='3StatementModel'!G72/'3StatementModel'!G$76 -> 0.0044112457 | H59: ='3StatementModel'!H72/'3StatementModel'!H$76 -> 0.0082050301 | I59: ='3StatementModel'!I72/'3StatementModel'!I$76 -> 0.047335211 | J59: ='3StatementModel'!J72/'3StatementModel'!J$76 -> 0.075514142 | K59: ='3StatementModel'!K72/'3StatementModel'!K$76 -> 0.10270501 | ... M59: ='3StatementModel'!M72/'3StatementModel'!M$76 -> 0.1167445
B60: =ConsolidatedBS!B33 -> Bank balances other than C&CE | D60: ='3StatementModel'!D73/'3StatementModel'!D$76 -> 0.39404046 | E60: ='3StatementModel'!E73/'3StatementModel'!E$76 -> 0.1656103 | F60: ='3StatementModel'!F73/'3StatementModel'!F$76 -> 0.035314229 | G60: ='3StatementModel'!G73/'3StatementModel'!G$76 -> 0.0016909775 | H60: ='3StatementModel'!H73/'3StatementModel'!H$76 -> 0.0016207694 | I60: ='3StatementModel'!I73/'3StatementModel'!I$76 -> 0.0014647594 | J60: ='3StatementModel'!J73/'3StatementModel'!J$76 -> 0.0013406224 | K60: ='3StatementModel'!K73/'3StatementModel'!K$76 -> 0.0012378175 | ... M60: ='3StatementModel'!M73/'3StatementModel'!M$76 -> 0.0011032454
B61: Total Current Assets | D61: ='3StatementModel'!D74/'3StatementModel'!D$76 -> 0.6050054 | E61: ='3StatementModel'!E74/'3StatementModel'!E$76 -> 0.34792642 | F61: ='3StatementModel'!F74/'3StatementModel'!F$76 -> 0.1904496 | G61: ='3StatementModel'!G74/'3StatementModel'!G$76 -> 0.17930935 | H61: ='3StatementModel'!H74/'3StatementModel'!H$76 -> 0.25601902 | I61: ='3StatementModel'!I74/'3StatementModel'!I$76 -> 0.28609233 | J61: ='3StatementModel'!J74/'3StatementModel'!J$76 -> 0.30693684 | K61: ='3StatementModel'!K74/'3StatementModel'!K$76 -> 0.32494018 | ... M61: ='3StatementModel'!M74/'3StatementModel'!M$76 -> 0.33919143
B63: Total Assets | D63: ='3StatementModel'!D76/'3StatementModel'!D$76 -> 1 | E63: ='3StatementModel'!E76/'3StatementModel'!E$76 -> 1 | F63: ='3StatementModel'!F76/'3StatementModel'!F$76 -> 1 | G63: ='3StatementModel'!G76/'3StatementModel'!G$76 -> 1 | H63: ='3StatementModel'!H76/'3StatementModel'!H$76 -> 1 | I63: ='3StatementModel'!I76/'3StatementModel'!I$76 -> 1 | J63: ='3StatementModel'!J76/'3StatementModel'!J$76 -> 1 | K63: ='3StatementModel'!K76/'3StatementModel'!K$76 -> 1 | ... M63: ='3StatementModel'!M76/'3StatementModel'!M$76 -> 1
B65: Equity & Liabilities
B67: Equity
B68: =ConsolidatedBS!B40 -> Equity share capital | D68: ='3StatementModel'!D81/'3StatementModel'!D$110 -> 0.0018772397 | E68: ='3StatementModel'!E81/'3StatementModel'!E$110 -> 0.001693946 | F68: ='3StatementModel'!F81/'3StatementModel'!F$110 -> 0.0014246543 | G68: ='3StatementModel'!G81/'3StatementModel'!G$110 -> 0.00118385 | H68: ='3StatementModel'!H81/'3StatementModel'!H$110 -> 0.0010090375 | I68: ='3StatementModel'!I81/'3StatementModel'!I$110 -> 0.00091189785 | J68: ='3StatementModel'!J81/'3StatementModel'!J$110 -> 0.00083460582 | K68: ='3StatementModel'!K81/'3StatementModel'!K$110 -> 0.00077059726 | ... M68: ='3StatementModel'!M81/'3StatementModel'!M$110 -> 0.00068681157
B69: =ConsolidatedBS!B41 -> Other equity | D69: ='3StatementModel'!D82/'3StatementModel'!D$110 -> 0.78378018 | E69: ='3StatementModel'!E82/'3StatementModel'!E$110 -> 0.77947909 | F69: ='3StatementModel'!F82/'3StatementModel'!F$110 -> 0.77941507 | G69: ='3StatementModel'!G82/'3StatementModel'!G$110 -> 0.77906453 | H69: ='3StatementModel'!H82/'3StatementModel'!H$110 -> 0.78268746 | I69: ='3StatementModel'!I82/'3StatementModel'!I$110 -> 0.78645779 | J69: ='3StatementModel'!J82/'3StatementModel'!J$110 -> 0.79077394 | K69: ='3StatementModel'!K82/'3StatementModel'!K$110 -> 0.79314616 | ... M69: ='3StatementModel'!M82/'3StatementModel'!M$110 -> 0.78902414
B70: =ConsolidatedBS!B42 -> Total equity | D70: ='3StatementModel'!D83/'3StatementModel'!D$110 -> 0.78565742 | E70: ='3StatementModel'!E83/'3StatementModel'!E$110 -> 0.78117304 | F70: ='3StatementModel'!F83/'3StatementModel'!F$110 -> 0.78083973 | G70: ='3StatementModel'!G83/'3StatementModel'!G$110 -> 0.78024838 | H70: ='3StatementModel'!H83/'3StatementModel'!H$110 -> 0.7836965 | I70: ='3StatementModel'!I83/'3StatementModel'!I$110 -> 0.78736968 | J70: ='3StatementModel'!J83/'3StatementModel'!J$110 -> 0.79160855 | K70: ='3StatementModel'!K83/'3StatementModel'!K$110 -> 0.79391676 | ... M70: ='3StatementModel'!M83/'3StatementModel'!M$110 -> 0.78971095
B72: =ConsolidatedBS!B44 -> Non-current liabilities:
B73: =ConsolidatedBS!B46 -> Borrowings | D73: ='3StatementModel'!D86/'3StatementModel'!D$110 -> 0 | E73: ='3StatementModel'!E86/'3StatementModel'!E$110 -> 0 | F73: ='3StatementModel'!F86/'3StatementModel'!F$110 -> 0.0032795698 | G73: ='3StatementModel'!G86/'3StatementModel'!G$110 -> 0.0070676451 | H73: ='3StatementModel'!H86/'3StatementModel'!H$110 -> 0.0067843239 | I73: ='3StatementModel'!I86/'3StatementModel'!I$110 -> 0.0072169972 | J73: ='3StatementModel'!J86/'3StatementModel'!J$110 -> 0.0058485696 | K73: ='3StatementModel'!K86/'3StatementModel'!K$110 -> 0.0043496325 | ... M73: ='3StatementModel'!M86/'3StatementModel'!M$110 -> 0.00089009137
B74: =ConsolidatedBS!B47 -> Lease liability | D74: ='3StatementModel'!D87/'3StatementModel'!D$110 -> 0.0031678848 | E74: ='3StatementModel'!E87/'3StatementModel'!E$110 -> 0.002188375 | F74: ='3StatementModel'!F87/'3StatementModel'!F$110 -> 0.0035311632 | G74: ='3StatementModel'!G87/'3StatementModel'!G$110 -> 0.0046688139 | H74: ='3StatementModel'!H87/'3StatementModel'!H$110 -> 0.0045561247 | I74: ='3StatementModel'!I87/'3StatementModel'!I$110 -> 0.0041175081 | J74: ='3StatementModel'!J87/'3StatementModel'!J$110 -> 0.0037685101 | K74: ='3StatementModel'!K87/'3StatementModel'!K$110 -> 0.0034794911 | ... M74: ='3StatementModel'!M87/'3StatementModel'!M$110 -> 0.0031011721
B75: =ConsolidatedBS!B48 -> Other financial liabilities | D75: ='3StatementModel'!D88/'3StatementModel'!D$110 -> 0.0010042167 | E75: ='3StatementModel'!E88/'3StatementModel'!E$110 -> 0.00091822528 | F75: ='3StatementModel'!F88/'3StatementModel'!F$110 -> 0.00080791181 | G75: ='3StatementModel'!G88/'3StatementModel'!G$110 -> 0.00065159312 | H75: ='3StatementModel'!H88/'3StatementModel'!H$110 -> 0.0010760123 | I75: ='3StatementModel'!I88/'3StatementModel'!I$110 -> 0.00097242499 | J75: ='3StatementModel'!J88/'3StatementModel'!J$110 -> 0.0008900027 | K75: ='3StatementModel'!K88/'3StatementModel'!K$110 -> 0.00082174559 | ... M75: ='3StatementModel'!M88/'3StatementModel'!M$110 -> 0.00073239862
B76: =ConsolidatedBS!B49 -> Provisions | D76: ='3StatementModel'!D89/'3StatementModel'!D$110 -> 0.0015495985 | E76: ='3StatementModel'!E89/'3StatementModel'!E$110 -> 0.0042107011 | F76: ='3StatementModel'!F89/'3StatementModel'!F$110 -> 0.0053371144 | G76: ='3StatementModel'!G89/'3StatementModel'!G$110 -> 0.0075674736 | H76: ='3StatementModel'!H89/'3StatementModel'!H$110 -> 0.0071725568 | I76: ='3StatementModel'!I89/'3StatementModel'!I$110 -> 0.0064820573 | J76: ='3StatementModel'!J89/'3StatementModel'!J$110 -> 0.0059326411 | K76: ='3StatementModel'!K89/'3StatementModel'!K$110 -> 0.0054776482 | ... M76: ='3StatementModel'!M89/'3StatementModel'!M$110 -> 0.004882073
B77: =ConsolidatedBS!B50 -> Deferred tax liabilities (net) | D77: ='3StatementModel'!D90/'3StatementModel'!D$110 -> 0.015214365 | E77: ='3StatementModel'!E90/'3StatementModel'!E$110 -> 0.013634592 | F77: ='3StatementModel'!F90/'3StatementModel'!F$110 -> 0.015174261 | G77: ='3StatementModel'!G90/'3StatementModel'!G$110 -> 0.019936069 | H77: ='3StatementModel'!H90/'3StatementModel'!H$110 -> 0.018140228 | I77: ='3StatementModel'!I90/'3StatementModel'!I$110 -> 0.016393875 | J77: ='3StatementModel'!J90/'3StatementModel'!J$110 -> 0.015004338 | K77: ='3StatementModel'!K90/'3StatementModel'!K$110 -> 0.013853608 | ... M77: ='3StatementModel'!M90/'3StatementModel'!M$110 -> 0.012347329
B78: =ConsolidatedBS!B51 -> Government grant | D78: ='3StatementModel'!D91/'3StatementModel'!D$110 -> 0.0043561851 | E78: ='3StatementModel'!E91/'3StatementModel'!E$110 -> 0.0039504753 | F78: ='3StatementModel'!F91/'3StatementModel'!F$110 -> 0.0050198879 | G78: ='3StatementModel'!G91/'3StatementModel'!G$110 -> 0.0057627293 | H78: ='3StatementModel'!H91/'3StatementModel'!H$110 -> 0.0045336771 | I78: ='3StatementModel'!I91/'3StatementModel'!I$110 -> 0.0040972216 | J78: ='3StatementModel'!J91/'3StatementModel'!J$110 -> 0.003749943 | K78: ='3StatementModel'!K91/'3StatementModel'!K$110 -> 0.003462348 | ... M78: ='3StatementModel'!M91/'3StatementModel'!M$110 -> 0.003085893
B79: =ConsolidatedBS!B52 -> Other non-current liabilities | D79: ='3StatementModel'!D92/'3StatementModel'!D$110 -> 0.0084829527 | E79: ='3StatementModel'!E92/'3StatementModel'!E$110 -> 0.014655669 | F79: ='3StatementModel'!F92/'3StatementModel'!F$110 -> 0.017521945 | G79: ='3StatementModel'!G92/'3StatementModel'!G$110 -> 0.018510087 | H79: ='3StatementModel'!H92/'3StatementModel'!H$110 -> 0.017062744 | I79: ='3StatementModel'!I92/'3StatementModel'!I$110 -> 0.015420119 | J79: ='3StatementModel'!J92/'3StatementModel'!J$110 -> 0.014113117 | K79: ='3StatementModel'!K92/'3StatementModel'!K$110 -> 0.013030738 | ... M79: ='3StatementModel'!M92/'3StatementModel'!M$110 -> 0.011613928
B80: =ConsolidatedBS!B53 -> Total non-current liabilities | D80: ='3StatementModel'!D93/'3StatementModel'!D$108 -> 0.1575758 | E80: ='3StatementModel'!E93/'3StatementModel'!E$108 -> 0.18077314 | F80: ='3StatementModel'!F93/'3StatementModel'!F$108 -> 0.23120912 | G80: ='3StatementModel'!G93/'3StatementModel'!G$108 -> 0.29198607 | H80: ='3StatementModel'!H93/'3StatementModel'!H$108 -> 0.27427049 | I80: ='3StatementModel'!I93/'3StatementModel'!I$108 -> 0.25725496 | J80: ='3StatementModel'!J93/'3StatementModel'!J$108 -> 0.23660818 | K80: ='3StatementModel'!K93/'3StatementModel'!K$108 -> 0.21581187 | ... M80: ='3StatementModel'!M93/'3StatementModel'!M$108 -> 0.17429764
B82: =ConsolidatedBS!B55 -> Current liabilities :
B83: =ConsolidatedBS!B56 -> Trade payables | D83: ='3StatementModel'!D96/'3StatementModel'!D$110 -> 0.10394055 | E83: ='3StatementModel'!E96/'3StatementModel'!E$110 -> 0.11078741 | F83: ='3StatementModel'!F96/'3StatementModel'!F$110 -> 0.094305342 | G83: ='3StatementModel'!G96/'3StatementModel'!G$110 -> 0.09037255 | H83: ='3StatementModel'!H96/'3StatementModel'!H$110 -> 0.093093098 | I83: ='3StatementModel'!I96/'3StatementModel'!I$110 -> 0.097874346 | J83: ='3StatementModel'!J96/'3StatementModel'!J$110 -> 0.10345998 | K83: ='3StatementModel'!K96/'3StatementModel'!K$110 -> 0.10959124 | ... M83: ='3StatementModel'!M96/'3StatementModel'!M$110 -> 0.12597841
B84: =ConsolidatedBS!B57 -> Othe Current Liabilites / Financial Liabilities | D84: ='3StatementModel'!D97/'3StatementModel'!D$110 -> 0 | E84: ='3StatementModel'!E97/'3StatementModel'!E$110 -> 0 | F84: ='3StatementModel'!F97/'3StatementModel'!F$110 -> 0 | G84: ='3StatementModel'!G97/'3StatementModel'!G$110 -> 0 | H84: ='3StatementModel'!H97/'3StatementModel'!H$110 -> 0 | I84: ='3StatementModel'!I97/'3StatementModel'!I$110 -> 0 | J84: ='3StatementModel'!J97/'3StatementModel'!J$110 -> 0 | K84: ='3StatementModel'!K97/'3StatementModel'!K$110 -> 0 | ... M84: ='3StatementModel'!M97/'3StatementModel'!M$110 -> 0
B85: =ConsolidatedBS!B58 -> Borrowings | D85: ='3StatementModel'!D98/'3StatementModel'!D$110 -> 0.010812159 | E85: ='3StatementModel'!E98/'3StatementModel'!E$110 -> 0.0036456394 | F85: ='3StatementModel'!F98/'3StatementModel'!F$110 -> 0.0069143916 | G85: ='3StatementModel'!G98/'3StatementModel'!G$110 -> 0.0048478182 | H85: ='3StatementModel'!H98/'3StatementModel'!H$110 -> 0.0030215927 | I85: ='3StatementModel'!I98/'3StatementModel'!I$110 -> 0.005051898 | J85: ='3StatementModel'!J98/'3StatementModel'!J$110 -> 0.005282579 | K85: ='3StatementModel'!K98/'3StatementModel'!K$110 -> 0.0055358959 | ... M85: ='3StatementModel'!M98/'3StatementModel'!M$110 -> 0.0062306396
B86: =ConsolidatedBS!B59 -> Lease liability | D86: ='3StatementModel'!D99/'3StatementModel'!D$110 -> 0.0010797734 | E86: ='3StatementModel'!E99/'3StatementModel'!E$110 -> 0.00083953796 | F86: ='3StatementModel'!F99/'3StatementModel'!F$110 -> 0.0012980762 | G86: ='3StatementModel'!G99/'3StatementModel'!G$110 -> 0.001551371 | H86: ='3StatementModel'!H99/'3StatementModel'!H$110 -> 0.0024968343 | I86: ='3StatementModel'!I99/'3StatementModel'!I$110 -> 0.002256465 | J86: ='3StatementModel'!J99/'3StatementModel'!J$110 -> 0.002065208 | K86: ='3StatementModel'!K99/'3StatementModel'!K$110 -> 0.0019068207 | ... M86: ='3StatementModel'!M99/'3StatementModel'!M$110 -> 0.0016994954
B87: =ConsolidatedBS!B60 -> Other financial liabilities | D87: ='3StatementModel'!D100/'3StatementModel'!D$110 -> 0.014074146 | E87: ='3StatementModel'!E100/'3StatementModel'!E$110 -> 0.01548963 | F87: ='3StatementModel'!F100/'3StatementModel'!F$110 -> 0.01156288 | G87: ='3StatementModel'!G100/'3StatementModel'!G$110 -> 0.01323508 | H87: ='3StatementModel'!H100/'3StatementModel'!H$110 -> 0.013058241 | I87: ='3StatementModel'!I100/'3StatementModel'!I$110 -> 0.011801129 | J87: ='3StatementModel'!J100/'3StatementModel'!J$110 -> 0.010800871 | K87: ='3StatementModel'!K100/'3StatementModel'!K$110 -> 0.0099725178 | ... M87: ='3StatementModel'!M100/'3StatementModel'!M$110 -> 0.0088882233
B88: =ConsolidatedBS!B61 -> Provisions | D88: ='3StatementModel'!D101/'3StatementModel'!D$110 -> 0.0061949595 | E88: ='3StatementModel'!E101/'3StatementModel'!E$110 -> 0.0075477871 | F88: ='3StatementModel'!F101/'3StatementModel'!F$110 -> 0.0080989122 | G88: ='3StatementModel'!G101/'3StatementModel'!G$110 -> 0.0043043195 | H88: ='3StatementModel'!H101/'3StatementModel'!H$110 -> 0.0045189574 | I88: ='3StatementModel'!I101/'3StatementModel'!I$110 -> 0.0040839189 | J88: ='3StatementModel'!J101/'3StatementModel'!J$110 -> 0.0037377678 | K88: ='3StatementModel'!K101/'3StatementModel'!K$110 -> 0.0034511066 | ... M88: ='3StatementModel'!M101/'3StatementModel'!M$110 -> 0.0030758738
B89: =ConsolidatedBS!B62 -> Government grant | D89: ='3StatementModel'!D102/'3StatementModel'!D$110 -> 0.0010722177 | E89: ='3StatementModel'!E102/'3StatementModel'!E$110 -> 0.0012007561 | F89: ='3StatementModel'!F102/'3StatementModel'!F$110 -> 0.0016903119 | G89: ='3StatementModel'!G102/'3StatementModel'!G$110 -> 0.0011107782 | H89: ='3StatementModel'!H102/'3StatementModel'!H$110 -> 0.0014896368 | I89: ='3StatementModel'!I102/'3StatementModel'!I$110 -> 0.0013462299 | J89: ='3StatementModel'!J102/'3StatementModel'!J$110 -> 0.0012321241 | K89: ='3StatementModel'!K102/'3StatementModel'!K$110 -> 0.0011376286 | ... M89: ='3StatementModel'!M102/'3StatementModel'!M$110 -> 0.0010139363
B90: =ConsolidatedBS!B63 -> Contract liability | D90: ='3StatementModel'!D103/'3StatementModel'!D$110 -> 0.015638169 | E90: ='3StatementModel'!E103/'3StatementModel'!E$110 -> 0.010541623 | F90: ='3StatementModel'!F103/'3StatementModel'!F$110 -> 0.0093813615 | G90: ='3StatementModel'!G103/'3StatementModel'!G$110 -> 0.011353372 | H90: ='3StatementModel'!H103/'3StatementModel'!H$110 -> 0.0099608418 | I90: ='3StatementModel'!I103/'3StatementModel'!I$110 -> 0.009001915 | J90: ='3StatementModel'!J103/'3StatementModel'!J$110 -> 0.0082389169 | K90: ='3StatementModel'!K103/'3StatementModel'!K$110 -> 0.0076070484 | ... M90: ='3StatementModel'!M103/'3StatementModel'!M$110 -> 0.0067799473
B91: =ConsolidatedBS!B64 -> Other current liabilities | D91: ='3StatementModel'!D104/'3StatementModel'!D$110 -> 0.018755225 | E91: ='3StatementModel'!E104/'3StatementModel'!E$110 -> 0.018645178 | F91: ='3StatementModel'!F104/'3StatementModel'!F$110 -> 0.023629988 | G91: ='3StatementModel'!G104/'3StatementModel'!G$110 -> 0.019644646 | H91: ='3StatementModel'!H104/'3StatementModel'!H$110 -> 0.020555368 | I91: ='3StatementModel'!I104/'3StatementModel'!I$110 -> 0.01857651 | J91: ='3StatementModel'!J104/'3StatementModel'!J$110 -> 0.017001974 | K91: ='3StatementModel'!K104/'3StatementModel'!K$110 -> 0.015698039 | ... M91: ='3StatementModel'!M104/'3StatementModel'!M$110 -> 0.013991218
B92: =ConsolidatedBS!B65 -> Current tax liabilities (net) | D92: ='3StatementModel'!D105/'3StatementModel'!D$110 -> 0.0090001724 | E92: ='3StatementModel'!E105/'3StatementModel'!E$110 -> 0.010571363 | F92: ='3StatementModel'!F105/'3StatementModel'!F$110 -> 0.011607156 | G92: ='3StatementModel'!G105/'3StatementModel'!G$110 -> 0.0091672709 | H92: ='3StatementModel'!H105/'3StatementModel'!H$110 -> 0.0087832634 | I92: ='3StatementModel'!I105/'3StatementModel'!I$110 -> 0.0079377016 | J92: ='3StatementModel'!J105/'3StatementModel'!J$110 -> 0.0072649058 | K92: ='3StatementModel'!K105/'3StatementModel'!K$110 -> 0.0067077372 | ... M92: ='3StatementModel'!M105/'3StatementModel'!M$110 -> 0.0059784166
B93: =ConsolidatedBS!B66 -> Total current liabilities | D93: ='3StatementModel'!D106/'3StatementModel'!D$110 -> 0.18056738 | E93: ='3StatementModel'!E106/'3StatementModel'!E$110 -> 0.17926893 | F93: ='3StatementModel'!F106/'3StatementModel'!F$110 -> 0.16848842 | G93: ='3StatementModel'!G106/'3StatementModel'!G$110 -> 0.15558721 | H93: ='3StatementModel'!H106/'3StatementModel'!H$110 -> 0.15697783 | I93: ='3StatementModel'!I106/'3StatementModel'!I$110 -> 0.15793011 | J93: ='3StatementModel'!J106/'3StatementModel'!J$110 -> 0.15908433 | K93: ='3StatementModel'!K106/'3StatementModel'!K$110 -> 0.16160803 | ... M93: ='3StatementModel'!M106/'3StatementModel'!M$110 -> 0.17363616
B95: Total Liabilities | D95: ='3StatementModel'!D108/'3StatementModel'!D$110 -> 0.21434258 | E95: ='3StatementModel'!E108/'3StatementModel'!E$110 -> 0.21882696 | F95: ='3StatementModel'!F108/'3StatementModel'!F$110 -> 0.21916027 | G95: ='3StatementModel'!G108/'3StatementModel'!G$110 -> 0.21975162 | H95: ='3StatementModel'!H108/'3StatementModel'!H$110 -> 0.2163035 | I95: ='3StatementModel'!I108/'3StatementModel'!I$110 -> 0.21263032 | J95: ='3StatementModel'!J108/'3StatementModel'!J$110 -> 0.20839145 | K95: ='3StatementModel'!K108/'3StatementModel'!K$110 -> 0.20608324 | ... M95: ='3StatementModel'!M108/'3StatementModel'!M$110 -> 0.21028905
B97: Total equity and liabilities | D97: ='3StatementModel'!D110/'3StatementModel'!D$110 -> 1 | E97: ='3StatementModel'!E110/'3StatementModel'!E$110 -> 1 | F97: ='3StatementModel'!F110/'3StatementModel'!F$110 -> 1 | G97: ='3StatementModel'!G110/'3StatementModel'!G$110 -> 1 | H97: ='3StatementModel'!H110/'3StatementModel'!H$110 -> 1 | I97: ='3StatementModel'!I110/'3StatementModel'!I$110 -> 1 | J97: ='3StatementModel'!J110/'3StatementModel'!J$110 -> 1 | K97: ='3StatementModel'!K110/'3StatementModel'!K$110 -> 1 | ... M97: ='3StatementModel'!M110/'3StatementModel'!M$110 -> 1

Sheet RatioAnalysis
B2: ='Input Sheet'!C5 -> Eicher Motors
B3: Ratio Analysis
H4: Current Case: | I4: 0
D8: Actual | I8: Explicit Forecast Period
D9: =Controlsheet!D9 -> 2021 | E9: =Controlsheet!E9 -> 2022 | F9: =Controlsheet!F9 -> 2023 | G9: =Controlsheet!G9 -> 2024 | H9: =Controlsheet!H9 -> 2025 | I9: =H9+1 -> 2026 | J9: =I9+1 -> 2027 | K9: =J9+1 -> 2028 | L9: =K9+1 -> 2029 | M9: =L9+1 -> 2030
A11: # | B11: Liquidity Ratios
B13: Current Assets | D13: ='3StatementModel'!D74 -> 8807.36 | E13: ='3StatementModel'!E74 -> 5613.41 | F13: ='3StatementModel'!F74 -> 3649.82 | G13: ='3StatementModel'!G74 -> 4146.12 | H13: ='3StatementModel'!H74 -> 6958.2 | I13: ='3StatementModel'!I74 -> 8603.7111 | J13: ='3StatementModel'!J74 -> 10085.292 | K13: ='3StatementModel'!K74 -> 11563.591 | ... M13: ='3StatementModel'!M74 -> 13543.118
B14: Current Liabilities | D14: ='3StatementModel'!D106 -> 2628.81 | E14: ='3StatementModel'!E106 -> 2893.37 | F14: ='3StatementModel'!F106 -> 3234.58 | G14: ='3StatementModel'!G106 -> 3598.41 | H14: ='3StatementModel'!H106 -> 4265.78 | I14: ='3StatementModel'!I106 -> 4748.8254 | J14: ='3StatementModel'!J106 -> 5226.5299 | K14: ='3StatementModel'!K106 -> 5750.4646 | ... M14: ='3StatementModel'!M106 -> 6932.1831
B15: Current Ratio | D15: =D13/D14 -> 3.350322 | E15: =E13/E14 -> 1.9400941 | F15: =F13/F14 -> 1.1283752 | G15: =G13/G14 -> 1.1522089 | H15: =H13/H14 -> 1.6311671 | I15: =I13/I14 -> 1.8117556 | J15: =J13/J14 -> 1.9296344 | K15: =K13/K14 -> 2.0108968 | ... M15: =M13/M14 -> 1.9536584
B17: Current Assets | D17: =D13 -> 8807.36 | E17: =E13 -> 5613.41 | F17: =F13 -> 3649.82 | G17: =G13 -> 4146.12 | H17: =H13 -> 6958.2 | I17: =I13 -> 8603.7111 | J17: =J13 -> 10085.292 | K17: =K13 -> 11563.591 | ... M17: =M13 -> 13543.118
B18: Inventory | D18: ='3StatementModel'!D65 -> 874.6 | E18: ='3StatementModel'!E65 -> 1132.4 | F18: ='3StatementModel'!F65 -> 1278.44 | G18: ='3StatementModel'!G65 -> 1409.64 | H18: ='3StatementModel'!H65 -> 1563.75 | I18: ='3StatementModel'!I65 -> 1783.6358 | J18: ='3StatementModel'!J65 -> 2037.8039 | K18: ='3StatementModel'!K65 -> 2312.9075 | ... M18: ='3StatementModel'!M65 -> 2920.7395
B19: Prepaid Expenses | D19: 0 | E19: 0 | F19: 0 | G19: 0 | H19: 0 | I19: 0 | J19: 0 | K19: 0 | L19: 0 | M19: 0
B20: Current Liabilities | D20: =D14 -> 2628.81 | E20: =E14 -> 2893.37 | F20: =F14 -> 3234.58 | G20: =G14 -> 3598.41 | H20: =H14 -> 4265.78 | I20: =I14 -> 4748.8254 | J20: =J14 -> 5226.5299 | K20: =K14 -> 5750.4646 | ... M20: =M14 -> 6932.1831
B21: Quick Ratio (Acid Test) | D21: =(D17-D18-D19)/D20 -> 3.0176239 | E21: =(E17-E18-E19)/E20 -> 1.5487165 | F21: =(F17-F18-F19)/F20 -> 0.73313382 | G21: =(G17-G18-G19)/G20 -> 0.76046921 | H21: =(H17-H18-H19)/H20 -> 1.264587 | I21: =(I17-I18-I19)/I20 -> 1.4361605 | J21: =(J17-J18-J19)/J20 -> 1.5397382 | K21: =(K17-K18-K19)/K20 -> 1.6086845 | ... M21: =(M17-M18-M19)/M20 -> 1.532328
B23: Inventory Days | D23: ='3StatementModel'!D116 -> 36.607361 | E23: ='3StatementModel'!E116 -> 35.568416 | F23: ='3StatementModel'!F116 -> 30.464812 | G23: ='3StatementModel'!G116 -> 29.667461 | H23: ='3StatementModel'!H116 -> 28.756418 | I23: ='3StatementModel'!I116 -> 30 | J23: ='3StatementModel'!J116 -> 30 | K23: ='3StatementModel'!K116 -> 30 | ... M23: ='3StatementModel'!M116 -> 30
B24: Debtor Days | D24: ='3StatementModel'!D115 -> 6.6199636 | E24: ='3StatementModel'!E115 -> 10.705615 | F24: ='3StatementModel'!F115 -> 9.3237863 | G24: ='3StatementModel'!G115 -> 8.2505754 | H24: ='3StatementModel'!H115 -> 10.631419 | I24: ='3StatementModel'!I115 -> 12 | J24: ='3StatementModel'!J115 -> 12 | K24: ='3StatementModel'!K115 -> 10 | ... M24: ='3StatementModel'!M115 -> 10
B25: Creditor Days | D25: ='3StatementModel'!D117 -> 108.03986 | E25: ='3StatementModel'!E117 -> 109.58494 | F25: ='3StatementModel'!F117 -> 80.469879 | G25: ='3StatementModel'!G117 -> 84.949024 | H25: ='3StatementModel'!H117 -> 89.671902 | I25: ='3StatementModel'!I117 -> 90 | J25: ='3StatementModel'!J117 -> 90 | K25: ='3StatementModel'!K117 -> 90 | ... M25: ='3StatementModel'!M117 -> 90
B26: Cash Conversion Cycle | D26: =D23+D24-D25 -> -64.812538 | E26: =E23+E24-E25 -> -63.310912 | F26: =F23+F24-F25 -> -40.681281 | G26: =G23+G24-G25 -> -47.030988 | H26: =H23+H24-H25 -> -50.284065 | I26: =I23+I24-I25 -> -48 | J26: =J23+J24-J25 -> -48 | K26: =K23+K24-K25 -> -50 | ... M26: =M23+M24-M25 -> -50
A28: # | B28: Leverage Ratios / Solvency Ratios
B30: Total Debt | D30: ='3StatementModel'!D86+'3StatementModel'!D98 -> 157.41 | E30: ='3StatementModel'!E86+'3StatementModel'!E98 -> 58.84 | F30: ='3StatementModel'!F86+'3StatementModel'!F98 -> 195.7 | G30: ='3StatementModel'!G86+'3StatementModel'!G98 -> 275.58 | H30: ='3StatementModel'!H86+'3StatementModel'!H98 -> 266.47 | I30: ='3StatementModel'!I86+'3StatementModel'!I98 -> 368.91534 | J30: ='3StatementModel'!J86+'3StatementModel'!J98 -> 365.7009 | K30: ='3StatementModel'!K86+'3StatementModel'!K98 -> 351.75468 | ... N30: ='3StatementModel'!N86+'3StatementModel'!N98 -> 318.39955
B31: Total Equity | D31: ='3StatementModel'!D83 -> 11438.08 | E31: ='3StatementModel'!E83 -> 12608 | F31: ='3StatementModel'!F83 -> 14990.28 | G31: ='3StatementModel'!G83 -> 18045.53 | H31: ='3StatementModel'!H83 -> 21296.49 | I31: ='3StatementModel'!I83 -> 23675.543 | J31: ='3StatementModel'!J83 -> 26007.375 | K31: ='3StatementModel'!K83 -> 28249.773 | ... M31: ='3StatementModel'!M83 -> 31528.115
B32: Debt to Equity Ratio | D32: =D30/D31 -> 0.013761925 | E32: =E30/E31 -> 0.0046668782 | F32: =F30/F31 -> 0.013055126 | G32: =G30/G31 -> 0.015271372 | H32: =H30/H31 -> 0.012512391 | I32: =I30/I31 -> 0.015582128 | J32: =J30/J31 -> 0.014061431 | K32: =K30/K31 -> 0.012451593 | ... M32: =M30/M31 -> 0.0090168826
B34: Total Debt | D34: =D30 -> 157.41 | E34: =E30 -> 58.84 | F34: =F30 -> 195.7 | G34: =G30 -> 275.58 | H34: =H30 -> 266.47 | I34: =I30 -> 368.91534 | J34: =J30 -> 365.7009 | K34: =K30 -> 351.75468 | ... M34: =M30 -> 284.28531
B35: Total Assets | D35: ='3StatementModel'!D76 -> 14557.49 | E35: ='3StatementModel'!E76 -> 16133.9 | F35: ='3StatementModel'!F76 -> 19164.23 | G35: ='3StatementModel'!G76 -> 23122.72 | H35: ='3StatementModel'!H76 -> 27178.45 | I35: ='3StatementModel'!I76 -> 30073.197 | J35: ='3StatementModel'!J76 -> 32857.873 | K35: ='3StatementModel'!K76 -> 35586.829 | ... M35: ='3StatementModel'!M76 -> 39927.654
B36: Debt to Assets Ratio | D36: =D34/D35 -> 0.01081299 | E36: =E34/E35 -> 0.0036469793 | F36: =F34/F35 -> 0.010211733 | G36: =G34/G35 -> 0.011918148 | H36: =H34/H35 -> 0.009804459 | I36: =I34/I35 -> 0.012267247 | J36: =J34/J35 -> 0.01112978 | K36: =K34/K35 -> 0.0098844062 | ... M36: =M34/M35 -> 0.0071200104
B38: Total Equity | D38: =D31 -> 11438.08 | E38: =E31 -> 12608 | F38: =F31 -> 14990.28 | G38: =G31 -> 18045.53 | H38: =H31 -> 21296.49 | I38: =I31 -> 23675.543 | J38: =J31 -> 26007.375 | K38: =K31 -> 28249.773 | ... M38: =M31 -> 31528.115
B39: Total Assets | D39: =D35 -> 14557.49 | E39: =E35 -> 16133.9 | F39: =F35 -> 19164.23 | G39: =G35 -> 23122.72 | H39: =H35 -> 27178.45 | I39: =I35 -> 30073.197 | J39: =J35 -> 32857.873 | K39: =K35 -> 35586.829 | ... M39: =M35 -> 39927.654
B40: Equity Ratio | D40: =D38/D39 -> 0.78571787 | E40: =E38/E39 -> 0.78146016 | F40: =F38/F39 -> 0.78220101 | G40: =G38/G39 -> 0.78042419 | H40: =H38/H39 -> 0.78358001 | I40: =I38/I39 -> 0.78726391 | J40: =J38/J39 -> 0.79151122 | K40: =K38/K39 -> 0.79382663 | ... M40: =M38/M39 -> 0.78963105
A42: # | B42: Profitability / Margins Ratios
B44: Gross Profit | D44: ='3StatementModel'!D15 -> 3608.08 | E44: ='3StatementModel'!E15 -> 4342.15 | F44: ='3StatementModel'!F15 -> 6230.28 | G44: ='3StatementModel'!G15 -> 7555.13 | H44: ='3StatementModel'!H15 -> 8573.27 | I44: ='3StatementModel'!I15 -> 9765.4061 | J44: ='3StatementModel'!J15 -> 11008.217 | K44: ='3StatementModel'!K15 -> 12325.484 | ... M44: ='3StatementModel'!M15 -> 15138.193
B45: Total Sales | D45: ='3StatementModel'!D13 -> 8720.35 | E45: ='3StatementModel'!E13 -> 10297.83 | F45: ='3StatementModel'!F13 -> 14442.18 | G45: ='3StatementModel'!G13 -> 16535.78 | H45: ='3StatementModel'!H13 -> 18870.35 | I45: ='3StatementModel'!I13 -> 21700.902 | J45: ='3StatementModel'!J13 -> 24793.281 | K45: ='3StatementModel'!K13 -> 28140.374 | ... M45: ='3StatementModel'!M13 -> 35535.664
B46: Gross Margins | D46: =D44/D45 -> 0.41375404 | E46: =E44/E45 -> 0.4216568 | F46: =F44/F45 -> 0.43139471 | G46: =G44/G45 -> 0.45689589 | H46: =H44/H45 -> 0.45432491 | I46: =I44/I45 -> 0.45 | J46: =J44/J45 -> 0.444 | K46: =K44/K45 -> 0.438 | ... M46: =M44/M45 -> 0.426
B48: EBITDA | D48: ='3StatementModel'!D25 -> 1781.33 | E48: ='3StatementModel'!E25 -> 2172.25 | F48: ='3StatementModel'!F25 -> 3443.58 | G48: ='3StatementModel'!G25 -> 4326.91 | H48: ='3StatementModel'!H25 -> 4712.03 | I48: ='3StatementModel'!I25 -> 5490.3283 | J48: ='3StatementModel'!J25 -> 6123.9404 | K48: ='3StatementModel'!K25 -> 6781.8301 | ... M48: ='3StatementModel'!M25 -> 8137.6671
B49: Total Sales | D49: =D45 -> 8720.35 | E49: =E45 -> 10297.83 | F49: =F45 -> 14442.18 | G49: =G45 -> 16535.78 | H49: =H45 -> 18870.35 | I49: =I45 -> 21700.902 | J49: =J45 -> 24793.281 | K49: =K45 -> 28140.374 | ... M49: =M45 -> 35535.664
B50: EBITDA Margins | D50: =D48/D49 -> 0.20427276 | E50: =E48/E49 -> 0.2109425 | F50: =F48/F49 -> 0.23843907 | G50: =G48/G49 -> 0.26166954 | H50: =H48/H49 -> 0.24970549 | I50: =I48/I49 -> 0.253 | J50: =J48/J49 -> 0.247 | K50: =K48/K49 -> 0.241 | ... M50: =M48/M49 -> 0.229
B52: EBIT | D52: ='3StatementModel'!D30 -> 1330.6 | E52: ='3StatementModel'!E30 -> 1720.32 | F52: ='3StatementModel'!F30 -> 2917.37 | G52: ='3StatementModel'!G30 -> 3729.31 | H52: ='3StatementModel'!H30 -> 3982.7 | I52: ='3StatementModel'!I30 -> 4640.9983 | J52: ='3StatementModel'!J30 -> 5154.6104 | K52: ='3StatementModel'!K30 -> 5692.5001 | ... M52: ='3StatementModel'!M30 -> 6808.3371
B53: Total Sales | D53: =D49 -> 8720.35 | E53: =E49 -> 10297.83 | F53: =F49 -> 14442.18 | G53: =G49 -> 16535.78 | H53: =H49 -> 18870.35 | I53: =I49 -> 21700.902 | J53: =J49 -> 24793.281 | K53: =K49 -> 28140.374 | ... M53: =M49 -> 35535.664
B54: EBIT Margins | D54: =D52/D53 -> 0.15258562 | E54: =E52/E53 -> 0.16705655 | F54: =F52/F53 -> 0.20200344 | G54: =G52/G53 -> 0.22552973 | H54: =H52/H53 -> 0.21105597 | I54: =I52/I53 -> 0.213862 | J54: =J52/J53 -> 0.20790352 | K54: =K52/K53 -> 0.20228943 | ... M54: =M52/M53 -> 0.19159167
B56: Net Profit | D56: ='3StatementModel'!D40 -> 1346.97 | E56: ='3StatementModel'!E40 -> 1676.6 | F56: ='3StatementModel'!F40 -> 2913.94 | G56: ='3StatementModel'!G40 -> 4001.01 | H56: ='3StatementModel'!H40 -> 4734.44 | I56: ='3StatementModel'!I40 -> 5286.7843 | J56: ='3StatementModel'!J40 -> 5829.5801 | K56: ='3StatementModel'!K40 -> 6406.8505 | ... M56: ='3StatementModel'!M40 -> 7629.7736
B57: Total Sales | D57: =D53 -> 8720.35 | E57: =E53 -> 10297.83 | F57: =F53 -> 14442.18 | G57: =G53 -> 16535.78 | H57: =H53 -> 18870.35 | I57: =I53 -> 21700.902 | J57: =J53 -> 24793.281 | K57: =K53 -> 28140.374 | ... M57: =M53 -> 35535.664
B58: Net Profit Margins | D58: =D56/D57 -> 0.15446284 | E58: =E56/E57 -> 0.162811 | F58: =F56/F57 -> 0.20176594 | G58: =G56/G57 -> 0.24196077 | H58: =H56/H57 -> 0.25089307 | I58: =I56/I57 -> 0.24362048 | J58: =J56/J57 -> 0.23512741 | K58: =K56/K57 -> 0.22767467 | ... M58: =M56/M57 -> 0.2147075
B60: Net Income | D60: =D56 -> 1346.97 | E60: =E56 -> 1676.6 | F60: =F56 -> 2913.94 | G60: =G56 -> 4001.01 | H60: =H56 -> 4734.44 | I60: =I56 -> 5286.7843 | J60: =J56 -> 5829.5801 | K60: =K56 -> 6406.8505 | ... M60: =M56 -> 7629.7736
B61: Total Assets | D61: =D35 -> 14557.49 | E61: =E35 -> 16133.9 | F61: =F35 -> 19164.23 | G61: =G35 -> 23122.72 | H61: =H35 -> 27178.45 | I61: =I35 -> 30073.197 | J61: =J35 -> 32857.873 | K61: =K35 -> 35586.829 | ... M61: =M35 -> 39927.654
B62: Return on Assets | D62: =D60/D61 -> 0.092527627 | E62: =E60/E61 -> 0.10391784 | F62: =F60/F61 -> 0.15205098 | G62: =G60/G61 -> 0.17303371 | H62: =H60/H61 -> 0.17419831 | I62: =I60/I61 -> 0.17579721 | J62: =J60/J61 -> 0.17741806 | K62: =K60/K61 -> 0.18003432 | ... M62: =M60/M61 -> 0.19108995
B64: Net Income | D64: =D60 -> 1346.97 | E64: =E60 -> 1676.6 | F64: =F60 -> 2913.94 | G64: =G60 -> 4001.01 | H64: =H60 -> 4734.44 | I64: =I60 -> 5286.7843 | J64: =J60 -> 5829.5801 | K64: =K60 -> 6406.8505 | ... M64: =M60 -> 7629.7736
B65: Total Equity | D65: =D38 -> 11438.08 | E65: =E38 -> 12608 | F65: =F38 -> 14990.28 | G65: =G38 -> 18045.53 | H65: =H38 -> 21296.49 | I65: =I38 -> 23675.543 | J65: =J38 -> 26007.375 | K65: =K38 -> 28249.773 | ... M65: =M38 -> 31528.115
B66: Return on Equity | D66: =D64/D65 -> 0.1177619 | E66: =E64/E65 -> 0.13297906 | F66: =F64/F65 -> 0.19438863 | G66: =G64/G65 -> 0.22171751 | H66: =H64/H65 -> 0.22231081 | I66: =I64/I65 -> 0.2233015 | J66: =J64/J65 -> 0.22415104 | K66: =K64/K65 -> 0.22679299 | ... M66: =M64/M65 -> 0.24199904
A68: # | B68: Efficiency Ratios
B70: Revenue | D70: =D45 -> 8720.35 | E70: =E45 -> 10297.83 | F70: =F45 -> 14442.18 | G70: =G45 -> 16535.78 | H70: =H45 -> 18870.35 | I70: =I45 -> 21700.902 | J70: =J45 -> 24793.281 | K70: =K45 -> 28140.374 | ... M70: =M45 -> 35535.664
B71: Total Asset | D71: =D61 -> 14557.49 | E71: =E61 -> 16133.9 | F71: =F61 -> 19164.23 | G71: =G61 -> 23122.72 | H71: =H61 -> 27178.45 | I71: =I61 -> 30073.197 | J71: =J61 -> 32857.873 | K71: =K61 -> 35586.829 | ... M71: =M61 -> 39927.654
B72: Asset Turnover Ratio | D72: =D70/D71 -> 0.5990284 | E72: =E70/E71 -> 0.63827283 | F72: =F70/F71 -> 0.75360085 | G72: =G70/G71 -> 0.71513126 | H72: =H70/H71 -> 0.69431296 | I72: =I70/I71 -> 0.72160277 | J72: =J70/J71 -> 0.75456136 | K72: =K70/K71 -> 0.7907525 | ... M72: =M70/M71 -> 0.8900013
B74: Change in Revenue | E74: =E70-D70 -> 1577.48 | F74: =F70-E70 -> 4144.35 | G74: =G70-F70 -> 2093.6 | H74: =H70-G70 -> 2334.57 | I74: =I70-H70 -> 2830.5525 | J74: =J70-I70 -> 3092.3786 | K74: =K70-J70 -> 3347.0929 | L74: =L70-K70 -> 3587.8977 | M74: =M70-L70 -> 3807.3926
B75: Change in Total Asset | E75: =E71-D71 -> 1576.41 | F75: =F71-E71 -> 3030.33 | G75: =G71-F71 -> 3958.49 | H75: =H71-G71 -> 4055.73 | I75: =I71-H71 -> 2894.7474 | J75: =J71-I71 -> 2784.6754 | K75: =K71-J71 -> 2728.9565 | L75: =L71-K71 -> 2269.9828 | M75: =M71-L71 -> 2070.8422
B76: Reinvestment Ratio | E76: =E74/E75 -> 1.0006788 | F76: =F74/F75 -> 1.3676233 | G76: =G74/G75 -> 0.52888854 | H76: =H74/H75 -> 0.57562264 | I76: =I74/I75 -> 0.97782367 | J76: =J74/J75 -> 1.1104988 | K76: =K74/K75 -> 1.2265102 | L76: =L74/L75 -> 1.5805836 | M76: =M74/M75 -> 1.8385721
B78: COGS | D78: ='3StatementModel'!D14 -> 5112.27 | E78: ='3StatementModel'!E14 -> 5955.68 | F78: ='3StatementModel'!F14 -> 8211.9 | G78: ='3StatementModel'!G14 -> 8980.65 | H78: ='3StatementModel'!H14 -> 10297.08 | I78: ='3StatementModel'!I14 -> 11935.496 | J78: ='3StatementModel'!J14 -> 13785.064 | K78: ='3StatementModel'!K14 -> 15814.89 | ... M78: ='3StatementModel'!M14 -> 20397.471
B79: Inventory | D79: =D18 -> 874.6 | E79: =E18 -> 1132.4 | F79: =F18 -> 1278.44 | G79: =G18 -> 1409.64 | H79: =H18 -> 1563.75 | I79: =I18 -> 1783.6358 | J79: =J18 -> 2037.8039 | K79: =K18 -> 2312.9075 | ... M79: =M18 -> 2920.7395
B80: Inventory Turnover Ratio | D80: =D78/D79 -> 5.8452664 | E80: =E78/E79 -> 5.259343 | F80: =F78/F79 -> 6.4233754 | G80: =G78/G79 -> 6.3708819 | H80: =H78/H79 -> 6.5848633 | I80: =I78/I79 -> 6.6916667 | J80: =J78/J79 -> 6.7646667 | K80: =K78/K79 -> 6.8376667 | ... M80: =M78/M79 -> 6.9836667
A82: # | B82: Coverage Ratios
B84: Total Debt | D84: =D34 -> 157.41 | E84: =E34 -> 58.84 | F84: =F34 -> 195.7 | G84: =G34 -> 275.58 | H84: =H34 -> 266.47 | I84: =I34 -> 368.91534 | J84: =J34 -> 365.7009 | K84: =K34 -> 351.75468 | ... M84: =M34 -> 284.28531
B85: EBITDA | D85: =D48 -> 1781.33 | E85: =E48 -> 2172.25 | F85: =F48 -> 3443.58 | G85: =G48 -> 4326.91 | H85: =H48 -> 4712.03 | I85: =I48 -> 5490.3283 | J85: =J48 -> 6123.9404 | K85: =K48 -> 6781.8301 | ... M85: =M48 -> 8137.6671
B86: Debt to EBITDA Coverage Ratio | D86: =D84/D85 -> 0.088366558 | E86: =E84/E85 -> 0.027087122 | F86: =F84/F85 -> 0.056830392 | G86: =G84/G85 -> 0.063689792 | H86: =H84/H85 -> 0.056550998 | I86: =I84/I85 -> 0.067193676 | J86: =J84/J85 -> 0.059716599 | K86: =K84/K85 -> 0.05186722 | ... M86: =M84/M85 -> 0.034934498
B88: EBIT | D88: =D52 -> 1330.6 | E88: =E52 -> 1720.32 | F88: =F52 -> 2917.37 | G88: =G52 -> 3729.31 | H88: =H52 -> 3982.7 | I88: =I52 -> 4640.9983 | J88: =J52 -> 5154.6104 | K88: =K52 -> 5692.5001 | ... M88: =M52 -> 6808.3371
B89: Interest Expense | D89: ='3StatementModel'!D34 -> 16.45 | E89: ='3StatementModel'!E34 -> 18.78 | F89: ='3StatementModel'!F34 -> 28.02 | G89: ='3StatementModel'!G34 -> 50.88 | H89: ='3StatementModel'!H34 -> 54.34 | I89: ='3StatementModel'!I34 -> 22.238487 | J89: ='3StatementModel'!J34 -> 25.711568 | K89: ='3StatementModel'!K34 -> 25.110945 | ... M89: ='3StatementModel'!M34 -> 21.332504
B90: Interest Coverage Ratio | D90: =D88/D89 -> 80.887538 | E90: =E88/E89 -> 91.603834 | F90: =F88/F89 -> 104.11742 | G90: =G88/G89 -> 73.296187 | H90: =H88/H89 -> 73.292234 | I90: =I88/I89 -> 208.69218 | J90: =J88/J89 -> 200.47826 | K90: =K88/K89 -> 226.69398 | ... M90: =M88/M89 -> 319.15322

Sheet DCF>

Sheet DCFVal
B2: ='Input Sheet'!C5 -> Eicher Motors
B3: Ratio Analysis | U3: Mid Year Convention
H4: Current Case: | I4: 0 | U4: Yes
U5: No
D8: Actual | I8: Explicit Forecast Period
B9: In INR Crores unless stated otherwise | D9: ='3StatementModel'!D9 -> 2021 | E9: ='3StatementModel'!E9 -> 2022 | F9: ='3StatementModel'!F9 -> 2023 | G9: ='3StatementModel'!G9 -> 2024 | H9: ='3StatementModel'!H9 -> 2025 | I9: ='3StatementModel'!I9 -> 2026 | J9: ='3StatementModel'!J9 -> 2027 | K9: ='3StatementModel'!K9 -> 2028 | ... R9: ='3StatementModel'!R9 -> 2035
A11: # | B11: Free Cash Flow to Firm
B13: EBITDA | D13: ='3StatementModel'!D25 -> 1781.33 | E13: ='3StatementModel'!E25 -> 2172.25 | F13: ='3StatementModel'!F25 -> 3443.58 | G13: ='3StatementModel'!G25 -> 4326.91 | H13: ='3StatementModel'!H25 -> 4712.03 | I13: ='3StatementModel'!I25 -> 5490.3283 | J13: ='3StatementModel'!J25 -> 6123.9404 | K13: ='3StatementModel'!K25 -> 6781.8301 | ... R13: ='3StatementModel'!R25 -> 14341.35
B14: Less : Depreciation & Amortization | D14: ='3StatementModel'!D29*-1 -> -450.73 | E14: ='3StatementModel'!E29*-1 -> -451.93 | F14: ='3StatementModel'!F29*-1 -> -526.21 | G14: ='3StatementModel'!G29*-1 -> -597.6 | H14: ='3StatementModel'!H29*-1 -> -729.33 | I14: ='3StatementModel'!I29*-1 -> -849.33 | J14: ='3StatementModel'!J29*-1 -> -969.33 | K14: ='3StatementModel'!K29*-1 -> -1089.33 | ... R14: ='3StatementModel'!R29*-1 -> -1929.33
B15: EBIT | D15: =SUM(D13:D14) -> 1330.6 | E15: =SUM(E13:E14) -> 1720.32 | F15: =SUM(F13:F14) -> 2917.37 | G15: =SUM(G13:G14) -> 3729.31 | H15: =SUM(H13:H14) -> 3982.7 | I15: =SUM(I13:I14) -> 4640.9983 | J15: =SUM(J13:J14) -> 5154.6104 | K15: =SUM(K13:K14) -> 5692.5001 | ... R15: =SUM(R13:R14) -> 12412.02
B16: Less : Tax | D16: ='3StatementModel'!D39*-1 -> -451.5 | E16: ='3StatementModel'!E39*-1 -> -525.91 | F16: ='3StatementModel'!F39*-1 -> -885.69 | G16: ='3StatementModel'!G39*-1 -> -1201.01 | H16: ='3StatementModel'!H39*-1 -> -1198.63 | I16: ='3StatementModel'!I39*-1 -> -1160.2325 | J16: ='3StatementModel'!J39*-1 -> -1288.3794 | K16: ='3StatementModel'!K39*-1 -> -1423.6482 | ... R16: ='3StatementModel'!R39*-1 -> -3109.5617
B17: EBIT (1-t) | D17: =SUM(D15:D16) -> 879.1 | E17: =SUM(E15:E16) -> 1194.41 | F17: =SUM(F15:F16) -> 2031.68 | G17: =SUM(G15:G16) -> 2528.3 | H17: =SUM(H15:H16) -> 2784.07 | I17: =SUM(I15:I16) -> 3480.7659 | J17: =SUM(J15:J16) -> 3866.231 | K17: =SUM(K15:K16) -> 4268.852 | ... R17: =SUM(R15:R16) -> 9302.4583
B18: Add : Depreciation & Amortization | D18: =D14*-1 -> 450.73 | E18: =E14*-1 -> 451.93 | F18: =F14*-1 -> 526.21 | G18: =G14*-1 -> 597.6 | H18: =H14*-1 -> 729.33 | I18: =I14*-1 -> 849.33 | J18: =J14*-1 -> 969.33 | K18: =K14*-1 -> 1089.33 | ... R18: =R14*-1 -> 1929.33
B19: Cash NOPAT | D19: =D17+D18 -> 1329.83 | E19: =E17+E18 -> 1646.34 | F19: =F17+F18 -> 2557.89 | G19: =G17+G18 -> 3125.9 | H19: =H17+H18 -> 3513.4 | I19: =I17+I18 -> 4330.0959 | J19: =J17+J18 -> 4835.561 | K19: =K17+K18 -> 5358.182 | ... R19: =R17+R18 -> 11231.788
B20: Less : Reinvestments
B21: Change in Working Capital | D21: ='3StatementModel'!D125 -> 235 | E21: ='3StatementModel'!E125 -> -131 | F21: ='3StatementModel'!F125 -> 66 | G21: ='3StatementModel'!G125 -> 388 | H21: ='3StatementModel'!H125 -> 211 | I21: ='3StatementModel'!I125 -> -31.7409 | J21: ='3StatementModel'!J125 -> 32.190167 | K21: ='3StatementModel'!K125 -> 195.91787 | ... R21: ='3StatementModel'!R125 -> 66.7316
B22: Capex during the year | D22: ='3StatementModel'!D129 -> -515 | E22: ='3StatementModel'!E129 -> -638.9 | F22: ='3StatementModel'!F129 -> -673.2 | G22: ='3StatementModel'!G129 -> -814.8 | H22: ='3StatementModel'!H129 -> -1028 | I22: ='3StatementModel'!I129 -> -1200 | J22: ='3StatementModel'!J129 -> -1200 | K22: ='3StatementModel'!K129 -> -1200 | ... R22: ='3StatementModel'!R129 -> -1200
B23: Free Cash Flow to Firm | D23: =D19+SUM(D21:D22) -> 1049.83 | E23: =E19+SUM(E21:E22) -> 876.44 | F23: =F19+SUM(F21:F22) -> 1950.69 | G23: =G19+SUM(G21:G22) -> 2699.1 | H23: =H19+SUM(H21:H22) -> 2696.4 | I23: =I19+SUM(I21:I22) -> 3098.355 | J23: =J19+SUM(J21:J22) -> 3667.7512 | K23: =K19+SUM(K21:K22) -> 4354.0998 | ... R23: =R19+SUM(R21:R22) -> 10098.52
B25: Discount Period (years) | C25: Mid Year ? | D25: Yes | I25: =IF(D25="Yes",(I9-H9)/2,I9-H9) -> 0.5 | J25: =I25+1 -> 1.5 | K25: =J25+1 -> 2.5 | L25: =K25+1 -> 3.5 | M25: =L25+1 -> 4.5 | N25: =M25+1 -> 5.5 | O25: =N25+1 -> 6.5 | P25: =O25+1 -> 7.5 | Q25: =P25+1 -> 8.5 | R25: =Q25+1 -> 9.5
B26: Discount Rate (WACC) | C26: =WACC!E23 -> 0.12
B27: Present Value Factor | I27: =1/(1+$C$26)^I25 -> 0.94491118 | J27: =1/(1+$C$26)^J25 -> 0.8436707 | K27: =1/(1+$C$26)^K25 -> 0.75327741 | L27: =1/(1+$C$26)^L25 -> 0.67256912 | M27: =1/(1+$C$26)^M25 -> 0.60050814 | N27: =1/(1+$C$26)^N25 -> 0.53616798 | O27: =1/(1+$C$26)^O25 -> 0.47872141 | P27: =1/(1+$C$26)^P25 -> 0.42742983 | ... R27: =1/(1+$C$26)^R25 -> 0.34074445
B29: Present Value of Free Cash Flow to Firm | I29: =I23*I27 -> 2927.6702 | J29: =J23*J27 -> 3094.3742 | K29: =K23*K27 -> 3279.8451 | L29: =L23*L27 -> 3204.7264 | M29: =M23*M27 -> 3193.2485 | N29: =N23*N27 -> 3236.5689 | O29: =O23*O27 -> 3299.0207 | P29: =P23*P27 -> 3353.2351 | ... R29: =R23*R27 -> 3441.0146
A31: # | B31: DCF Calculation - Perpetuity Growth
B33: Perpetual Growth Rate | C33: =WACC!E6 -> 0.043790142
B34: Terminal Year FCFF X (1+PGR) | C34: =R23*(1+C33) -> 10540.736
B35: Terminal Value | C35: =C34/(C26-C33) -> 138311.97
B36: Present Value of Terminal Value | C36: =C35*R27 -> 47129.035
B37: Present Value of FCFFs | C37: =SUM(I29:R29) -> 32429.964
B38: Enterprise Value | C38: =SUM(C36:C37) -> 79558.999
B39: Implied Exit Multiple | C39: =C38/R13 -> 5.5475251
B40: Implied EV/EBITDA | C40: =C38/'3StatementModel'!H25 -> 16.88423
B41: Less : Debt | C41: =SUM('3StatementModel'!H86,'3StatementModel'!H98)*-1 -> -266.47
B42: Add : Cash | C42: =SUM('3StatementModel'!H72,'3StatementModel'!H73) -> 267.05
B43: Less : Minority Interest | C43: 0
B44: Add : Non Operating Asset | C44: ='3StatementModel'!H58 -> 16013.75
B45: Equity Value | C45: =SUM(C38,C41,C42,C43,C44) -> 95573.329
B46: Less : Value of Options | C46: ='Options Value'!E28*-1 -> -202.92815
B47: Equity Value for Shareholders | C47: =SUM(C45:C46) -> 95370.401
A49: # | B49: DCF Calculation - Exit Multiple
B51: Exit Multiple | C51: 21.4
B52: Terminal Year EBITDA | C52: =R13 -> 14341.35
B53: Terminal Value | C53: =C51*C52 -> 306904.89
B54: Present Value of Terminal Value | C54: =C53*R27 -> 104576.14
B55: Present Value of FCFFs | C55: =C37 -> 32429.964
B56: Enterprise Value | C56: =SUM(C54:C55) -> 137006.1
B57: Implied Exit Multiple | C57: =C56/R13 -> 9.553222
B58: Implied EV/EBITDA | C58: =C56/'3StatementModel'!H25 -> 29.075812
B59: Less : Debt | C59: =C41 -> -266.47
B60: Add : Cash | C60: =C42 -> 267.05
B61: =B43 -> Less : Minority Interest | C61: =C43 -> 0
B62: =B44 -> Add : Non Operating Asset | C62: =C44 -> 16013.75
B63: Equity Value | C63: =SUM(C56,C59,C60,C61,C62) -> 153020.43
B64: =B46 -> Less : Value of Options | C64: =C46 -> -202.92815
B65: =B47 -> Equity Value for Shareholders | C65: =SUM(C63:C64) -> 152817.5
A67: # | B67: Sensitivity Analysis
E70: WACC
D71: =C47 -> 95370.401 | E71: 0.11 | F71: 0.12 | G71: 0.13 | H71: 0.14 | I71: 0.15
C72: Terminal Growth% | D72: 0.03 | E72: 98018.165 | F72: 87621.866 | G72: 79382.347 | H72: 72706.13 | I72: 67197.973
D73: 0.04 | E73: 105445.35 | F73: 92974.555 | G73: 83352.877 | H73: 75720.342 | I73: 69530.099
D74: 0.05 | E74: 115348.27 | F74: 99856.585 | G74: 88316.039 | H74: 79404.379 | I74: 72328.652
D75: 0.06 | E75: 129212.35 | F75: 109032.62 | G75: 94697.248 | H75: 84009.426 | I75: 75749.104
D76: 0.07 | E76: 150008.48 | F76: 121879.08 | G76: 103205.53 | H76: 89930.199 | I76: 80024.67
E81: WACC
D82: =C65 -> 152817.5 | E82: 0.11 | F82: 0.12 | G82: 0.13 | H82: 0.14 | I82: 0.15
C83: Exit Multiple | D83: 18 | E83: 145559.18 | F83: 136202.6 | G83: 127648.28 | H83: 119819.97 | I83: 112649.33
D84: 19 | E84: 150880.53 | F84: 141089.34 | G84: 132139.3 | H84: 123950.39 | I84: 116450.88
D85: 20 | E85: 156201.88 | F85: 145976.07 | G85: 136630.31 | H85: 128080.81 | I85: 120252.43
D86: 21 | E86: 161523.23 | F86: 150862.81 | G86: 141121.33 | H86: 132211.23 | I86: 124053.98
D87: 22 | E87: 166844.58 | F87: 155749.54 | G87: 145612.35 | H87: 136341.64 | I87: 127855.52

Sheet Relative Pricing>

Sheet Comps_Description
D3: Comparable Companies | E3: Description
D4: NSE: BAJAJ-AUTO | E4: Bajaj Auto, the flagship company of Bajaj Group, is a two-wheeler and three-wheeler manufacturing company that exports to 79 countries across several countries in Latin America, Southeast Asia, and many more. Its headquarter is in Pune, India. It has acquired 48% of the KTM Brand which manufactures sports and super sports two-wheelers, which was 14% in 2007 when the company first acquired KTM.
D9: NSE: TVSMOTOR | E9: TVS Motor Company Ltd (TVSM) is engaged in manufacturing two-wheelers and its accessories. It is one of the leading players in the two-wheeler industry and is the only company to have a presence in all the three categories, i.e., motorcycles, scooters, and mopeds, catering to both domestic and international markets. TVSM is also the only company to have a presence in the moped segment for the domestic market.
D14: NSE: HEROMOTOCO | E14: Hero Moto Corp earlier also known as “Hero Honda” is one of India’s first motorcycle manufacturers. It is the world’s largest manufacturer of 2 Wheelers, in terms of unit volumes sold by a single company in a calendar year, for more than 2 decades. The overall market share of the co. in the indian motorcycle market is 48% and in the two-wheeler segment stands at 34 % as of FY22.
D19: NSE: M&M | E19: Mahindra & Mahindra Ltd is one of the most diversified automobile company in India with presence across 2-wheelers, 3-wheelers, PVs, CVs, tractors & earthmovers. It also has presence across financial services, auto components, hospitality, infrastructure, retail, logistics, steel trading and processing, IT businesses, agri, aerospace, consulting services, defence, energy and industrial equipment through its subsidiaries and group companies.
D24: NSE: ASHOKLEY | E24: Ashok Leyland is the flagship Company of the Hinduja group, having a long-standing presence in the domestic medium and heavy commercial vehicle (M&HCV) segment. The company has a strong brand and well-diversified distribution and service network across the country and has a presence in 50 countries, it is one of the most fully-integrated manufacturing companies. Its headquarter is in Chennai. The company is India's 2nd largest manufacturer of commercial vehicles, the 4th largest manufacturer of buses globally, and the 9th largest manufacturer of trucks. It had a market share of 31% in the M&HCV bus and truck segment and 20% in the LCV segment as of FY24.

Sheet Benchmarking
B2: Summary
C3: 2021 | D3: 2022 | E3: 2023 | F3: 2024 | G3: 2025 | H3: Historical Average
B5: Average Revenue Growth | C5: =C28 -> 0.00028814762 | D5: =D28 -> 0.15434106 | E5: =E28 -> 0.22836987 | F5: =F28 -> 0.17706546 | G5: =G28 -> 0.12263924 | H5: =AVERAGE(C5:G5) -> 0.13654076
B6: Average EBITDA Margins | C6: =C40 -> 0.14465962 | D6: =D40 -> 0.13619437 | E6: =E40 -> 0.14763232 | F6: =F40 -> 0.16333651 | G6: =G40 -> 0.16740662 | H6: =AVERAGE(C6:G6) -> 0.15184589
B7: Average EBIT Margins | C7: =C64 -> 0.11790685 | D7: =D64 -> 0.11097654 | E7: =E64 -> 0.12487091 | F7: =F64 -> 0.14157478 | G7: =G64 -> 0.14487266 | H7: =AVERAGE(C7:G7) -> 0.12804035
B8: Average PBT Margins | C8: =C77 -> 0.10853736 | D8: =D77 -> 0.12049141 | E8: =E77 -> 0.12617845 | F8: =F77 -> 0.13559775 | G8: =G77 -> 0.13637448 | H8: =AVERAGE(C8:G8) -> 0.12543589
B9: Average PAT Margins | C9: =C52 -> 0.080390574 | D9: =D52 -> 0.093822061 | E9: =E52 -> 0.095738562 | F9: =F52 -> 0.10111875 | G9: =G52 -> 0.098233749 | H9: =AVERAGE(C9:G9) -> 0.093860739
B11: Median Revenue Growth | C11: =C29 -> 0.0078262952 | D11: =D29 -> 0.20438213 | E11: =E29 -> 0.23435 | F11: =F29 -> 0.18558091 | G11: =G29 -> 0.1314 | H11: =MEDIAN(C11:G11) -> 0.18558091
B12: Median EBITDA Margins | C12: =C41 -> 0.14285649 | D12: =D41 -> 0.13588182 | E12: =E41 -> 0.14660547 | F12: =F41 -> 0.15974025 | G12: =G41 -> 0.16824309 | H12: =MEDIAN(C12:G12) -> 0.14660547
B13: Median EBIT Margins | C13: =C65 -> 0.10856739 | D13: =D65 -> 0.10539117 | E13: =E65 -> 0.11546029 | F13: =F65 -> 0.13175169 | G13: =G65 -> 0.13947099 | H13: =MEDIAN(C13:G13) -> 0.11546029
B14: Median PBT Margins | C14: =C78 -> 0.083427033 | D14: =D78 -> 0.10365388 | E14: =E78 -> 0.11452596 | F14: =F78 -> 0.12479268 | G14: =G78 -> 0.13241525 | H14: =MEDIAN(C14:G14) -> 0.11452596
B15: Median PAT Margins | C15: =C53 -> 0.0630585 | D15: =D53 -> 0.0796252 | E15: =E53 -> 0.087881984 | F15: =F53 -> 0.093625582 | G15: =G53 -> 0.097660046 | H15: =MEDIAN(C15:G15) -> 0.087881984
B20: Revenue Growth
B21: in % | C21: 2021 | D21: 2022 | E21: 2023 | F21: 2024 | G21: 2025
B23: Bajaj Auto | C23: -0.0728 | D23: 0.1948 | E23: 0.0999 | F23: 0.2308 | G23: 0.1365
B24: TVS Motors | C24: 0.0303 | D24: 0.2541 | E24: 0.3128 | F24: 0.2243 | G24: 0.1263
B25: Hero Motorcorp | C25: 0.0583 | D25: -0.0455 | E25: 0.1559 | F25: 0.1063 | G25: 0.083
B26: Mahindra & Mahindra Ltd | C26: -0.01464741 | D26: 0.21396426 | E26: 0.34487949 | F26: 0.14686182 | G26: 0.14475698
J27: Mahindra & Mahindra Ltd
B28: Mean | C28: =AVERAGE(C23:C26) -> 0.00028814762 | D28: =AVERAGE(D23:D26) -> 0.15434106 | E28: =AVERAGE(E23:E26) -> 0.22836987 | F28: =AVERAGE(F23:F26) -> 0.17706546 | G28: =AVERAGE(G23:G26) -> 0.12263924
B29: Median | C29: =MEDIAN(C23:C26) -> 0.0078262952 | D29: =MEDIAN(D23:D26) -> 0.20438213 | E29: =MEDIAN(E23:E26) -> 0.23435 | F29: =MEDIAN(F23:F26) -> 0.18558091 | G29: =MEDIAN(G23:G26) -> 0.1314
B32: EBITDA Margin
B33: in % | C33: 2021 | D33: 2022 | E33: 2023 | F33: 2024 | G33: 2025
B35: Bajaj Auto | C35: 0.17799523 | D35: 0.15866182 | E35: 0.1773302 | F35: 0.1953331 | G35: 0.18736512
B36: TVS Motors | C36: 0.11493027 | D36: 0.11310182 | E36: 0.12593517 | F36: 0.14050266 | G36: 0.14912106
B37: Hero Motorcorp | C37: 0.13106351 | D37: 0.11017966 | E37: 0.11998813 | F37: 0.13853245 | G37: 0.14145616
B38: Mahindra & Mahindra Ltd | C38: 0.15464948 | D38: 0.16283417 | E38: 0.16727577 | F38: 0.17897785 | G38: 0.19168415
B40: Mean | C40: =AVERAGE(C35:C38) -> 0.14465962 | D40: =AVERAGE(D35:D38) -> 0.13619437 | E40: =AVERAGE(E35:E38) -> 0.14763232 | F40: =AVERAGE(F35:F38) -> 0.16333651 | G40: =AVERAGE(G35:G38) -> 0.16740662
B41: Median | C41: =MEDIAN(C35:C38) -> 0.14285649 | D41: =MEDIAN(D35:D38) -> 0.13588182 | E41: =MEDIAN(E35:E38) -> 0.14660547 | F41: =MEDIAN(F35:F38) -> 0.15974025 | G41: =MEDIAN(G35:G38) -> 0.16824309
B44: PAT Margin
B45: in % | C45: 2021 | D45: 2022 | E45: 2023 | F45: 2024 | G45: 2025
B47: Bajaj Auto | C47: 0.17508403 | D47: 0.18602878 | E47: 0.16623637 | F47: 0.17178886 | G47: 0.14363751
B48: TVS Motors | C48: 0.031280862 | D48: 0.030009062 | E48: 0.040953913 | F48: 0.045434968 | G48: 0.053977397
B49: Hero Motorcorp | C49: 0.094836138 | D49: 0.078813845 | E49: 0.081968173 | F49: 0.099028755 | G49: 0.10692679
B50: Mahindra & Mahindra Ltd | C50: 0.020361271 | D50: 0.080436555 | E50: 0.093795795 | F50: 0.088222409 | G50: 0.088393301
B52: Mean | C52: =AVERAGE(C47:C50) -> 0.080390574 | D52: =AVERAGE(D47:D50) -> 0.093822061 | E52: =AVERAGE(E47:E50) -> 0.095738562 | F52: =AVERAGE(F47:F50) -> 0.10111875 | G52: =AVERAGE(G47:G50) -> 0.098233749
B53: Median | C53: =MEDIAN(C47:C50) -> 0.0630585 | D53: =MEDIAN(D47:D50) -> 0.0796252 | E53: =MEDIAN(E47:E50) -> 0.087881984 | F53: =MEDIAN(F47:F50) -> 0.093625582 | G53: =MEDIAN(G47:G50) -> 0.097660046
B56: EBIT Margin
B57: in % | C57: 2021 | D57: 2022 | E57: 2023 | F57: 2024 | G57: 2025
B59: Bajaj Auto | C59: 0.16864556 | D59: 0.15052296 | E59: 0.16948911 | F59: 0.18720369 | G59: 0.1792421
B60: TVS Motors | C60: 0.085847045 | D60: 0.082600878 | E60: 0.099073966 | F60: 0.11559203 | G60: 0.12540631
B61: Hero Motorcorp | C61: 0.10796471 | D61: 0.086846661 | E61: 0.09957176 | F61: 0.11849043 | G61: 0.12130658
B62: Mahindra & Mahindra Ltd | C62: 0.10917006 | D62: 0.12393567 | E62: 0.13134881 | F62: 0.14501295 | G62: 0.15353567
B64: Mean | C64: =AVERAGE(C59:C62) -> 0.11790685 | D64: =AVERAGE(D59:D62) -> 0.11097654 | E64: =AVERAGE(E59:E62) -> 0.12487091 | F64: =AVERAGE(F59:F62) -> 0.14157478 | G64: =AVERAGE(G59:G62) -> 0.14487266
B65: Median | C65: =MEDIAN(C59:C62) -> 0.10856739 | D65: =MEDIAN(D59:D62) -> 0.10539117 | E65: =MEDIAN(E59:E62) -> 0.11546029 | F65: =MEDIAN(F59:F62) -> 0.13175169 | G65: =MEDIAN(G59:G62) -> 0.13947099
B69: PBT Margin
B70: in % | C70: 2021 | D70: 2022 | E70: 2023 | F70: 2024 | G70: 2025
B72: Bajaj Auto | C72: 0.22498872 | D72: 0.23085675 | E72: 0.21511173 | F72: 0.22375627 | G72: 0.2004828
B73: TVS Motors | C73: 0.042306659 | D73: 0.043801126 | E73: 0.060550153 | F73: 0.069049379 | G73: 0.080184608
B74: Hero Motorcorp | C74: 0.12433529 | D74: 0.10348486 | E74: 0.11310899 | F74: 0.13470193 | G74: 0.14499179
B75: Mahindra & Mahindra Ltd | C75: 0.042518772 | D75: 0.1038229 | E75: 0.11594292 | F75: 0.11488344 | G75: 0.11983871
B77: Mean | C77: =AVERAGE(C72:C75) -> 0.10853736 | D77: =AVERAGE(D72:D75) -> 0.12049141 | E77: =AVERAGE(E72:E75) -> 0.12617845 | F77: =AVERAGE(F72:F75) -> 0.13559775 | G77: =AVERAGE(G72:G75) -> 0.13637448
B78: Median | C78: =MEDIAN(C72:C75) -> 0.083427033 | D78: =MEDIAN(D72:D75) -> 0.10365388 | E78: =MEDIAN(E72:E75) -> 0.11452596 | F78: =MEDIAN(F72:F75) -> 0.12479268 | G78: =MEDIAN(G72:G75) -> 0.13241525
B83: Revenue
C84: 2025 | D84: 2026 | E84: 2027
B85: Eicher Motors | C85: 18870.35 | D85: 21700.902 | E85: 24793.281
B86: Bajaj Auto | C86: 50995 | D86: 60148 | E86: 67449
B87: TVS Motors | C87: 44089 | D87: 40595 | E87: 49467
B88: Hero Motorcorp | C88: 40923 | D88: 43001 | E88: 45740
B89: Mahindra & Mahindra Ltd | C89: 159211 | D89: 180172 | E89: 199947
B91: EBITDA
C92: 2025 | D92: 2026 | E92: 2027
B93: Eicher Motors | C93: 4712.03 | D93: 5490.3283 | E93: 6272.7001
B94: Bajaj Auto | C94: 10468 | D94: 12034 | E94: 13765
B95: TVS Motors | C95: 6649 | D95: 5464 | E95: 6609
B96: Hero Motorcorp | C96: 5946 | D96: 6126 | E96: 6454
B97: Mahindra & Mahindra Ltd | C97: 30518 | D97: 32874 | E97: 36528
B99: EBIT
C100: 2025 | D100: 2026 | E100: 2027
B101: Eicher Motors | C101: 3982.7 | D101: 4640.9983 | E101: 5303.3701
B102: Bajaj Auto | C102: 9140 | D102: 11064.9 | E102: 12512
B103: TVS Motors | C103: 5529 | D103: 4822.7 | E103: 5834.2
B104: Hero Motorcorp | C104: 4964 | D104: 5760.7 | E104: 6438.2
B105: Mahindra & Mahindra Ltd | C105: 24445 | D105: 15835.4 | E105: 18100
B107: PBT
C108: 2025 | D108: 2026 | E108: 2027
B109: Eicher Motors | C109: 5933.07 | D109: 6447.0168 | E109: 7266.7192
B110: Bajaj Auto | C110: 10224 | D110: 12550 | E110: 14152
B111: TVS Motors | C111: 3535 | D111: 4301 | E111: 5298
B112: Hero Motorcorp | C112: 5934 | D112: 6542 | E112: 7054
B113: Mahindra & Mahindra Ltd | C113: 19080 | D113: 19354 | E113: 22124
B115: PAT
C116: 2025 | D116: 2026 | E116: 2027
B117: Eicher Motors | C117: 4734.44 | D117: 5286.7843 | E117: 5940.9713
B118: Bajaj Auto | C118: 7325 | D118: 9626 | E118: 10750
B119: TVS Motors | C119: 2380 | D119: 3421 | E119: 4236
B120: Hero Motorcorp | C120: 4376 | D120: 5174.5 | E120: 5759.9
B121: Mahindra & Mahindra Ltd | C121: 14073 | D121: 16056 | E121: 18288

Sheet Relative_Val
B2: In INR Crores
D3: Market Data | J3: Financials | AC3: Multiples
J4: 2025 | K4: =J4+1 -> 2026 | L4: =K4+1 -> 2027 | M4: =J4 -> 2025 | N4: =M4+1 -> 2026 | O4: =N4+1 -> 2027 | P4: =J4 -> 2025 | Q4: =P4+1 -> 2026 | R4: =Q4+1 -> 2027 | S4: =J4 -> 2025 | T4: =S4+1 -> 2026 | U4: =T4+1 -> 2027 | V4: =J4 -> 2025 | W4: =V4+1 -> 2026 | X4: =W4+1 -> 2027 | Y4: =J4 -> 2025 | Z4: =Y4+1 -> 2026 | AA4: =Z4+1 -> 2027 | AC4: =J4 -> 2025 | AD4: =AC4+1 -> 2026 | AE4: =AD4+1 -> 2027 | AF4: =J4 -> 2025 | AG4: =AF4+1 -> 2026 | AH4: =AG4+1 -> 2027 | AI4: =J4 -> 2025 | AJ4: =AI4+1 -> 2026 | AK4: =AJ4+1 -> 2027
B5: Relative Valuation | D5: Ticker | E5: Share Price | F5: Market Cap | G5: Debt | H5: Cash | I5: Enterprise Value | J5: Sales | K5: Sales | L5: Sales | M5: Sales Growth (%) | N5: Sales Growth (%) | O5: Sales Growth (%) | P5: EBITDA | Q5: EBITDA | R5: EBITDA | S5: EBITDA Margins (%) | T5: EBITDA Margins (%) | U5: EBITDA Margins (%) | V5: PAT | W5: PAT | X5: PAT | Y5: PAT Margins (%) | Z5: PAT Margins (%) | AA5: PAT Margins (%) | AC5: EV/Sales | AD5: EV/Sales | AE5: EV/Sales | AF5: EV/EBITDA | AG5: EV/EBITDA | AH5: EV/EBITDA | AI5: PE | AJ5: PE | AK5: PE
B7: Eicher Motors | D7: NSE: EICHERMOT | E7: 7217 | F7: 197993 | G7: 446 | H7: 263 | I7: =F7+G7-H7 -> 198176 | J7: =Benchmarking!C85 -> 18870.35 | K7: =Benchmarking!D85 -> 21700.902 | L7: =Benchmarking!E85 -> 24793.281 | M7: 0.141 | N7: =K7/J7-1 -> 0.15 | O7: =L7/K7-1 -> 0.1425 | P7: =Benchmarking!C93 -> 4712.03 | Q7: =Benchmarking!D93 -> 5490.3283 | R7: =Benchmarking!E93 -> 6272.7001 | S7: =P7/J7 -> 0.24970549 | T7: =Q7/K7 -> 0.253 | U7: =R7/L7 -> 0.253 | V7: =Benchmarking!C117 -> 4734.44 | W7: =Benchmarking!D117 -> 5286.7843 | X7: =Benchmarking!E117 -> 5940.9713 | Y7: =V7/J7 -> 0.25089307 | Z7: =W7/K7 -> 0.24362048 | AA7: =X7/L7 -> 0.23962021 | AC7: =$I7/J7 -> 10.501978 | AD7: =$I7/K7 -> 9.1321548 | AE7: =$I7/L7 -> 7.9931333 | AF7: =$I7/P7 -> 42.057457 | AG7: =$I7/Q7 -> 36.095473 | AH7: =$I7/R7 -> 31.593412 | AI7: =$F7/V7 -> 41.819729 | AJ7: =$F7/W7 -> 37.450554 | AK7: =$F7/X7 -> 33.326705
B8: Bajaj Auto | D8: NSE: BAJAJ-AUTO | E8: 9048 | F8: 252730 | G8: 19693 | H8: 2848 | I8: =F8+G8-H8 -> 269575 | J8: =Benchmarking!C86 -> 50995 | K8: =Benchmarking!D86 -> 60148 | L8: =Benchmarking!E86 -> 67449 | M8: =Benchmarking!G23 -> 0.1365 | N8: =K8/J8-1 -> 0.17948819 | O8: =L8/K8-1 -> 0.12138392 | P8: =Benchmarking!C94 -> 10468 | Q8: =Benchmarking!D94 -> 12034 | R8: =Benchmarking!E94 -> 13765 | S8: =P8/J8 -> 0.20527503 | T8: =Q8/K8 -> 0.20007315 | U8: =R8/L8 -> 0.20408012 | V8: =Benchmarking!C118 -> 7325 | W8: =Benchmarking!D118 -> 9626 | X8: =Benchmarking!E118 -> 10750 | Y8: =V8/J8 -> 0.14364153 | Z8: =W8/K8 -> 0.16003857 | AA8: =X8/L8 -> 0.15937968 | AC8: =$I8/J8 -> 5.2863026 | AD8: =$I8/K8 -> 4.4818614 | AE8: =$I8/L8 -> 3.9967235 | AF8: =$I8/P8 -> 25.752293 | AG8: =$I8/Q8 -> 22.401114 | AH8: =$I8/R8 -> 19.58409 | AI8: =$F8/V8 -> 34.502389 | AJ8: =$F8/W8 -> 26.254935 | AK8: =$F8/X8 -> 23.509767
B9: TVS Motor Co. | D9: NSE: TVSMOTOR | E9: 3448 | F9: 163936 | G9: 16862 | H9: 4386 | I9: =F9+G9-H9 -> 176412 | J9: =Benchmarking!C87 -> 44089 | K9: =Benchmarking!D87 -> 40595 | L9: =Benchmarking!E87 -> 49467 | M9: =Benchmarking!G24 -> 0.1263 | N9: =K9/J9-1 -> -0.079248792 | O9: =L9/K9-1 -> 0.21854908 | P9: =Benchmarking!C95 -> 6649 | Q9: =Benchmarking!D95 -> 5464 | R9: =Benchmarking!E95 -> 6609 | S9: =P9/J9 -> 0.15080859 | T9: =Q9/K9 -> 0.13459786 | U9: =R9/L9 -> 0.13360422 | V9: =Benchmarking!C119 -> 2380 | W9: =Benchmarking!D119 -> 3421 | X9: =Benchmarking!E119 -> 4236 | Y9: =V9/J9 -> 0.053981719 | Z9: =W9/K9 -> 0.084271462 | AA9: =X9/L9 -> 0.085632846 | AC9: =$I9/J9 -> 4.0012702 | AD9: =$I9/K9 -> 4.3456583 | AE9: =$I9/L9 -> 3.5662563 | AF9: =$I9/P9 -> 26.53211 | AG9: =$I9/Q9 -> 32.286237 | AH9: =$I9/R9 -> 26.692692 | AI9: =$F9/V9 -> 68.880672 | AJ9: =$F9/W9 -> 47.920491 | AK9: =$F9/X9 -> 38.700661
B10: Hero Motocorp | D10: NSE: HEROMOTOCO | E10: 6082 | F10: 121663 | G10: 718 | H10: 574 | I10: =F10+G10-H10 -> 121807 | J10: =Benchmarking!C88 -> 40923 | K10: =Benchmarking!D88 -> 43001 | L10: =Benchmarking!E88 -> 45740 | M10: =Benchmarking!G25 -> 0.083 | N10: =K10/J10-1 -> 0.050778291 | O10: =L10/K10-1 -> 0.063696193 | P10: =Benchmarking!C96 -> 5946 | Q10: =Benchmarking!D96 -> 6126 | R10: =Benchmarking!E96 -> 6454 | S10: =P10/J10 -> 0.14529727 | T10: =Q10/K10 -> 0.1424618 | U10: =R10/L10 -> 0.14110188 | V10: =Benchmarking!C120 -> 4376 | W10: =Benchmarking!D120 -> 5174.5 | X10: =Benchmarking!E120 -> 5759.9 | Y10: =V10/J10 -> 0.10693253 | Z10: =W10/K10 -> 0.12033441 | AA10: =X10/L10 -> 0.12592698 | AC10: =$I10/J10 -> 2.9764924 | AD10: =$I10/K10 -> 2.8326551 | AE10: =$I10/L10 -> 2.6630302 | AF10: =$I10/P10 -> 20.485536 | AG10: =$I10/Q10 -> 19.883611 | AH10: =$I10/R10 -> 18.873102 | AI10: =$F10/V10 -> 27.802331 | AJ10: =$F10/W10 -> 23.51203 | AK10: =$F10/X10 -> 21.122415
B11: M & M | D11: NSE: M&M | E11: 3669 | F11: 456467 | G11: 126709 | H11: 20615 | I11: =F11+G11-H11 -> 562561 | J11: =Benchmarking!C89 -> 159211 | K11: =Benchmarking!D89 -> 180172 | L11: =Benchmarking!E89 -> 199947 | M11: =Benchmarking!G26 -> 0.14475698 | N11: =K11/J11-1 -> 0.13165548 | O11: =L11/K11-1 -> 0.10975623 | P11: =Benchmarking!C97 -> 30518 | Q11: =Benchmarking!D97 -> 32874 | R11: =Benchmarking!E97 -> 36528 | S11: =P11/J11 -> 0.19168274 | T11: =Q11/K11 -> 0.18245898 | U11: =R11/L11 -> 0.18268841 | V11: =Benchmarking!C121 -> 14073 | W11: =Benchmarking!D121 -> 16056 | X11: =Benchmarking!E121 -> 18288 | Y11: =V11/J11 -> 0.088392134 | Z11: =W11/K11 -> 0.089114846 | AA11: =X11/L11 -> 0.091464238 | AC11: =$I11/J11 -> 3.5334305 | AD11: =$I11/K11 -> 3.1223553 | AE11: =$I11/L11 -> 2.8135506 | AF11: =$I11/P11 -> 18.433744 | AG11: =$I11/Q11 -> 17.112642 | AH11: =$I11/R11 -> 15.400816 | AI11: =$F11/V11 -> 32.435657 | AJ11: =$F11/W11 -> 28.429684 | AK11: =$F11/X11 -> 24.959919
B13: High | AC13: =MAX(AC8:AC11) -> 5.2863026 | AD13: =MAX(AD8:AD11) -> 4.4818614 | AE13: =MAX(AE8:AE11) -> 3.9967235 | AF13: =MAX(AF8:AF11) -> 26.53211 | AG13: =MAX(AG8:AG11) -> 32.286237 | AH13: =MAX(AH8:AH11) -> 26.692692 | AI13: =MAX(AI8:AI11) -> 68.880672 | AJ13: =MAX(AJ8:AJ11) -> 47.920491 | AK13: =MAX(AK8:AK11) -> 38.700661 | AM13: EV/Sales
B14: 75th Percentile | AC14: =QUARTILE(AC8:AC11,3) -> 4.3225283 | AD14: =QUARTILE(AD8:AD11,3) -> 4.3797091 | AE14: =QUARTILE(AE8:AE11,3) -> 3.6738731 | AF14: =QUARTILE(AF8:AF11,3) -> 25.947247 | AG14: =QUARTILE(AG8:AG11,3) -> 24.872394 | AH14: =QUARTILE(AH8:AH11,3) -> 21.361241 | AI14: =QUARTILE(AI8:AI11,3) -> 43.09696 | AJ14: =QUARTILE(AJ8:AJ11,3) -> 33.302385 | AK14: =QUARTILE(AK8:AK11,3) -> 28.395105 | AM14: EV/EBITDA
B15: Average | AC15: =AVERAGE(AC8:AC11) -> 3.9493739 | AD15: =AVERAGE(AD8:AD11) -> 3.6956325 | AE15: =AVERAGE(AE8:AE11) -> 3.2598901 | AF15: =AVERAGE(AF8:AF11) -> 22.800921 | AG15: =AVERAGE(AG8:AG11) -> 22.920901 | AH15: =AVERAGE(AH8:AH11) -> 20.137675 | AI15: =AVERAGE(AI8:AI11) -> 40.905262 | AJ15: =AVERAGE(AJ8:AJ11) -> 31.529285 | AK15: =AVERAGE(AK8:AK11) -> 27.073191 | AM15: Price/Earnings
B16: Median | AC16: =MEDIAN(AC8:AC11) -> 3.7673503 | AD16: =MEDIAN(AD8:AD11) -> 3.7340068 | AE16: =MEDIAN(AE8:AE11) -> 3.1899034 | AF16: =MEDIAN(AF8:AF11) -> 23.118915 | AG16: =MEDIAN(AG8:AG11) -> 21.142362 | AH16: =MEDIAN(AH8:AH11) -> 19.228596 | AI16: =MEDIAN(AI8:AI11) -> 33.469023 | AJ16: =MEDIAN(AJ8:AJ11) -> 27.342309 | AK16: =MEDIAN(AK8:AK11) -> 24.234843
B17: 25th Percentile | AC17: =QUARTILE(AC8:AC11,1) -> 3.394196 | AD17: =QUARTILE(AD8:AD11,1) -> 3.0499302 | AE17: =QUARTILE(AE8:AE11,1) -> 2.7759205 | AF17: =QUARTILE(AF8:AF11,1) -> 19.972588 | AG17: =QUARTILE(AG8:AG11,1) -> 19.190869 | AH17: =QUARTILE(AH8:AH11,1) -> 18.00503 | AI17: =QUARTILE(AI8:AI11,1) -> 31.277325 | AJ17: =QUARTILE(AJ8:AJ11,1) -> 25.569208 | AK17: =QUARTILE(AK8:AK11,1) -> 22.912929
B18: Low | AC18: =MIN(AC8:AC11) -> 2.9764924 | AD18: =MIN(AD8:AD11) -> 2.8326551 | AE18: =MIN(AE8:AE11) -> 2.6630302 | AF18: =MIN(AF8:AF11) -> 18.433744 | AG18: =MIN(AG8:AG11) -> 17.112642 | AH18: =MIN(AH8:AH11) -> 15.400816 | AI18: =MIN(AI8:AI11) -> 27.802331 | AJ18: =MIN(AJ8:AJ11) -> 23.51203 | AK18: =MIN(AK8:AK11) -> 21.122415
B20: Relative Valuation
B21: Sales | D21: =J7 -> 18870.35
B22: EBITDA | D22: =P7 -> 4712.03
B23: Earnings | D23: =V7 -> 4734.44
B24: Valuation Multiple | D24: EV/EBITDA
B25: =D24 -> EV/EBITDA | D25: =IF(B25=AM13,AC16,IF(B25=AM14,AF16,AI16)) -> 23.118915
B26: =IF(D24=AM15,"Equity Value","Enterprise Value") -> Enterprise Value | D26: =IF(D24=AM13,D25*D21,IF(D24=AM14,D25*D22,D25*D23)) -> 108937.02
B27: =DCFVal!B41 -> Less : Debt | D27: =IF($D$24=$AM$15,0,DCFVal!C41) -> -266.47
B28: =DCFVal!B42 -> Add : Cash | D28: =IF($D$24=$AM$15,0,DCFVal!C42) -> 267.05
B29: =DCFVal!B43 -> Less : Minority Interest | D29: =IF($D$24=$AM$15,0,DCFVal!C43) -> 0
B30: =DCFVal!B44 -> Add : Non Operating Asset | D30: =IF($D$24=$AM$15,0,DCFVal!C44) -> 16013.75
B31: =DCFVal!B45 -> Equity Value | D31: =SUM(D26:D30) -> 124951.35
B32: =DCFVal!B46 -> Less : Value of Options | D32: =IF($D$24=$AM$15,0,DCFVal!C46) -> -202.92815
B33: =DCFVal!B47 -> Equity Value for Shareholders | D33: =SUM(D31:D32) -> 124748.42

Sheet Workings>

Sheet Assumptions Working
A2: # | B2: Revenue Growth
B4: Company Historical Growth
L5: CAGR
B6: ='ConsolidatedP&L'!B2 -> Particulars | D6: ='ConsolidatedP&L'!C2 -> 2019 | E6: ='ConsolidatedP&L'!D2 -> 2020 | F6: ='ConsolidatedP&L'!E2 -> 2021 | G6: ='ConsolidatedP&L'!F2 -> 2022 | H6: ='ConsolidatedP&L'!G2 -> 2023 | I6: ='ConsolidatedP&L'!H2 -> 2024 | J6: ='ConsolidatedP&L'!I2 -> 2025 | L6: 3 Years | M6: 5 Years
B7: ='ConsolidatedP&L'!B6 -> Revenue from operations | D7: ='ConsolidatedP&L'!C6 -> 9797.06 | E7: ='ConsolidatedP&L'!D6 -> 9153.58 | F7: ='ConsolidatedP&L'!E6 -> 8720.35 | G7: ='ConsolidatedP&L'!F6 -> 10297.83 | H7: ='ConsolidatedP&L'!G6 -> 14442.18 | I7: ='ConsolidatedP&L'!H6 -> 16535.78 | J7: ='ConsolidatedP&L'!I6 -> 18870.35 | L7: =_xlfn.RRI(3,G7,J7) -> 0.22370879 | M7: =_xlfn.RRI(5,E7,J7) -> 0.15568052
B8: Sales Growth | D8: ='ConsolidatedP&L'!C8 -> 0.062673143 | E8: ='ConsolidatedP&L'!D8 -> -0.065680929 | F8: ='ConsolidatedP&L'!E8 -> -0.047329023 | G8: ='ConsolidatedP&L'!F8 -> 0.18089641 | H8: ='ConsolidatedP&L'!G8 -> 0.40244887 | I8: ='ConsolidatedP&L'!H8 -> 0.14496426 | J8: ='ConsolidatedP&L'!I8 -> 0.14118294
K10: 21915 | L10: =K10/J7-1 -> 0.16134571
V18: Revenue is expected to grow by 16.1% in FY26
W19: Q2FY26 | X19: Q3FY26 | Y19: FY26 | Z19: FY27
W20: Crore Rs | X20: Crore Rs | Y20: Crore Rs | Z20: Crore Rs
V21: Avg Estimate | W21: 6064.7 | X21: 5576.6 | Y21: 21915.6 | Z21: 24581.9 | AA21: =Z21/Y21-1 -> 0.12166219
V22: High Estimate | W22: 6257.9 | X22: 5958 | Y22: 23453.6 | Z22: 26853.2 | AA22: =Z22/Y22-1 -> 0.14495003
V23: Low Estimate | W23: 5663.1 | X23: 5197.9 | Y23: 20820.1 | Z23: 21976.6 | AA23: =Z23/Y23-1 -> 0.055547284
V24: No. of Analysts | W24: 16 | X24: 3 | Y24: 27 | Z24: 27
A42: # | B42: Gross Margin
B44: Company Historical Margin
B46: ='ConsolidatedP&L'!B2 -> Particulars | C46: ='ConsolidatedP&L'!C2 -> 2019 | D46: ='ConsolidatedP&L'!C2 -> 2019 | E46: ='ConsolidatedP&L'!D2 -> 2020 | F46: ='ConsolidatedP&L'!E2 -> 2021 | G46: ='ConsolidatedP&L'!F2 -> 2022 | H46: ='ConsolidatedP&L'!G2 -> 2023 | I46: ='ConsolidatedP&L'!H2 -> 2024 | J46: ='ConsolidatedP&L'!I2 -> 2025 | L46: Median | M46: Average
B47: Gross Margins | D47: ='ConsolidatedP&L'!C19 -> 0.48378595 | E47: ='ConsolidatedP&L'!D19 -> 0.45420917 | F47: ='ConsolidatedP&L'!E19 -> 0.41375404 | G47: ='ConsolidatedP&L'!F19 -> 0.4216568 | H47: ='ConsolidatedP&L'!G19 -> 0.43139471 | I47: ='ConsolidatedP&L'!H19 -> 0.45689589 | J47: ='ConsolidatedP&L'!I19 -> 0.45432491 | L47: =MEDIAN(D47:J47) -> 0.45420917 | M47: =AVERAGE(D47:J47) -> 0.44514592
B50: Sector Data - Damodaran
B52: Just India
B53: Auto & Truck | D53: 0.3915
B55: All Emerging Markets
B56: Auto & Truck | D56: 0.2105
B58: Global
B59: Auto & Truck | D59: 0.1834
B62: Mangement Guidance
N75: Source | O75: BOB CAPITAL RESEARCH REPORT
O76: https://www.barodaetrade.com/Reports/EicherMotors-Q3FY25ResultReview11Feb25-Research.pdf
B123: Steel Market in India
B147: Source | C147: https://www.maximizemarketresearch.com/market-report/global-automotive-steel-market/22955/
B150: Street Estimates
B152: Prabhudas Liladher
D153: FY26 | E153: FY27
B154: Gross Margin (%) | D154: 46.7 | E154: 46.7
B156: ICICI Securities
B157: Gross Margin (%) | D157: 38.4 | E157: 38.9
B159: Median GM | D159: =MEDIAN(D154,D157) -> 42.55 | E159: =MEDIAN(E154,E157) -> 42.8
A181: # | B181: SG&A Expenses
L182: CAGR
B183: ='ConsolidatedP&L'!B2 -> Particulars | D183: ='ConsolidatedP&L'!C2 -> 2019 | E183: ='ConsolidatedP&L'!D2 -> 2020 | F183: ='ConsolidatedP&L'!E2 -> 2021 | G183: ='ConsolidatedP&L'!F2 -> 2022 | H183: ='ConsolidatedP&L'!G2 -> 2023 | I183: ='ConsolidatedP&L'!H2 -> 2024 | J183: ='ConsolidatedP&L'!I2 -> 2025 | L183: 3 Years | M183: 5 Years
B184: ='ConsolidatedP&L'!B6 -> Revenue from operations | D184: ='ConsolidatedP&L'!C6 -> 9797.06 | E184: ='ConsolidatedP&L'!D6 -> 9153.58 | F184: ='ConsolidatedP&L'!E6 -> 8720.35 | G184: ='ConsolidatedP&L'!F6 -> 10297.83 | H184: ='ConsolidatedP&L'!G6 -> 14442.18 | I184: ='ConsolidatedP&L'!H6 -> 16535.78 | J184: ='ConsolidatedP&L'!I6 -> 18870.35 | L184: =_xlfn.RRI(3,G184,J184) -> 0.22370879 | M184: =_xlfn.RRI(5,E184,J184) -> 0.15568052
B185: Growth YoY % | D185: ='ConsolidatedP&L'!C8 -> 0.062673143 | E185: ='ConsolidatedP&L'!D8 -> -0.065680929 | F185: ='ConsolidatedP&L'!E8 -> -0.047329023 | G185: ='ConsolidatedP&L'!F8 -> 0.18089641 | H185: ='ConsolidatedP&L'!G8 -> 0.40244887 | I185: ='ConsolidatedP&L'!H8 -> 0.14496426 | J185: ='ConsolidatedP&L'!I8 -> 0.14118294
B187: SG&A Expenses | D187: ='ConsolidatedP&L'!C31*-1 -> 1836.57 | E187: ='ConsolidatedP&L'!D31*-1 -> 1977.29 | F187: ='ConsolidatedP&L'!E31*-1 -> 1826.83 | G187: ='ConsolidatedP&L'!F31*-1 -> 2169.9 | H187: ='ConsolidatedP&L'!G31*-1 -> 2786.7 | I187: ='ConsolidatedP&L'!H31*-1 -> 3228.22 | J187: ='ConsolidatedP&L'!I31*-1 -> 3861.24 | L187: =_xlfn.RRI(3,G187,J187) -> 0.21179464 | M187: =_xlfn.RRI(5,E187,J187) -> 0.14322387
B188: Growth YoY % | E188: =E187/D187-1 -> 0.076621093 | F188: =F187/E187-1 -> -0.076094048 | G188: =G187/F187-1 -> 0.18779525 | H188: =H187/G187-1 -> 0.28425273 | I188: =I187/H187-1 -> 0.1584383 | J188: =J187/I187-1 -> 0.19608949
B190: Historical SG&A Analysis
B192: Profit and Loss | D192: 2019 | E192: =D192+1 -> 2020 | F192: =E192+1 -> 2021 | G192: =F192+1 -> 2022 | H192: =G192+1 -> 2023 | I192: =H192+1 -> 2024 | J192: =I192+1 -> 2025
B193: Revenue from operations | D193: 9797.06 | E193: 9153.58 | F193: 8720.35 | G193: 10297.83 | H193: 14442.18 | I193: 16535.78 | J193: 18870.35
B195: Employee Benefits Expense | D195: 702.44 | E195: 795.78 | F195: 843.23 | G195: 821.02 | H195: 1001.93 | I195: 1235.69 | J195: 1391.23
B196: Consumption of Stores and machinery spares (including loose tools and packing material) | D196: 169.63 | E196: 156.38 | F196: 139.51 | G196: 198.56 | H196: 262.25 | I196: 239.14 | J196: 286.56
B197: Power and fuel | D197: 66.96 | E197: 62.86 | F197: 52.98 | G197: 55.78 | H197: 72.97 | I197: 80.61 | J197: 89.53
B198: Insurance | D198: 13.24 | E198: 17.5 | F198: 25.94 | G198: 31.83 | H198: 37.58 | I198: 43.18 | J198: 51.5
B199: Repairs and maintenance:
B200: Buildings | D200: 3.48 | E200: 3.57 | F200: 3.77 | G200: 3.28 | H200: 6.29 | I200: 7.08 | J200: 6.43
B201: Plant and equipment | D201: 44.94 | E201: 42.88 | F201: 43.83 | G201: 48.48 | H201: 44.09 | I201: 52.71 | J201: 50.63
B202: Others | D202: 45.44 | E202: 53.75 | F202: 63.74 | G202: 82.09 | H202: 84.58 | I202: 95.43 | J202: 110.15
B203: Rates and taxes | D203: 6.07 | E203: 3.98 | F203: 5.12 | G203: 6.26 | H203: 5.99 | I203: 39.01 | J203: 17.22
B204: Advertisement | D204: 30.36 | E204: 21.76 | F204: 18.2 | G204: 30.82 | H204: 42.21 | I204: 55.17 | J204: 108.35
B205: Freight and handling charges | D205: 143.61 | E205: 144.91 | F205: 121.1 | G205: 180.97 | H205: 272.83 | I205: 265.57 | J205: 330.64
B206: Provision for warranty and onerous contract | D206: 43.33 | E206: 55.63 | F206: 53.87 | G206: 118.56 | H206: 145.47 | I206: 103.86 | J206: 88.13
B207: Selling and distribution expenses | D207: 196.01 | E207: 244.73 | F207: 180.93 | G207: 284.69 | H207: 426.39 | I207: 546.2 | J207: 760.88
B208: Expense related to short term leases | D208: 48.69 | E208: 14.37 | F208: 14.45 | G208: 28.11 | H208: 46.11 | I208: 68.03 | J208: 76.64
B209: Legal and professional charges | D209: 58.46 | E209: 60.18 | F209: 59.61 | G209: 72.05 | H209: 62.52 | I209: 90.02 | J209: 122.61
B210: Travelling expenses | D210: 93.57 | E210: 92.29 | F210: 33 | G210: 50.18 | H210: 110.66 | I210: 137.33 | J210: 163.13
B211: Development expenses (Revenue R&D expensed) | D211: 13.59 | E211: 11.12 | F211: 8.93 | G211: 12.04 | H211: 14.82 | I211: 36.54 | J211: 37.08
... B215: Miscellaneous expenses | D215: 95.62 | E215: 119.71 | F215: 73.5 | G215: 85.75 | H215: 95.31 | I215: 76.91 | J215: 92.42
B216: Total SG&A Expenses | D216: =SUM(D195:D198,D200:D215) -> 1822.45 | E216: =SUM(E195:E198,E200:E215) -> 1959.33 | F216: =SUM(F195:F198,F200:F215) -> 1818.35 | G216: =SUM(G195:G198,G200:G215) -> 2169.9 | H216: =SUM(H195:H198,H200:H215) -> 2786.7 | I216: =SUM(I195:I198,I200:I215) -> 3228.22 | J216: =SUM(J195:J198,J200:J215) -> 3861.24
L217: Median | M217: Average
B218: SG&A % Revenue | D218: =D216/D193 -> 0.18602009 | E218: =E216/E193 -> 0.21405068 | F218: =F216/F193 -> 0.20851801 | G218: =G216/G193 -> 0.2107143 | H218: =H216/H193 -> 0.19295563 | I218: =I216/I193 -> 0.19522635 | J218: =J216/J193 -> 0.20461942 | L218: =MEDIAN(D218:J218) -> 0.20461942 | M218: =AVERAGE(D218:J218) -> 0.20172921
B220: Profit and Loss | D220: 2019 | E220: =D220+1 -> 2020 | F220: =E220+1 -> 2021 | G220: =F220+1 -> 2022 | H220: =G220+1 -> 2023 | I220: =H220+1 -> 2024 | J220: =I220+1 -> 2025 | L220: Median | M220: Average
B221: Employee Benefits Expense | D221: =D195/D$216 -> 0.38543719 | E221: =E195/E$216 -> 0.40614904 | F221: =F195/F$216 -> 0.4637336 | G221: =G195/G$216 -> 0.37836767 | H221: =H195/H$216 -> 0.35953996 | I221: =I195/I$216 -> 0.38277751 | J221: =J195/J$216 -> 0.36030653 | L221: =MEDIAN(D221:J221) -> 0.38277751 | M221: =AVERAGE(D221:J221) -> 0.39090164
B222: Consumption of Stores and machinery spares (including loose tools and packing material) | D222: =D196/D$216 -> 0.093077999 | E222: =E196/E$216 -> 0.079812997 | F222: =F196/F$216 -> 0.076723403 | G222: =G196/G$216 -> 0.091506521 | H222: =H196/H$216 -> 0.094107726 | I222: =I196/I$216 -> 0.074077975 | J222: =J196/J$216 -> 0.074214501 | L222: =MEDIAN(D222:J222) -> 0.079812997 | M222: =AVERAGE(D222:J222) -> 0.08336016
